Workbook

Sheet Dashboard
B2: DASHBOARD COMERCIAL INMOBILIARIO - CSO ( Chief Sales Manager)
B3: Control de ventas, embudo, fuentes, visitas, separaciones, facturación y proyecciones. Edita las fechas para analizar cualquier semana o periodo.
B5: Fecha inicio | C5: 45930 | D5: Fecha fin | E5: 46295 | L5: Fecha actual | O5: =TODAY() -> 46294
B7: 1. RESULTADOS COMERCIALES
B9: Meta vs Resultados | F9: Unidades
B10: Meta | D10: =SUMPRODUCT(Meta!$B$5:$B1136*IF(EOMONTH(Meta!$A$5:$A1136,0)<$C$5,0,IF(Meta!$A$5:$A1136>$E$5,0,(IF(EOMONTH(Meta!$A$5:$A1136,0)<$E$5,EOMONTH(Meta!$A$5:$A1136,0),$E$5)-IF(Meta!$A$5:$A1136>$C$5,Meta!$A$5:$A1136,$C$5)+1)/DAY(EOMONTH(Meta!$A$5:$A1136,0))))) -> 3600000 | F10: =SUMPRODUCT(Meta!$C$5:$C1136*IF(EOMONTH(Meta!$A$5:$A1136,0)<$C$5,0,IF(Meta!$A$5:$A1136>$E$5,0,(IF(EOMONTH(Meta!$A$5:$A1136,0)<$E$5,EOMONTH(Meta!$A$5:$A1136,0),$E$5)-IF(Meta!$A$5:$A1136>$C$5,Meta!$A$5:$A1136,$C$5)+1)/DAY(EOMONTH(Meta!$A$5:$A1136,0))))) -> 90
B11: Ventas Reales | D11: =SUMIFS(Data_Ventas!$N$2:$N1136,Data_Ventas!$A$2:$A1136,">="&$C$5,Data_Ventas!$A$2:$A1136,"<="&$E$5,Data_Ventas!$H$2:$H1136,"Venta") -> 742424.5 | F11: =COUNTIFS(Data_Ventas!$A$2:$A1136,">="&$C$5,Data_Ventas!$A$2:$A1136,"<="&$E$5,Data_Ventas!$H$2:$H1136,"Venta") -> 14
B12: Separaciones | D12: =SUMIFS(Data_Ventas!$N$2:$N1136,Data_Ventas!$A$2:$A1136,">="&$C$5,Data_Ventas!$A$2:$A1136,"<="&$E$5,Data_Ventas!$H$2:$H1136,"Separado") -> 0 | F12: =COUNTIFS(Data_Ventas!$A$15:$A1136,">="&$C$5,Data_Ventas!$A$15:$A1136,"<="&$E$5,Data_Ventas!$H$15:$H1136,"Separado") -> 0
B13: Bolsa cotizaciones | D13: =SUMIFS(Data_Cotiz!$N$2:$N1136,Data_Cotiz!$A$2:$A1136,">="&$C$5,Data_Cotiz!$A$2:$A1136,"<="&$E$5,Data_Cotiz!$H$2:$H1136,"En Cotizacion") -> 0 | F13: =COUNTIFS(Data_Ventas!$A$15:$A1136,">="&$C$5,Data_Ventas!$A$15:$A1136,"<="&$E$5,Data_Ventas!$H$15:$H1136,"En cotizacion") -> 0
B14: Pipeline Ponderado | D14: =SUMIFS(Data_Cotiz!$N$2:$N1136,Data_Cotiz!$A$2:$A1136,">="&$C$5,Data_Cotiz!$A$2:$A1136,"<="&$E$5,Data_Cotiz!$H$2:$H1136,"Listo para comprar") -> 0 | F14: =COUNTIFS(Data_Ventas!$A$15:$A1136,">="&$C$5,Data_Ventas!$A$15:$A1136,"<="&$E$5,Data_Ventas!$H$15:$H1136,"Listo para comprar") -> 0
B15: Forecast cierre | D15: =D11+D12+D14 -> 742424.5 | F15: =F11+F12+F14 -> 14
B16: Gap | D16: =D15-D10 -> -2857575.5
B18: cumplimiento de ventas | D18: =$D$11/$D$10 -> 0.20622903
B19: Indice Cumplimiento ventas | D19: =($D$11/$D$10)*100 -> 20.622903
B21: Facturacion Acumulada
B22: Periodo | D22: Facturación Acum.
B23: Semana actual | D23: =SUMIFS(Data_Ventas!$N$2:$N1136,Data_Ventas!$A$2:$A1136,">="&($E$5-WEEKDAY($E$5,2)+1),Data_Ventas!$A$2:$A1136,"<="&($E$5-WEEKDAY($E$5,2)+7)) -> 0
B24: Mes actual | D24: =SUMIFS(Data_Ventas!$N$2:$N1136,Data_Ventas!$A$2:$A1136,">="&DATE(YEAR($E$5),MONTH($E$5),1),Data_Ventas!$A$2:$A1136,"<="&EOMONTH($E$5,0)) -> 80000
B25: Trimestre actual | D25: =SUMIFS(Data_Ventas!$N$2:$N1136,Data_Ventas!$A$2:$A1136,">="&DATE(YEAR($E$5),3*INT((MONTH($E$5)-1)/3)+1,1),Data_Ventas!$A$2:$A1136,"<="&EOMONTH(DATE(YEAR($E$5),3*INT((MONTH($E$5)-1)/3)+1,1),2)) -> 247000
B26: Semestre actual | D26: =SUMIFS(Data_Ventas!$N$2:$N1136,Data_Ventas!$A$2:$A1136,">="&DATE(YEAR($E$5),IF(MONTH($E$5)<=6,1,7),1),Data_Ventas!$A$2:$A1136,"<="&EOMONTH(DATE(YEAR($E$5),IF(MONTH($E$5)<=6,1,7),1),5)) -> 247000
B27: Año actual | D27: =SUMIFS(Data_Ventas!$N$2:$N1136,Data_Ventas!$A$2:$A1136,">="&DATE(YEAR($E$5),1,1),Data_Ventas!$A$2:$A1136,"<="&DATE(YEAR($E$5),12,31)) -> 595160
B29: 2. MIX CONTADO/ FINANCIADO, CASH-IN, PRECIO, DESCUENTOS
B31: Tipo de compra
B32: Tipo | C32: Unidades | D32: % Unid | E32: Venta S/ | G32: ticket prom. | H32: % Vent
B33: Contado | C33: =COUNTIFS(Data_Ventas!$A$2:$A1136,">="&$C$5,Data_Ventas!$A$2:$A1136,"<="&$E$5,Data_Ventas!$H$2:$H1136,"Venta",Data_Ventas!$Q$2:$Q1136,B33) -> 2 | D33: =C33/$C$35 -> 0.14285714 | E33: =SUMIFS(Data_Ventas!$N$2:$N1136,Data_Ventas!$A$2:$A1136,">="&$C$5,Data_Ventas!$A$2:$A1136,"<="&$E$5,Data_Ventas!$H$2:$H1136,"Venta",Data_Ventas!$Q$2:$Q1136,B33) -> 103360 | G33: =IFERROR($E$33/$C$33,0) -> 51680 | H33: =E33/$E$35 -> 0.13921954
B34: Financiado | C34: =COUNTIFS(Data_Ventas!$A$2:$A1136,">="&$C$5,Data_Ventas!$A$2:$A1136,"<="&$E$5,Data_Ventas!$H$2:$H1136,"Venta",Data_Ventas!$Q$2:$Q1136,B34) -> 12 | D34: =C34/$C$35 -> 0.85714286 | E34: =SUMIFS(Data_Ventas!$N$2:$N1136,Data_Ventas!$A$2:$A1136,">="&$C$5,Data_Ventas!$A$2:$A1136,"<="&$E$5,Data_Ventas!$H$2:$H1136,"Venta",Data_Ventas!$Q$2:$Q1136,B34) -> 639064.5 | G34: =$E$34/$C$34 -> 53255.375 | H34: =E34/$E$35 -> 0.86078046
B35: Total | C35: =SUM(C33:C34) -> 14 | D35: =SUM(D33:D34) -> 1 | E35: =SUM(E33:E34) -> 742424.5 | H35: =SUM(H33:H34) -> 1
B37: Saldo financiado generado | D37: =E34-D41 -> 554014.5 | F37: =D37/D11 -> 0.74622335
B39: Cash-in comercial
B40: Tipo | D40: Cash-in venta | F40: Cash-in %
B41: Iniciales cobradas financiado | D41: =SUMIFS(Data_Ventas!$R$2:$R1136,Data_Ventas!$A$2:$A1136,">="&$C$5,Data_Ventas!$A$2:$A1136,"<="&$E$5,Data_Ventas!$H$2:$H1136,"Venta",Data_Ventas!$Q$2:$Q1136,B34) -> 85050 | F41: =D41/D11 -> 0.1145571
B42: ventas contados | D42: =SUMIFS(Data_Ventas!$R$2:$R1136,Data_Ventas!$A$2:$A1136,">="&$C$5,Data_Ventas!$A$2:$A1136,"<="&$E$5,Data_Ventas!$H$2:$H1136,"Venta",Data_Ventas!$Q$2:$Q1136,B33) -> 103360 | F42: =D42/D10 -> 0.028711111
B43: cash-in total | D43: =SUM(D41:D42) -> 188410
B45: cash-in por lote | D45: =$D$60/$C$35 -> 13457.857
B46: Inicial promedio S/. | D46: =$D$41/$C$34 -> 7087.5
B48: Descuentos
B49: Ventas a precios lista | D49: =SUMIFS(Data_Ventas!$M$2:$M1136,Data_Ventas!$A$2:$A1136,">="&$C$5,Data_Ventas!$A$2:$A1136,"<="&$E$5,Data_Ventas!$H$2:$H1136,"Venta") -> 742424.5
B50: Descuentos totales | D50: =SUMIFS(Data_Ventas!$O$2:$O1136,Data_Ventas!$A$2:$A1136,">="&$C$5,Data_Ventas!$A$2:$A1136,"<="&$E$5,Data_Ventas!$H$2:$H1136,"Venta") -> 0
B51: Descuento promedio | D51: =D50/F11 -> 0
B52: proteccion del precio % | D52: =D11/D49 -> 1
B54: Cancelaciones | F54: cant
B55: Cancelaciones S/. | D55: =SUMIFS(Data_Ventas!$N$2:$N1136,Data_Ventas!$A$2:$A1136,">="&$C$5,Data_Ventas!$A$2:$A1136,"<="&$E$5,Data_Ventas!$H$2:$H1136,"Venta Perdida") -> 40000 | F55: =COUNTIFS(Data_Ventas!$A$2:$A1136,">="&$C$5,Data_Ventas!$A$2:$A1136,"<="&$E$5,Data_Ventas!$H$2:$H1136,"Venta Perdida") -> 1
B56: Monto consolidado | D56: =$D$55+$D$11 -> 782424.5 | F56: =$F$11+$F$55 -> 15
B58: 3. CALIDAD FINANCIERA DE LA VENTA
B60: Cash-in total S/. | D60: =SUM(D41:E42) -> 188410
B61: Cash-in total % | D61: =D60/D11 -> 0.25377665
B62: Inicial promedio % | D62: =$D$41/$E$34 -> 0.13308516
B63: Descuentos % | D63: =$D$50/$D$49 -> 0
B64: Cancelación % | D64: =$D$55/$D$11 -> 0.053877532
B65: Consolidación % | D65: =$D$11/$D$56 -> 0.94887686
B66: FPD / mora temprana %
B67: Índice calidad venta | D67: =((MIN($D$61/Configuracion!$B$20,1)*30%)+(MIN($D$62/Configuracion!$B$21,1)*20%)+(MAX(0,1-($D$63/Configuracion!$B$22)*20%)*20%)+(IF($D$64=0,1,MIN(Configuracion!$B$23/$D$64,1))*20%)+(MIN($D$65/Configuracion!B24,1)*10%))*100 -> 83.60959
B69: Diagnóstico | D69: =IF(D67>=90,"🟢 Ventas de alta calidad",IF(D67>=80,"🟡 Ventas calidad aceptable, revisar",IF(D67>=70,"🟠 Venta calidad débil","🔴 Mala calidad comercial"))) -> 🟡 Ventas calidad aceptable, revisar
B71: SCORE CSO | D71: =($D$19*60%)+($D$67*40%) -> 45.817578
B73: 4. COSTOS Y EFICIENCIA COMERCIAL
B75: Gastos directos CSO | D75: 70000 | F75: =D75/$D$11 -> 0.094285682
B76: Gastos de Publicidad y Mkt CMO | D76: 30000 | F76: =D76/$D$11 -> 0.040408149
B77: Gastos totales | D77: =SUM(D75:D76) -> 100000
B79: Venta por S/1 de gasto CSO | D79: =D11/D75 -> 10.606064
B80: Cash-in por S/1 de gasto CSO | D80: =$D$60/$D$75 -> 2.6915714
H81: presupuesto consumido %
B82: CAC Marketing | D82: =D76/$F$11 -> 2142.8571 | H82: comisiones/ ventas
B83: CAC Comercial | D83: =D75/$F$11 -> 5000
B84: CAC Total | D84: =D82+D83 -> 7142.8571
B86: CONTRIBUCION COMERCIAL | D86: =D11-D75-D76 -> 642424.5
B87: ROI | D87: =($D$11-$D$77)/$D$77 -> 6.424245
B89: 5. INVENTARIO, ABSORCIÓN, AGING Y PRICING
B91: Inventario Total | D91: 181 | E91: 1
B92: Total Vendidos | D92: =F11 -> 14 | E92: =D92/$D$91 -> 0.077348066
B93: Inventario Falta vender | D93: =D91-D92 -> 167 | E93: =D93/$D$91 -> 0.92265193
B94: Venta mensual promedio (velocid) | D94: =D92/(DATEDIF(Configuracion!B8,O5,"m")) -> 1.2727273
B95: Absorcion mensual | D95: =D94/D92 -> 0.090909091 | E95: =D94/D91 -> 0.0070316424
B96: Meses de inventario | D96: =D93/D94 -> 131.21429
B97: Lotes >90 días
B98: Unidades sin visitas
B99: Lotes para próximo aumento precio
B101: 6. PRODUCTIVIDAD POR ASESOR
B103: Asesores activos
B104: Capacidad leads/mes
B105: Leads Asignados
B106: Uso capacidad
B107: % asesores en meta
B108: calidad promedio asesores
B109: venta por lead S/.
B110: tiempo resp. promedio min
B112: Puesto | C112: Vendedor | D112: Ventas | E112: Facturación
C113: TOTAL | D113: =SUM(D114:D116) -> 12 | E113: =SUM(E114:E116) -> 660424.5
B114: 1 | C114: {=INDEX(Asesores!$A$5:$A$14,MATCH(B114,Asesores!$AB$5:$AB$14,0))} -> Juan Carlos Paredes | D114: {=INDEX(Asesores!$M$5:$M$14,MATCH(B114,Asesores!$AB$5:$AB$14,0))} -> 6 | E114: {=INDEX(Asesores!$N$5:$N$14,MATCH(B114,Asesores!$AB$5:$AB$14,0))} -> 367200
B115: 2 | C115: {=INDEX(Asesores!$A$5:$A$14,MATCH(B115,Asesores!$AB$5:$AB$14,0))} -> JeanPaul Campos | D115: {=INDEX(Asesores!$M$5:$M$14,MATCH(B115,Asesores!$AB$5:$AB$14,0))} -> 3 | E115: {=INDEX(Asesores!$N$5:$N$14,MATCH(B115,Asesores!$AB$5:$AB$14,0))} -> 168224.5
B116: 3 | C116: {=INDEX(Asesores!$A$5:$A$14,MATCH(B116,Asesores!$AB$5:$AB$14,0))} -> Alfredo Caceda | D116: {=INDEX(Asesores!$M$5:$M$14,MATCH(B116,Asesores!$AB$5:$AB$14,0))} -> 3 | E116: {=INDEX(Asesores!$N$5:$N$14,MATCH(B116,Asesores!$AB$5:$AB$14,0))} -> 125000
B118: 7. EMBUDO Y CONVERSIONES
B120: Canales de Captación
B121: =Configuracion!E11 -> Publicidad pagada | D121: =COUNTIFS(Data_Ventas!$A$2:$A1136,">="&$C$5,Data_Ventas!$A$2:$A1136,"<="&$E$5,Data_Ventas!$F$2:$F1136,B121)+COUNTIFS(Data_Cotiz!$A$2:$A1136,">="&$C$5,Data_Cotiz!$A$2:$A1136,"<="&$E$5,Data_Cotiz!$F$2:$F1136,B121)+COUNTIFS(Data_Leads!$A$2:$A1136,">="&$C$5,Data_Leads!$A$2:$A1136,"<="&$E$5,Data_Leads!$J$2:$J1136,B121) -> 598
B122: =Configuracion!E12 -> Referido | D122: =COUNTIFS(Data_Ventas!$A$2:$A1136,">="&$C$5,Data_Ventas!$A$2:$A1136,"<="&$E$5,Data_Ventas!$F$2:$F1136,B122)+COUNTIFS(Data_Cotiz!$A$2:$A1136,">="&$C$5,Data_Cotiz!$A$2:$A1136,"<="&$E$5,Data_Cotiz!$F$2:$F1136,B122)+COUNTIFS(Data_Leads!$A$2:$A1136,">="&$C$5,Data_Leads!$A$2:$A1136,"<="&$E$5,Data_Leads!$J$2:$J1136,B122) -> 14
B123: =Configuracion!E13 -> Activación | D123: =COUNTIFS(Data_Ventas!$A$2:$A1136,">="&$C$5,Data_Ventas!$A$2:$A1136,"<="&$E$5,Data_Ventas!$F$2:$F1136,B123)+COUNTIFS(Data_Cotiz!$A$2:$A1136,">="&$C$5,Data_Cotiz!$A$2:$A1136,"<="&$E$5,Data_Cotiz!$F$2:$F1136,B123)+COUNTIFS(Data_Leads!$A$2:$A1136,">="&$C$5,Data_Leads!$A$2:$A1136,"<="&$E$5,Data_Leads!$J$2:$J1136,B123) -> 0
B124: =Configuracion!E14 -> Orgánico | D124: =COUNTIFS(Data_Ventas!$A$2:$A1136,">="&$C$5,Data_Ventas!$A$2:$A1136,"<="&$E$5,Data_Ventas!$F$2:$F1136,B124)+COUNTIFS(Data_Cotiz!$A$2:$A1136,">="&$C$5,Data_Cotiz!$A$2:$A1136,"<="&$E$5,Data_Cotiz!$F$2:$F1136,B124)+COUNTIFS(Data_Leads!$A$2:$A1136,">="&$C$5,Data_Leads!$A$2:$A1136,"<="&$E$5,Data_Leads!$J$2:$J1136,B124) -> 0 | F124: ALERTA COMERCIAL 3:1
B125: =Configuracion!E15 -> Base de datos | D125: =COUNTIFS(Data_Ventas!$A$2:$A1136,">="&$C$5,Data_Ventas!$A$2:$A1136,"<="&$E$5,Data_Ventas!$F$2:$F1136,B125)+COUNTIFS(Data_Cotiz!$A$2:$A1136,">="&$C$5,Data_Cotiz!$A$2:$A1136,"<="&$E$5,Data_Cotiz!$F$2:$F1136,B125)+COUNTIFS(Data_Leads!$A$2:$A1136,">="&$C$5,Data_Leads!$A$2:$A1136,"<="&$E$5,Data_Leads!$J$2:$J1136,B125) -> 0 | F125: =IF($D$138=0,"Aún no hay separaciones en el rango",IF($D$137/$D$138>=3,"Buen volumen de visitas: sostener 3+ por separación","Aumentar visitas: objetivo mínimo 3 clientes por cada separación")) -> Aumentar visitas: objetivo mínimo 3 clientes por cada separación
B126: =Configuracion!E16 -> Redes Sociales | D126: =COUNTIFS(Data_Ventas!$A$2:$A1136,">="&$C$5,Data_Ventas!$A$2:$A1136,"<="&$E$5,Data_Ventas!$F$2:$F1136,B126)+COUNTIFS(Data_Cotiz!$A$2:$A1136,">="&$C$5,Data_Cotiz!$A$2:$A1136,"<="&$E$5,Data_Cotiz!$F$2:$F1136,B126)+COUNTIFS(Data_Leads!$A$2:$A1136,">="&$C$5,Data_Leads!$A$2:$A1136,"<="&$E$5,Data_Leads!$J$2:$J1136,B126) -> 0
B127: =Configuracion!E17 -> tiktok | D127: =COUNTIFS(Data_Ventas!$A$2:$A1136,">="&$C$5,Data_Ventas!$A$2:$A1136,"<="&$E$5,Data_Ventas!$F$2:$F1136,B127)+COUNTIFS(Data_Cotiz!$A$2:$A1136,">="&$C$5,Data_Cotiz!$A$2:$A1136,"<="&$E$5,Data_Cotiz!$F$2:$F1136,B127)+COUNTIFS(Data_Leads!$A$2:$A1136,">="&$C$5,Data_Leads!$A$2:$A1136,"<="&$E$5,Data_Leads!$J$2:$J1136,B127) -> 0
D129: Cantidad | E129: Conversion | F129: Meta | G129: Gap | H129: Estado | J129: EVOLUCIÓN ÚLTIMAS 12 SEMANAS
...

Sheet Meta
A1: PLAN CSO — META, PRESUPUESTO, FORECAST, CASH-IN Y PRECISIÓN
N3: Resultados Proyectados
A4: Mes | B4: Meta venta S/ | C4: Meta lotes | D4: Meta cash-in S/ | E4: Presupuesto CSO | F4: Presupuesto CMO | G4: Eventos plan | H4: Forecast S/ | I4: Venta real S/ | J4: Lotes real | K4: Cash-in real | L4: Forecast accuracy | M4: Gap vs meta | N4: Lead | O4: Agenda | P4: Visitas | Q4: Separaciones | R4: Estado
A5: 46023 | B5: 400000 | C5: 10 | D5: 175000 | E5: 65000 | F5: 43000 | G5: 4 | H5: =SUMIFS(Data_Ventas!$N:$N,Data_Ventas!$A:$A,">="&$A5,Data_Ventas!$A:$A,"<="&EOMONTH($A5,0),Data_Ventas!$H:$H,"Separado")+I5+SUMIFS(Data_Cotiz!$N:$N,Data_Cotiz!$A:$A,">="&$A5,Data_Cotiz!$A:$A,"<="&EOMONTH($A5,0),Data_Cotiz!$H:$H,"Listo para comprar") -> 244800 | I5: =SUMIFS(Data_Ventas!$N:$N,Data_Ventas!$A:$A,">="&$A5,Data_Ventas!$A:$A,"<="&EOMONTH($A5,0),Data_Ventas!$H:$H,"Venta") -> 244800 | J5: =COUNTIFS(Data_Ventas!$A:$A,">="&$A5,Data_Ventas!$A:$A,"<="&EOMONTH($A5,0),Data_Ventas!$H:$H,"Venta") -> 4 | K5: =SUMIFS(Data_Ventas!$R:$R,Data_Ventas!$A:$A,">="&$A5,Data_Ventas!$A:$A,"<="&EOMONTH($A5,0),Data_Ventas!$H:$H,"Venta") -> 27200 | L5: =IF(OR(H5="",I5="",I5=0),"",MAX(1-ABS(H5-I5)/I5)) -> 1 | M5: =IF(H5="","",H5-B5) -> -155200 | N5: =ROUNDUP(O5/Configuracion!$B$11,0) -> 325 | O5: =ROUNDUP(P5/Configuracion!$B$12,0) -> 65 | P5: =ROUNDUP(Q5/Configuracion!$B$13,0) -> 39 | Q5: =ROUNDUP(C5/Configuracion!$B$14,0) -> 13
A6: 46054 | B6: 400000 | C6: 10 | D6: 175000 | E6: 65000 | F6: 43000 | G6: 4 | H6: =SUMIFS(Data_Ventas!$N:$N,Data_Ventas!$A:$A,">="&$A6,Data_Ventas!$A:$A,"<="&EOMONTH($A6,0),Data_Ventas!$H:$H,"Separado")+I6+SUMIFS(Data_Cotiz!$N:$N,Data_Cotiz!$A:$A,">="&$A6,Data_Cotiz!$A:$A,"<="&EOMONTH($A6,0),Data_Cotiz!$H:$H,"Listo para comprar") -> 52360 | I6: =SUMIFS(Data_Ventas!$N:$N,Data_Ventas!$A:$A,">="&$A6,Data_Ventas!$A:$A,"<="&EOMONTH($A6,0),Data_Ventas!$H:$H,"Venta") -> 52360 | J6: =COUNTIFS(Data_Ventas!$A:$A,">="&$A6,Data_Ventas!$A:$A,"<="&EOMONTH($A6,0),Data_Ventas!$H:$H,"Venta") -> 1 | K6: =SUMIFS(Data_Ventas!$R:$R,Data_Ventas!$A:$A,">="&$A6,Data_Ventas!$A:$A,"<="&EOMONTH($A6,0),Data_Ventas!$H:$H,"Venta") -> 52360 | L6: =IF(OR(H6="",I6="",I6=0),"",MAX(1-ABS(H6-I6)/I6)) -> 1 | M6: =IF(H6="","",H6-B6) -> -347640 | N6: =ROUNDUP(O6/Configuracion!$B$11,0) -> 325 | O6: =ROUNDUP(P6/Configuracion!$B$12,0) -> 65 | P6: =ROUNDUP(Q6/Configuracion!$B$13,0) -> 39 | Q6: =ROUNDUP(C6/Configuracion!$B$14,0) -> 13
A7: 46082 | B7: 400000 | C7: 10 | D7: 175000 | E7: 65000 | F7: 43000 | G7: 4 | H7: =SUMIFS(Data_Ventas!$N:$N,Data_Ventas!$A:$A,">="&$A7,Data_Ventas!$A:$A,"<="&EOMONTH($A7,0),Data_Ventas!$H:$H,"Separado")+I7+SUMIFS(Data_Cotiz!$N:$N,Data_Cotiz!$A:$A,">="&$A7,Data_Cotiz!$A:$A,"<="&EOMONTH($A7,0),Data_Cotiz!$H:$H,"Listo para comprar") -> 51000 | I7: =SUMIFS(Data_Ventas!$N:$N,Data_Ventas!$A:$A,">="&$A7,Data_Ventas!$A:$A,"<="&EOMONTH($A7,0),Data_Ventas!$H:$H,"Venta") -> 51000 | J7: =COUNTIFS(Data_Ventas!$A:$A,">="&$A7,Data_Ventas!$A:$A,"<="&EOMONTH($A7,0),Data_Ventas!$H:$H,"Venta") -> 1 | K7: =SUMIFS(Data_Ventas!$R:$R,Data_Ventas!$A:$A,">="&$A7,Data_Ventas!$A:$A,"<="&EOMONTH($A7,0),Data_Ventas!$H:$H,"Venta") -> 51000 | L7: =IF(OR(H7="",I7="",I7=0),"",MAX(1-ABS(H7-I7)/I7)) -> 1 | M7: =IF(H7="","",H7-B7) -> -349000 | N7: =ROUNDUP(O7/Configuracion!$B$11,0) -> 325 | O7: =ROUNDUP(P7/Configuracion!$B$12,0) -> 65 | P7: =ROUNDUP(Q7/Configuracion!$B$13,0) -> 39 | Q7: =ROUNDUP(C7/Configuracion!$B$14,0) -> 13
A8: 46113 | B8: 400000 | C8: 10 | D8: 175000 | E8: 65000 | F8: 43000 | G8: 4 | H8: =SUMIFS(Data_Ventas!$N:$N,Data_Ventas!$A:$A,">="&$A8,Data_Ventas!$A:$A,"<="&EOMONTH($A8,0),Data_Ventas!$H:$H,"Separado")+I8+SUMIFS(Data_Cotiz!$N:$N,Data_Cotiz!$A:$A,">="&$A8,Data_Cotiz!$A:$A,"<="&EOMONTH($A8,0),Data_Cotiz!$H:$H,"Listo para comprar") -> 0 | I8: =SUMIFS(Data_Ventas!$N:$N,Data_Ventas!$A:$A,">="&$A8,Data_Ventas!$A:$A,"<="&EOMONTH($A8,0),Data_Ventas!$H:$H,"Venta") -> 0 | J8: =COUNTIFS(Data_Ventas!$A:$A,">="&$A8,Data_Ventas!$A:$A,"<="&EOMONTH($A8,0),Data_Ventas!$H:$H,"Venta") -> 0 | K8: =SUMIFS(Data_Ventas!$R:$R,Data_Ventas!$A:$A,">="&$A8,Data_Ventas!$A:$A,"<="&EOMONTH($A8,0),Data_Ventas!$H:$H,"Venta") -> 0 | L8: =IF(OR(H8="",I8="",I8=0),"",MAX(1-ABS(H8-I8)/I8)) | M8: =IF(H8="","",H8-B8) -> -400000 | N8: =ROUNDUP(O8/Configuracion!$B$11,0) -> 325 | O8: =ROUNDUP(P8/Configuracion!$B$12,0) -> 65 | P8: =ROUNDUP(Q8/Configuracion!$B$13,0) -> 39 | Q8: =ROUNDUP(C8/Configuracion!$B$14,0) -> 13
A9: 46143 | B9: 400000 | C9: 10 | D9: 175000 | E9: 65000 | F9: 43000 | G9: 4 | H9: =SUMIFS(Data_Ventas!$N:$N,Data_Ventas!$A:$A,">="&$A9,Data_Ventas!$A:$A,"<="&EOMONTH($A9,0),Data_Ventas!$H:$H,"Separado")+I9+SUMIFS(Data_Cotiz!$N:$N,Data_Cotiz!$A:$A,">="&$A9,Data_Cotiz!$A:$A,"<="&EOMONTH($A9,0),Data_Cotiz!$H:$H,"Listo para comprar") -> 0 | I9: =SUMIFS(Data_Ventas!$N:$N,Data_Ventas!$A:$A,">="&$A9,Data_Ventas!$A:$A,"<="&EOMONTH($A9,0),Data_Ventas!$H:$H,"Venta") -> 0 | J9: =COUNTIFS(Data_Ventas!$A:$A,">="&$A9,Data_Ventas!$A:$A,"<="&EOMONTH($A9,0),Data_Ventas!$H:$H,"Venta") -> 0 | K9: =SUMIFS(Data_Ventas!$R:$R,Data_Ventas!$A:$A,">="&$A9,Data_Ventas!$A:$A,"<="&EOMONTH($A9,0),Data_Ventas!$H:$H,"Venta") -> 0 | L9: =IF(OR(H9="",I9="",I9=0),"",MAX(1-ABS(H9-I9)/I9)) | M9: =IF(H9="","",H9-B9) -> -400000 | N9: =ROUNDUP(O9/Configuracion!$B$11,0) -> 325 | O9: =ROUNDUP(P9/Configuracion!$B$12,0) -> 65 | P9: =ROUNDUP(Q9/Configuracion!$B$13,0) -> 39 | Q9: =ROUNDUP(C9/Configuracion!$B$14,0) -> 13
A10: 46174 | B10: 400000 | C10: 10 | D10: 175000 | E10: 65000 | F10: 43000 | G10: 4 | H10: =SUMIFS(Data_Ventas!$N:$N,Data_Ventas!$A:$A,">="&$A10,Data_Ventas!$A:$A,"<="&EOMONTH($A10,0),Data_Ventas!$H:$H,"Separado")+I10+SUMIFS(Data_Cotiz!$N:$N,Data_Cotiz!$A:$A,">="&$A10,Data_Cotiz!$A:$A,"<="&EOMONTH($A10,0),Data_Cotiz!$H:$H,"Listo para comprar") -> 0 | I10: =SUMIFS(Data_Ventas!$N:$N,Data_Ventas!$A:$A,">="&$A10,Data_Ventas!$A:$A,"<="&EOMONTH($A10,0),Data_Ventas!$H:$H,"Venta") -> 0 | J10: =COUNTIFS(Data_Ventas!$A:$A,">="&$A10,Data_Ventas!$A:$A,"<="&EOMONTH($A10,0),Data_Ventas!$H:$H,"Venta") -> 0 | K10: =SUMIFS(Data_Ventas!$R:$R,Data_Ventas!$A:$A,">="&$A10,Data_Ventas!$A:$A,"<="&EOMONTH($A10,0),Data_Ventas!$H:$H,"Venta") -> 0 | L10: =IF(OR(H10="",I10="",I10=0),"",MAX(1-ABS(H10-I10)/I10)) | M10: =IF(H10="","",H10-B10) -> -400000 | N10: =ROUNDUP(O10/Configuracion!$B$11,0) -> 325 | O10: =ROUNDUP(P10/Configuracion!$B$12,0) -> 65 | P10: =ROUNDUP(Q10/Configuracion!$B$13,0) -> 39 | Q10: =ROUNDUP(C10/Configuracion!$B$14,0) -> 13
A11: 46204 | B11: 400000 | C11: 10 | D11: 175000 | E11: 65000 | F11: 43000 | G11: 4 | H11: =SUMIFS(Data_Ventas!$N:$N,Data_Ventas!$A:$A,">="&$A11,Data_Ventas!$A:$A,"<="&EOMONTH($A11,0),Data_Ventas!$H:$H,"Separado")+I11+SUMIFS(Data_Cotiz!$N:$N,Data_Cotiz!$A:$A,">="&$A11,Data_Cotiz!$A:$A,"<="&EOMONTH($A11,0),Data_Cotiz!$H:$H,"Listo para comprar") -> 42000 | I11: =SUMIFS(Data_Ventas!$N:$N,Data_Ventas!$A:$A,">="&$A11,Data_Ventas!$A:$A,"<="&EOMONTH($A11,0),Data_Ventas!$H:$H,"Venta") -> 42000 | J11: =COUNTIFS(Data_Ventas!$A:$A,">="&$A11,Data_Ventas!$A:$A,"<="&EOMONTH($A11,0),Data_Ventas!$H:$H,"Venta") -> 1 | K11: =SUMIFS(Data_Ventas!$R:$R,Data_Ventas!$A:$A,">="&$A11,Data_Ventas!$A:$A,"<="&EOMONTH($A11,0),Data_Ventas!$H:$H,"Venta") -> 30000 | L11: =IF(OR(H11="",I11="",I11=0),"",MAX(1-ABS(H11-I11)/I11)) -> 1 | M11: =IF(H11="","",H11-B11) -> -358000 | N11: =ROUNDUP(O11/Configuracion!$B$11,0) -> 325 | O11: =ROUNDUP(P11/Configuracion!$B$12,0) -> 65 | P11: =ROUNDUP(Q11/Configuracion!$B$13,0) -> 39 | Q11: =ROUNDUP(C11/Configuracion!$B$14,0) -> 13
A12: 46235 | B12: 400000 | C12: 10 | D12: 175000 | E12: 65000 | F12: 43000 | G12: 4 | H12: =SUMIFS(Data_Ventas!$N:$N,Data_Ventas!$A:$A,">="&$A12,Data_Ventas!$A:$A,"<="&EOMONTH($A12,0),Data_Ventas!$H:$H,"Separado")+I12+SUMIFS(Data_Cotiz!$N:$N,Data_Cotiz!$A:$A,">="&$A12,Data_Cotiz!$A:$A,"<="&EOMONTH($A12,0),Data_Cotiz!$H:$H,"Listo para comprar") -> 125000 | I12: =SUMIFS(Data_Ventas!$N:$N,Data_Ventas!$A:$A,">="&$A12,Data_Ventas!$A:$A,"<="&EOMONTH($A12,0),Data_Ventas!$H:$H,"Venta") -> 125000 | J12: =COUNTIFS(Data_Ventas!$A:$A,">="&$A12,Data_Ventas!$A:$A,"<="&EOMONTH($A12,0),Data_Ventas!$H:$H,"Venta") -> 3 | K12: =SUMIFS(Data_Ventas!$R:$R,Data_Ventas!$A:$A,">="&$A12,Data_Ventas!$A:$A,"<="&EOMONTH($A12,0),Data_Ventas!$H:$H,"Venta") -> 8250 | L12: =IF(OR(H12="",I12="",I12=0),"",MAX(1-ABS(H12-I12)/I12)) -> 1 | M12: =IF(H12="","",H12-B12) -> -275000 | N12: =ROUNDUP(O12/Configuracion!$B$11,0) -> 325 | O12: =ROUNDUP(P12/Configuracion!$B$12,0) -> 65 | P12: =ROUNDUP(Q12/Configuracion!$B$13,0) -> 39 | Q12: =ROUNDUP(C12/Configuracion!$B$14,0) -> 13
A13: 46266 | B13: 400000 | C13: 10 | D13: 175000 | E13: 65000 | F13: 43000 | G13: 4 | H13: =SUMIFS(Data_Ventas!$N:$N,Data_Ventas!$A:$A,">="&$A13,Data_Ventas!$A:$A,"<="&EOMONTH($A13,0),Data_Ventas!$H:$H,"Separado")+I13+SUMIFS(Data_Cotiz!$N:$N,Data_Cotiz!$A:$A,">="&$A13,Data_Cotiz!$A:$A,"<="&EOMONTH($A13,0),Data_Cotiz!$H:$H,"Listo para comprar") -> 40000 | I13: =SUMIFS(Data_Ventas!$N:$N,Data_Ventas!$A:$A,">="&$A13,Data_Ventas!$A:$A,"<="&EOMONTH($A13,0),Data_Ventas!$H:$H,"Venta") -> 40000 | J13: =COUNTIFS(Data_Ventas!$A:$A,">="&$A13,Data_Ventas!$A:$A,"<="&EOMONTH($A13,0),Data_Ventas!$H:$H,"Venta") -> 1 | K13: =SUMIFS(Data_Ventas!$R:$R,Data_Ventas!$A:$A,">="&$A13,Data_Ventas!$A:$A,"<="&EOMONTH($A13,0),Data_Ventas!$H:$H,"Venta") -> 5000 | L13: =IF(OR(H13="",I13="",I13=0),"",MAX(1-ABS(H13-I13)/I13)) -> 1 | M13: =IF(H13="","",H13-B13) -> -360000 | N13: =ROUNDUP(O13/Configuracion!$B$11,0) -> 325 | O13: =ROUNDUP(P13/Configuracion!$B$12,0) -> 65 | P13: =ROUNDUP(Q13/Configuracion!$B$13,0) -> 39 | Q13: =ROUNDUP(C13/Configuracion!$B$14,0) -> 13
A14: 46296 | B14: 400000 | C14: 10 | D14: 175000 | E14: 65000 | F14: 43000 | G14: 4 | H14: =SUMIFS(Data_Ventas!$N:$N,Data_Ventas!$A:$A,">="&$A14,Data_Ventas!$A:$A,"<="&EOMONTH($A14,0),Data_Ventas!$H:$H,"Separado")+I14+SUMIFS(Data_Cotiz!$N:$N,Data_Cotiz!$A:$A,">="&$A14,Data_Cotiz!$A:$A,"<="&EOMONTH($A14,0),Data_Cotiz!$H:$H,"Listo para comprar") -> 0 | I14: =SUMIFS(Data_Ventas!$N:$N,Data_Ventas!$A:$A,">="&$A14,Data_Ventas!$A:$A,"<="&EOMONTH($A14,0),Data_Ventas!$H:$H,"Venta") -> 0 | J14: =COUNTIFS(Data_Ventas!$A:$A,">="&$A14,Data_Ventas!$A:$A,"<="&EOMONTH($A14,0),Data_Ventas!$H:$H,"Venta") -> 0 | K14: =SUMIFS(Data_Ventas!$R:$R,Data_Ventas!$A:$A,">="&$A14,Data_Ventas!$A:$A,"<="&EOMONTH($A14,0),Data_Ventas!$H:$H,"Venta") -> 0 | M14: =IF(H14="","",H14-B14) -> -400000 | N14: =ROUNDUP(O14/Configuracion!$B$11,0) -> 325 | O14: =ROUNDUP(P14/Configuracion!$B$12,0) -> 65 | P14: =ROUNDUP(Q14/Configuracion!$B$13,0) -> 39 | Q14: =ROUNDUP(C14/Configuracion!$B$14,0) -> 13
A15: 46327 | B15: 400000 | C15: 10 | D15: 175000 | E15: 65000 | F15: 43000 | G15: 4 | H15: =SUMIFS(Data_Ventas!$N:$N,Data_Ventas!$A:$A,">="&$A15,Data_Ventas!$A:$A,"<="&EOMONTH($A15,0),Data_Ventas!$H:$H,"Separado")+I15+SUMIFS(Data_Cotiz!$N:$N,Data_Cotiz!$A:$A,">="&$A15,Data_Cotiz!$A:$A,"<="&EOMONTH($A15,0),Data_Cotiz!$H:$H,"Listo para comprar") -> 0 | I15: =SUMIFS(Data_Ventas!$N:$N,Data_Ventas!$A:$A,">="&$A15,Data_Ventas!$A:$A,"<="&EOMONTH($A15,0),Data_Ventas!$H:$H,"Venta") -> 0 | J15: =COUNTIFS(Data_Ventas!$A:$A,">="&$A15,Data_Ventas!$A:$A,"<="&EOMONTH($A15,0),Data_Ventas!$H:$H,"Venta") -> 0 | K15: =SUMIFS(Data_Ventas!$R:$R,Data_Ventas!$A:$A,">="&$A15,Data_Ventas!$A:$A,"<="&EOMONTH($A15,0),Data_Ventas!$H:$H,"Venta") -> 0 | M15: =IF(H15="","",H15-B15) -> -400000 | N15: =ROUNDUP(O15/Configuracion!$B$11,0) -> 325 | O15: =ROUNDUP(P15/Configuracion!$B$12,0) -> 65 | P15: =ROUNDUP(Q15/Configuracion!$B$13,0) -> 39 | Q15: =ROUNDUP(C15/Configuracion!$B$14,0) -> 13
A16: 46357 | B16: 400000 | C16: 10 | D16: 175000 | E16: 65000 | F16: 43000 | G16: 4 | H16: =SUMIFS(Data_Ventas!$N:$N,Data_Ventas!$A:$A,">="&$A16,Data_Ventas!$A:$A,"<="&EOMONTH($A16,0),Data_Ventas!$H:$H,"Separado")+I16+SUMIFS(Data_Cotiz!$N:$N,Data_Cotiz!$A:$A,">="&$A16,Data_Cotiz!$A:$A,"<="&EOMONTH($A16,0),Data_Cotiz!$H:$H,"Listo para comprar") -> 0 | I16: =SUMIFS(Data_Ventas!$N:$N,Data_Ventas!$A:$A,">="&$A16,Data_Ventas!$A:$A,"<="&EOMONTH($A16,0),Data_Ventas!$H:$H,"Venta") -> 0 | J16: =COUNTIFS(Data_Ventas!$A:$A,">="&$A16,Data_Ventas!$A:$A,"<="&EOMONTH($A16,0),Data_Ventas!$H:$H,"Venta") -> 0 | K16: =SUMIFS(Data_Ventas!$R:$R,Data_Ventas!$A:$A,">="&$A16,Data_Ventas!$A:$A,"<="&EOMONTH($A16,0),Data_Ventas!$H:$H,"Venta") -> 0 | M16: =IF(H16="","",H16-B16) -> -400000 | N16: =ROUNDUP(O16/Configuracion!$B$11,0) -> 325 | O16: =ROUNDUP(P16/Configuracion!$B$12,0) -> 65 | P16: =ROUNDUP(Q16/Configuracion!$B$13,0) -> 39 | Q16: =ROUNDUP(C16/Configuracion!$B$14,0) -> 13

Sheet Resum_Semanal
A1: RESUMEN SEMANAL AUTOMÁTICO
B3: PROYECTADA | G3: REAL
A4: Semana inicia | B4: Leads | C4: Visitas | D4: Separaciones | E4: Ventas | F4: Facturación | G4: Leads | H4: Visitas | I4: Separaciones | J4: Ventas | K4: Facturación | L4: Cumplimiento S/.
A5: =Dashboard!$E$5-WEEKDAY(Dashboard!$E$5,2)+1-78 -> 46215 | B5: =IFERROR(LET(meta,SUMIFS(Meta!$N$5:$N$16,Meta!$A$5:$A$16,">="&EOMONTH($A5,-1)+1,Meta!$A$5:$A$16,"<="&EOMONTH($A5,0)),semanas,COUNTIFS($A$5:$A$35,">="&EOMONTH($A5,-1)+1,$A$5:$A$35,"<="&EOMONTH($A5,0)),posicion,COUNTIFS($A$5:$A5,">="&EOMONTH($A5,-1)+1,$A$5:$A5,"<="&EOMONTH($A5,0)),QUOTIENT(meta,semanas)+IF(posicion<=MOD(meta,semanas),1,0)),"") -> 109 | C5: =IFERROR(LET(meta,SUMIFS(Meta!$P$5:$P$16,Meta!$A$5:$A$16,">="&EOMONTH($A5,-1)+1,Meta!$A$5:$A$16,"<="&EOMONTH($A5,0)),semanas,COUNTIFS($A$5:$A$35,">="&EOMONTH($A5,-1)+1,$A$5:$A$35,"<="&EOMONTH($A5,0)),posicion,COUNTIFS($A$5:$A5,">="&EOMONTH($A5,-1)+1,$A$5:$A5,"<="&EOMONTH($A5,0)),QUOTIENT(meta,semanas)+IF(posicion<=MOD(meta,semanas),1,0)),"") -> 13 | D5: =IFERROR(LET(meta,SUMIFS(Meta!$Q$5:$Q$16,Meta!$A$5:$A$16,">="&EOMONTH($A5,-1)+1,Meta!$A$5:$A$16,"<="&EOMONTH($A5,0)),semanas,COUNTIFS($A$5:$A$35,">="&EOMONTH($A5,-1)+1,$A$5:$A$35,"<="&EOMONTH($A5,0)),posicion,COUNTIFS($A$5:$A5,">="&EOMONTH($A5,-1)+1,$A$5:$A5,"<="&EOMONTH($A5,0)),QUOTIENT(meta,semanas)+IF(posicion<=MOD(meta,semanas),1,0)),"") -> 5 | E5: =IFERROR(LET(meta,SUMIFS(Meta!$C$5:$C$16,Meta!$A$5:$A$16,">="&EOMONTH($A5,-1)+1,Meta!$A$5:$A$16,"<="&EOMONTH($A5,0)),semanas,COUNTIFS($A$5:$A$35,">="&EOMONTH($A5,-1)+1,$A$5:$A$35,"<="&EOMONTH($A5,0)),posicion,COUNTIFS($A$5:$A5,">="&EOMONTH($A5,-1)+1,$A$5:$A5,"<="&EOMONTH($A5,0)),QUOTIENT(meta,semanas)+IF(posicion<=MOD(meta,semanas),1,0)),"") -> 4 | F5: =IFERROR(SUMIFS(Meta!$B$5:$B$16,Meta!$A$5:$A$16,">="&EOMONTH($A5,-1)+1,Meta!$A$5:$A$16,"<="&EOMONTH($A5,0))/COUNTIFS($A$5:$A$35,">="&EOMONTH($A5,-1)+1,$A$5:$A$35,"<="&EOMONTH($A5,0)),"") -> 133333.33 | G5: =COUNTIFS(Data_Ventas!$E$2:$E1001,">="&A5,Data_Ventas!$E$2:$E1001,"<="&A5+6) -> 0 | H5: =COUNTIFS(Data_Ventas!$A$2:$A1001,">="&A5,Data_Ventas!$A$2:$A1001,"<="&A5+6,Data_Ventas!$H$2:$H1001,"Visitó proyecto") -> 0 | I5: =COUNTIFS(Data_Ventas!$A$2:$A1001,">="&A5,Data_Ventas!$A$2:$A1001,"<="&A5+6,Data_Ventas!$H$2:$H1001,"Separado") -> 0 | J5: =COUNTIFS(Data_Ventas!$A$2:$A1001,">="&A5,Data_Ventas!$A$2:$A1001,"<="&A5+6,Data_Ventas!$H$2:$H1001,"Venta") -> 0 | K5: =SUMIFS(Data_Ventas!$N$2:$N1001,Data_Ventas!$A$2:$A1001,">="&A5,Data_Ventas!$A$2:$A1001,"<="&A5+6,Data_Ventas!$H$2:$H1001,"Venta") -> 0 | L5: =IFERROR(K5/F5,"0%") -> 0
A6: =A5+7 -> 46222 | B6: =IFERROR(LET(meta,SUMIFS(Meta!$N$5:$N$16,Meta!$A$5:$A$16,">="&EOMONTH($A6,-1)+1,Meta!$A$5:$A$16,"<="&EOMONTH($A6,0)),semanas,COUNTIFS($A$5:$A$35,">="&EOMONTH($A6,-1)+1,$A$5:$A$35,"<="&EOMONTH($A6,0)),posicion,COUNTIFS($A$5:$A6,">="&EOMONTH($A6,-1)+1,$A$5:$A6,"<="&EOMONTH($A6,0)),QUOTIENT(meta,semanas)+IF(posicion<=MOD(meta,semanas),1,0)),"") -> 108 | C6: =IFERROR(LET(meta,SUMIFS(Meta!$P$5:$P$16,Meta!$A$5:$A$16,">="&EOMONTH($A6,-1)+1,Meta!$A$5:$A$16,"<="&EOMONTH($A6,0)),semanas,COUNTIFS($A$5:$A$35,">="&EOMONTH($A6,-1)+1,$A$5:$A$35,"<="&EOMONTH($A6,0)),posicion,COUNTIFS($A$5:$A6,">="&EOMONTH($A6,-1)+1,$A$5:$A6,"<="&EOMONTH($A6,0)),QUOTIENT(meta,semanas)+IF(posicion<=MOD(meta,semanas),1,0)),"") -> 13 | D6: =IFERROR(LET(meta,SUMIFS(Meta!$Q$5:$Q$16,Meta!$A$5:$A$16,">="&EOMONTH($A6,-1)+1,Meta!$A$5:$A$16,"<="&EOMONTH($A6,0)),semanas,COUNTIFS($A$5:$A$35,">="&EOMONTH($A6,-1)+1,$A$5:$A$35,"<="&EOMONTH($A6,0)),posicion,COUNTIFS($A$5:$A6,">="&EOMONTH($A6,-1)+1,$A$5:$A6,"<="&EOMONTH($A6,0)),QUOTIENT(meta,semanas)+IF(posicion<=MOD(meta,semanas),1,0)),"") -> 4 | E6: =IFERROR(LET(meta,SUMIFS(Meta!$C$5:$C$16,Meta!$A$5:$A$16,">="&EOMONTH($A6,-1)+1,Meta!$A$5:$A$16,"<="&EOMONTH($A6,0)),semanas,COUNTIFS($A$5:$A$35,">="&EOMONTH($A6,-1)+1,$A$5:$A$35,"<="&EOMONTH($A6,0)),posicion,COUNTIFS($A$5:$A6,">="&EOMONTH($A6,-1)+1,$A$5:$A6,"<="&EOMONTH($A6,0)),QUOTIENT(meta,semanas)+IF(posicion<=MOD(meta,semanas),1,0)),"") -> 3 | F6: =IFERROR(SUMIFS(Meta!$B$5:$B$16,Meta!$A$5:$A$16,">="&EOMONTH($A6,-1)+1,Meta!$A$5:$A$16,"<="&EOMONTH($A6,0))/COUNTIFS($A$5:$A$35,">="&EOMONTH($A6,-1)+1,$A$5:$A$35,"<="&EOMONTH($A6,0)),"") -> 133333.33 | G6: =COUNTIFS(Data_Ventas!$E$2:$E1001,">="&A6,Data_Ventas!$E$2:$E1001,"<="&A6+6) -> 0 | H6: =COUNTIFS(Data_Ventas!$A$2:$A1001,">="&A6,Data_Ventas!$A$2:$A1001,"<="&A6+6,Data_Ventas!$H$2:$H1001,"Visitó proyecto") -> 0 | I6: =COUNTIFS(Data_Ventas!$A$2:$A1001,">="&A6,Data_Ventas!$A$2:$A1001,"<="&A6+6,Data_Ventas!$H$2:$H1001,"Separado") -> 0 | J6: =COUNTIFS(Data_Ventas!$A$2:$A1001,">="&A6,Data_Ventas!$A$2:$A1001,"<="&A6+6,Data_Ventas!$H$2:$H1001,"Venta") -> 0 | K6: =SUMIFS(Data_Ventas!$N$2:$N1001,Data_Ventas!$A$2:$A1001,">="&A6,Data_Ventas!$A$2:$A1001,"<="&A6+6,Data_Ventas!$H$2:$H1001,"Venta") -> 0 | L6: =IFERROR(K6/F6,"0%") -> 0
A7: =A6+7 -> 46229 | B7: =IFERROR(LET(meta,SUMIFS(Meta!$N$5:$N$16,Meta!$A$5:$A$16,">="&EOMONTH($A7,-1)+1,Meta!$A$5:$A$16,"<="&EOMONTH($A7,0)),semanas,COUNTIFS($A$5:$A$35,">="&EOMONTH($A7,-1)+1,$A$5:$A$35,"<="&EOMONTH($A7,0)),posicion,COUNTIFS($A$5:$A7,">="&EOMONTH($A7,-1)+1,$A$5:$A7,"<="&EOMONTH($A7,0)),QUOTIENT(meta,semanas)+IF(posicion<=MOD(meta,semanas),1,0)),"") -> 108 | C7: =IFERROR(LET(meta,SUMIFS(Meta!$P$5:$P$16,Meta!$A$5:$A$16,">="&EOMONTH($A7,-1)+1,Meta!$A$5:$A$16,"<="&EOMONTH($A7,0)),semanas,COUNTIFS($A$5:$A$35,">="&EOMONTH($A7,-1)+1,$A$5:$A$35,"<="&EOMONTH($A7,0)),posicion,COUNTIFS($A$5:$A7,">="&EOMONTH($A7,-1)+1,$A$5:$A7,"<="&EOMONTH($A7,0)),QUOTIENT(meta,semanas)+IF(posicion<=MOD(meta,semanas),1,0)),"") -> 13 | D7: =IFERROR(LET(meta,SUMIFS(Meta!$Q$5:$Q$16,Meta!$A$5:$A$16,">="&EOMONTH($A7,-1)+1,Meta!$A$5:$A$16,"<="&EOMONTH($A7,0)),semanas,COUNTIFS($A$5:$A$35,">="&EOMONTH($A7,-1)+1,$A$5:$A$35,"<="&EOMONTH($A7,0)),posicion,COUNTIFS($A$5:$A7,">="&EOMONTH($A7,-1)+1,$A$5:$A7,"<="&EOMONTH($A7,0)),QUOTIENT(meta,semanas)+IF(posicion<=MOD(meta,semanas),1,0)),"") -> 4 | E7: =IFERROR(LET(meta,SUMIFS(Meta!$C$5:$C$16,Meta!$A$5:$A$16,">="&EOMONTH($A7,-1)+1,Meta!$A$5:$A$16,"<="&EOMONTH($A7,0)),semanas,COUNTIFS($A$5:$A$35,">="&EOMONTH($A7,-1)+1,$A$5:$A$35,"<="&EOMONTH($A7,0)),posicion,COUNTIFS($A$5:$A7,">="&EOMONTH($A7,-1)+1,$A$5:$A7,"<="&EOMONTH($A7,0)),QUOTIENT(meta,semanas)+IF(posicion<=MOD(meta,semanas),1,0)),"") -> 3 | F7: =IFERROR(SUMIFS(Meta!$B$5:$B$16,Meta!$A$5:$A$16,">="&EOMONTH($A7,-1)+1,Meta!$A$5:$A$16,"<="&EOMONTH($A7,0))/COUNTIFS($A$5:$A$35,">="&EOMONTH($A7,-1)+1,$A$5:$A$35,"<="&EOMONTH($A7,0)),"") -> 133333.33 | G7: =COUNTIFS(Data_Ventas!$E$2:$E1001,">="&A7,Data_Ventas!$E$2:$E1001,"<="&A7+6) -> 0 | H7: =COUNTIFS(Data_Ventas!$A$2:$A1001,">="&A7,Data_Ventas!$A$2:$A1001,"<="&A7+6,Data_Ventas!$H$2:$H1001,"Visitó proyecto") -> 0 | I7: =COUNTIFS(Data_Ventas!$A$2:$A1001,">="&A7,Data_Ventas!$A$2:$A1001,"<="&A7+6,Data_Ventas!$H$2:$H1001,"Separado") -> 0 | J7: =COUNTIFS(Data_Ventas!$A$2:$A1001,">="&A7,Data_Ventas!$A$2:$A1001,"<="&A7+6,Data_Ventas!$H$2:$H1001,"Venta") -> 0 | K7: =SUMIFS(Data_Ventas!$N$2:$N1001,Data_Ventas!$A$2:$A1001,">="&A7,Data_Ventas!$A$2:$A1001,"<="&A7+6,Data_Ventas!$H$2:$H1001,"Venta") -> 0 | L7: =IFERROR(K7/F7,"0%") -> 0
A8: =A7+7 -> 46236 | B8: =IFERROR(LET(meta,SUMIFS(Meta!$N$5:$N$16,Meta!$A$5:$A$16,">="&EOMONTH($A8,-1)+1,Meta!$A$5:$A$16,"<="&EOMONTH($A8,0)),semanas,COUNTIFS($A$5:$A$35,">="&EOMONTH($A8,-1)+1,$A$5:$A$35,"<="&EOMONTH($A8,0)),posicion,COUNTIFS($A$5:$A8,">="&EOMONTH($A8,-1)+1,$A$5:$A8,"<="&EOMONTH($A8,0)),QUOTIENT(meta,semanas)+IF(posicion<=MOD(meta,semanas),1,0)),"") -> 65 | C8: =IFERROR(LET(meta,SUMIFS(Meta!$P$5:$P$16,Meta!$A$5:$A$16,">="&EOMONTH($A8,-1)+1,Meta!$A$5:$A$16,"<="&EOMONTH($A8,0)),semanas,COUNTIFS($A$5:$A$35,">="&EOMONTH($A8,-1)+1,$A$5:$A$35,"<="&EOMONTH($A8,0)),posicion,COUNTIFS($A$5:$A8,">="&EOMONTH($A8,-1)+1,$A$5:$A8,"<="&EOMONTH($A8,0)),QUOTIENT(meta,semanas)+IF(posicion<=MOD(meta,semanas),1,0)),"") -> 8 | D8: =IFERROR(LET(meta,SUMIFS(Meta!$Q$5:$Q$16,Meta!$A$5:$A$16,">="&EOMONTH($A8,-1)+1,Meta!$A$5:$A$16,"<="&EOMONTH($A8,0)),semanas,COUNTIFS($A$5:$A$35,">="&EOMONTH($A8,-1)+1,$A$5:$A$35,"<="&EOMONTH($A8,0)),posicion,COUNTIFS($A$5:$A8,">="&EOMONTH($A8,-1)+1,$A$5:$A8,"<="&EOMONTH($A8,0)),QUOTIENT(meta,semanas)+IF(posicion<=MOD(meta,semanas),1,0)),"") -> 3 | E8: =IFERROR(LET(meta,SUMIFS(Meta!$C$5:$C$16,Meta!$A$5:$A$16,">="&EOMONTH($A8,-1)+1,Meta!$A$5:$A$16,"<="&EOMONTH($A8,0)),semanas,COUNTIFS($A$5:$A$35,">="&EOMONTH($A8,-1)+1,$A$5:$A$35,"<="&EOMONTH($A8,0)),posicion,COUNTIFS($A$5:$A8,">="&EOMONTH($A8,-1)+1,$A$5:$A8,"<="&EOMONTH($A8,0)),QUOTIENT(meta,semanas)+IF(posicion<=MOD(meta,semanas),1,0)),"") -> 2 | F8: =IFERROR(SUMIFS(Meta!$B$5:$B$16,Meta!$A$5:$A$16,">="&EOMONTH($A8,-1)+1,Meta!$A$5:$A$16,"<="&EOMONTH($A8,0))/COUNTIFS($A$5:$A$35,">="&EOMONTH($A8,-1)+1,$A$5:$A$35,"<="&EOMONTH($A8,0)),"") -> 80000 | G8: =COUNTIFS(Data_Ventas!$E$2:$E1001,">="&A8,Data_Ventas!$E$2:$E1001,"<="&A8+6) -> 0 | H8: =COUNTIFS(Data_Ventas!$A$2:$A1001,">="&A8,Data_Ventas!$A$2:$A1001,"<="&A8+6,Data_Ventas!$H$2:$H1001,"Visitó proyecto") -> 0 | I8: =COUNTIFS(Data_Ventas!$A$2:$A1001,">="&A8,Data_Ventas!$A$2:$A1001,"<="&A8+6,Data_Ventas!$H$2:$H1001,"Separado") -> 0 | J8: =COUNTIFS(Data_Ventas!$A$2:$A1001,">="&A8,Data_Ventas!$A$2:$A1001,"<="&A8+6,Data_Ventas!$H$2:$H1001,"Venta") -> 0 | K8: =SUMIFS(Data_Ventas!$N$2:$N1001,Data_Ventas!$A$2:$A1001,">="&A8,Data_Ventas!$A$2:$A1001,"<="&A8+6,Data_Ventas!$H$2:$H1001,"Venta") -> 0 | L8: =IFERROR(K8/F8,"0%") -> 0
A9: =A8+7 -> 46243 | B9: =IFERROR(LET(meta,SUMIFS(Meta!$N$5:$N$16,Meta!$A$5:$A$16,">="&EOMONTH($A9,-1)+1,Meta!$A$5:$A$16,"<="&EOMONTH($A9,0)),semanas,COUNTIFS($A$5:$A$35,">="&EOMONTH($A9,-1)+1,$A$5:$A$35,"<="&EOMONTH($A9,0)),posicion,COUNTIFS($A$5:$A9,">="&EOMONTH($A9,-1)+1,$A$5:$A9,"<="&EOMONTH($A9,0)),QUOTIENT(meta,semanas)+IF(posicion<=MOD(meta,semanas),1,0)),"") -> 65 | C9: =IFERROR(LET(meta,SUMIFS(Meta!$P$5:$P$16,Meta!$A$5:$A$16,">="&EOMONTH($A9,-1)+1,Meta!$A$5:$A$16,"<="&EOMONTH($A9,0)),semanas,COUNTIFS($A$5:$A$35,">="&EOMONTH($A9,-1)+1,$A$5:$A$35,"<="&EOMONTH($A9,0)),posicion,COUNTIFS($A$5:$A9,">="&EOMONTH($A9,-1)+1,$A$5:$A9,"<="&EOMONTH($A9,0)),QUOTIENT(meta,semanas)+IF(posicion<=MOD(meta,semanas),1,0)),"") -> 8 | D9: =IFERROR(LET(meta,SUMIFS(Meta!$Q$5:$Q$16,Meta!$A$5:$A$16,">="&EOMONTH($A9,-1)+1,Meta!$A$5:$A$16,"<="&EOMONTH($A9,0)),semanas,COUNTIFS($A$5:$A$35,">="&EOMONTH($A9,-1)+1,$A$5:$A$35,"<="&EOMONTH($A9,0)),posicion,COUNTIFS($A$5:$A9,">="&EOMONTH($A9,-1)+1,$A$5:$A9,"<="&EOMONTH($A9,0)),QUOTIENT(meta,semanas)+IF(posicion<=MOD(meta,semanas),1,0)),"") -> 3 | E9: =IFERROR(LET(meta,SUMIFS(Meta!$C$5:$C$16,Meta!$A$5:$A$16,">="&EOMONTH($A9,-1)+1,Meta!$A$5:$A$16,"<="&EOMONTH($A9,0)),semanas,COUNTIFS($A$5:$A$35,">="&EOMONTH($A9,-1)+1,$A$5:$A$35,"<="&EOMONTH($A9,0)),posicion,COUNTIFS($A$5:$A9,">="&EOMONTH($A9,-1)+1,$A$5:$A9,"<="&EOMONTH($A9,0)),QUOTIENT(meta,semanas)+IF(posicion<=MOD(meta,semanas),1,0)),"") -> 2 | F9: =IFERROR(SUMIFS(Meta!$B$5:$B$16,Meta!$A$5:$A$16,">="&EOMONTH($A9,-1)+1,Meta!$A$5:$A$16,"<="&EOMONTH($A9,0))/COUNTIFS($A$5:$A$35,">="&EOMONTH($A9,-1)+1,$A$5:$A$35,"<="&EOMONTH($A9,0)),"") -> 80000 | G9: =COUNTIFS(Data_Ventas!$E$2:$E1001,">="&A9,Data_Ventas!$E$2:$E1001,"<="&A9+6) -> 0 | H9: =COUNTIFS(Data_Ventas!$A$2:$A1001,">="&A9,Data_Ventas!$A$2:$A1001,"<="&A9+6,Data_Ventas!$H$2:$H1001,"Visitó proyecto") -> 0 | I9: =COUNTIFS(Data_Ventas!$A$2:$A1001,">="&A9,Data_Ventas!$A$2:$A1001,"<="&A9+6,Data_Ventas!$H$2:$H1001,"Separado") -> 0 | J9: =COUNTIFS(Data_Ventas!$A$2:$A1001,">="&A9,Data_Ventas!$A$2:$A1001,"<="&A9+6,Data_Ventas!$H$2:$H1001,"Venta") -> 0 | K9: =SUMIFS(Data_Ventas!$N$2:$N1001,Data_Ventas!$A$2:$A1001,">="&A9,Data_Ventas!$A$2:$A1001,"<="&A9+6,Data_Ventas!$H$2:$H1001,"Venta") -> 0 | L9: =IFERROR(K9/F9,"0%") -> 0
A10: =A9+7 -> 46250 | B10: =IFERROR(LET(meta,SUMIFS(Meta!$N$5:$N$16,Meta!$A$5:$A$16,">="&EOMONTH($A10,-1)+1,Meta!$A$5:$A$16,"<="&EOMONTH($A10,0)),semanas,COUNTIFS($A$5:$A$35,">="&EOMONTH($A10,-1)+1,$A$5:$A$35,"<="&EOMONTH($A10,0)),posicion,COUNTIFS($A$5:$A10,">="&EOMONTH($A10,-1)+1,$A$5:$A10,"<="&EOMONTH($A10,0)),QUOTIENT(meta,semanas)+IF(posicion<=MOD(meta,semanas),1,0)),"") -> 65 | C10: =IFERROR(LET(meta,SUMIFS(Meta!$P$5:$P$16,Meta!$A$5:$A$16,">="&EOMONTH($A10,-1)+1,Meta!$A$5:$A$16,"<="&EOMONTH($A10,0)),semanas,COUNTIFS($A$5:$A$35,">="&EOMONTH($A10,-1)+1,$A$5:$A$35,"<="&EOMONTH($A10,0)),posicion,COUNTIFS($A$5:$A10,">="&EOMONTH($A10,-1)+1,$A$5:$A10,"<="&EOMONTH($A10,0)),QUOTIENT(meta,semanas)+IF(posicion<=MOD(meta,semanas),1,0)),"") -> 8 | D10: =IFERROR(LET(meta,SUMIFS(Meta!$Q$5:$Q$16,Meta!$A$5:$A$16,">="&EOMONTH($A10,-1)+1,Meta!$A$5:$A$16,"<="&EOMONTH($A10,0)),semanas,COUNTIFS($A$5:$A$35,">="&EOMONTH($A10,-1)+1,$A$5:$A$35,"<="&EOMONTH($A10,0)),posicion,COUNTIFS($A$5:$A10,">="&EOMONTH($A10,-1)+1,$A$5:$A10,"<="&EOMONTH($A10,0)),QUOTIENT(meta,semanas)+IF(posicion<=MOD(meta,semanas),1,0)),"") -> 3 | E10: =IFERROR(LET(meta,SUMIFS(Meta!$C$5:$C$16,Meta!$A$5:$A$16,">="&EOMONTH($A10,-1)+1,Meta!$A$5:$A$16,"<="&EOMONTH($A10,0)),semanas,COUNTIFS($A$5:$A$35,">="&EOMONTH($A10,-1)+1,$A$5:$A$35,"<="&EOMONTH($A10,0)),posicion,COUNTIFS($A$5:$A10,">="&EOMONTH($A10,-1)+1,$A$5:$A10,"<="&EOMONTH($A10,0)),QUOTIENT(meta,semanas)+IF(posicion<=MOD(meta,semanas),1,0)),"") -> 2 | F10: =IFERROR(SUMIFS(Meta!$B$5:$B$16,Meta!$A$5:$A$16,">="&EOMONTH($A10,-1)+1,Meta!$A$5:$A$16,"<="&EOMONTH($A10,0))/COUNTIFS($A$5:$A$35,">="&EOMONTH($A10,-1)+1,$A$5:$A$35,"<="&EOMONTH($A10,0)),"") -> 80000 | G10: =COUNTIFS(Data_Ventas!$E$2:$E1001,">="&A10,Data_Ventas!$E$2:$E1001,"<="&A10+6) -> 0 | H10: =COUNTIFS(Data_Ventas!$A$2:$A1001,">="&A10,Data_Ventas!$A$2:$A1001,"<="&A10+6,Data_Ventas!$H$2:$H1001,"Visitó proyecto") -> 0 | I10: =COUNTIFS(Data_Ventas!$A$2:$A1001,">="&A10,Data_Ventas!$A$2:$A1001,"<="&A10+6,Data_Ventas!$H$2:$H1001,"Separado") -> 0 | J10: =COUNTIFS(Data_Ventas!$A$2:$A1001,">="&A10,Data_Ventas!$A$2:$A1001,"<="&A10+6,Data_Ventas!$H$2:$H1001,"Venta") -> 1 | K10: =SUMIFS(Data_Ventas!$N$2:$N1001,Data_Ventas!$A$2:$A1001,">="&A10,Data_Ventas!$A$2:$A1001,"<="&A10+6,Data_Ventas!$H$2:$H1001,"Venta") -> 55000 | L10: =IFERROR(K10/F10,"0%") -> 0.6875
A11: =A10+7 -> 46257 | B11: =IFERROR(LET(meta,SUMIFS(Meta!$N$5:$N$16,Meta!$A$5:$A$16,">="&EOMONTH($A11,-1)+1,Meta!$A$5:$A$16,"<="&EOMONTH($A11,0)),semanas,COUNTIFS($A$5:$A$35,">="&EOMONTH($A11,-1)+1,$A$5:$A$35,"<="&EOMONTH($A11,0)),posicion,COUNTIFS($A$5:$A11,">="&EOMONTH($A11,-1)+1,$A$5:$A11,"<="&EOMONTH($A11,0)),QUOTIENT(meta,semanas)+IF(posicion<=MOD(meta,semanas),1,0)),"") -> 65 | C11: =IFERROR(LET(meta,SUMIFS(Meta!$P$5:$P$16,Meta!$A$5:$A$16,">="&EOMONTH($A11,-1)+1,Meta!$A$5:$A$16,"<="&EOMONTH($A11,0)),semanas,COUNTIFS($A$5:$A$35,">="&EOMONTH($A11,-1)+1,$A$5:$A$35,"<="&EOMONTH($A11,0)),posicion,COUNTIFS($A$5:$A11,">="&EOMONTH($A11,-1)+1,$A$5:$A11,"<="&EOMONTH($A11,0)),QUOTIENT(meta,semanas)+IF(posicion<=MOD(meta,semanas),1,0)),"") -> 8 | D11: =IFERROR(LET(meta,SUMIFS(Meta!$Q$5:$Q$16,Meta!$A$5:$A$16,">="&EOMONTH($A11,-1)+1,Meta!$A$5:$A$16,"<="&EOMONTH($A11,0)),semanas,COUNTIFS($A$5:$A$35,">="&EOMONTH($A11,-1)+1,$A$5:$A$35,"<="&EOMONTH($A11,0)),posicion,COUNTIFS($A$5:$A11,">="&EOMONTH($A11,-1)+1,$A$5:$A11,"<="&EOMONTH($A11,0)),QUOTIENT(meta,semanas)+IF(posicion<=MOD(meta,semanas),1,0)),"") -> 2 | E11: =IFERROR(LET(meta,SUMIFS(Meta!$C$5:$C$16,Meta!$A$5:$A$16,">="&EOMONTH($A11,-1)+1,Meta!$A$5:$A$16,"<="&EOMONTH($A11,0)),semanas,COUNTIFS($A$5:$A$35,">="&EOMONTH($A11,-1)+1,$A$5:$A$35,"<="&EOMONTH($A11,0)),posicion,COUNTIFS($A$5:$A11,">="&EOMONTH($A11,-1)+1,$A$5:$A11,"<="&EOMONTH($A11,0)),QUOTIENT(meta,semanas)+IF(posicion<=MOD(meta,semanas),1,0)),"") -> 2 | F11: =IFERROR(SUMIFS(Meta!$B$5:$B$16,Meta!$A$5:$A$16,">="&EOMONTH($A11,-1)+1,Meta!$A$5:$A$16,"<="&EOMONTH($A11,0))/COUNTIFS($A$5:$A$35,">="&EOMONTH($A11,-1)+1,$A$5:$A$35,"<="&EOMONTH($A11,0)),"") -> 80000 | G11: =COUNTIFS(Data_Ventas!$E$2:$E1001,">="&A11,Data_Ventas!$E$2:$E1001,"<="&A11+6) -> 0 | H11: =COUNTIFS(Data_Ventas!$A$2:$A1001,">="&A11,Data_Ventas!$A$2:$A1001,"<="&A11+6,Data_Ventas!$H$2:$H1001,"Visitó proyecto") -> 0 | I11: =COUNTIFS(Data_Ventas!$A$2:$A1001,">="&A11,Data_Ventas!$A$2:$A1001,"<="&A11+6,Data_Ventas!$H$2:$H1001,"Separado") -> 0 | J11: =COUNTIFS(Data_Ventas!$A$2:$A1001,">="&A11,Data_Ventas!$A$2:$A1001,"<="&A11+6,Data_Ventas!$H$2:$H1001,"Venta") -> 0 | K11: =SUMIFS(Data_Ventas!$N$2:$N1001,Data_Ventas!$A$2:$A1001,">="&A11,Data_Ventas!$A$2:$A1001,"<="&A11+6,Data_Ventas!$H$2:$H1001,"Venta") -> 0 | L11: =IFERROR(K11/F11,"0%") -> 0
A12: =A11+7 -> 46264 | B12: =IFERROR(LET(meta,SUMIFS(Meta!$N$5:$N$16,Meta!$A$5:$A$16,">="&EOMONTH($A12,-1)+1,Meta!$A$5:$A$16,"<="&EOMONTH($A12,0)),semanas,COUNTIFS($A$5:$A$35,">="&EOMONTH($A12,-1)+1,$A$5:$A$35,"<="&EOMONTH($A12,0)),posicion,COUNTIFS($A$5:$A12,">="&EOMONTH($A12,-1)+1,$A$5:$A12,"<="&EOMONTH($A12,0)),QUOTIENT(meta,semanas)+IF(posicion<=MOD(meta,semanas),1,0)),"") -> 65 | C12: =IFERROR(LET(meta,SUMIFS(Meta!$P$5:$P$16,Meta!$A$5:$A$16,">="&EOMONTH($A12,-1)+1,Meta!$A$5:$A$16,"<="&EOMONTH($A12,0)),semanas,COUNTIFS($A$5:$A$35,">="&EOMONTH($A12,-1)+1,$A$5:$A$35,"<="&EOMONTH($A12,0)),posicion,COUNTIFS($A$5:$A12,">="&EOMONTH($A12,-1)+1,$A$5:$A12,"<="&EOMONTH($A12,0)),QUOTIENT(meta,semanas)+IF(posicion<=MOD(meta,semanas),1,0)),"") -> 7 | D12: =IFERROR(LET(meta,SUMIFS(Meta!$Q$5:$Q$16,Meta!$A$5:$A$16,">="&EOMONTH($A12,-1)+1,Meta!$A$5:$A$16,"<="&EOMONTH($A12,0)),semanas,COUNTIFS($A$5:$A$35,">="&EOMONTH($A12,-1)+1,$A$5:$A$35,"<="&EOMONTH($A12,0)),posicion,COUNTIFS($A$5:$A12,">="&EOMONTH($A12,-1)+1,$A$5:$A12,"<="&EOMONTH($A12,0)),QUOTIENT(meta,semanas)+IF(posicion<=MOD(meta,semanas),1,0)),"") -> 2 | E12: =IFERROR(LET(meta,SUMIFS(Meta!$C$5:$C$16,Meta!$A$5:$A$16,">="&EOMONTH($A12,-1)+1,Meta!$A$5:$A$16,"<="&EOMONTH($A12,0)),semanas,COUNTIFS($A$5:$A$35,">="&EOMONTH($A12,-1)+1,$A$5:$A$35,"<="&EOMONTH($A12,0)),posicion,COUNTIFS($A$5:$A12,">="&EOMONTH($A12,-1)+1,$A$5:$A12,"<="&EOMONTH($A12,0)),QUOTIENT(meta,semanas)+IF(posicion<=MOD(meta,semanas),1,0)),"") -> 2 | F12: =IFERROR(SUMIFS(Meta!$B$5:$B$16,Meta!$A$5:$A$16,">="&EOMONTH($A12,-1)+1,Meta!$A$5:$A$16,"<="&EOMONTH($A12,0))/COUNTIFS($A$5:$A$35,">="&EOMONTH($A12,-1)+1,$A$5:$A$35,"<="&EOMONTH($A12,0)),"") -> 80000 | G12: =COUNTIFS(Data_Ventas!$E$2:$E1001,">="&A12,Data_Ventas!$E$2:$E1001,"<="&A12+6) -> 0 | H12: =COUNTIFS(Data_Ventas!$A$2:$A1001,">="&A12,Data_Ventas!$A$2:$A1001,"<="&A12+6,Data_Ventas!$H$2:$H1001,"Visitó proyecto") -> 0 | I12: =COUNTIFS(Data_Ventas!$A$2:$A1001,">="&A12,Data_Ventas!$A$2:$A1001,"<="&A12+6,Data_Ventas!$H$2:$H1001,"Separado") -> 0 | J12: =COUNTIFS(Data_Ventas!$A$2:$A1001,">="&A12,Data_Ventas!$A$2:$A1001,"<="&A12+6,Data_Ventas!$H$2:$H1001,"Venta") -> 2 | K12: =SUMIFS(Data_Ventas!$N$2:$N1001,Data_Ventas!$A$2:$A1001,">="&A12,Data_Ventas!$A$2:$A1001,"<="&A12+6,Data_Ventas!$H$2:$H1001,"Venta") -> 70000 | L12: =IFERROR(K12/F12,"0%") -> 0.875
A13: =A12+7 -> 46271 | B13: =IFERROR(LET(meta,SUMIFS(Meta!$N$5:$N$16,Meta!$A$5:$A$16,">="&EOMONTH($A13,-1)+1,Meta!$A$5:$A$16,"<="&EOMONTH($A13,0)),semanas,COUNTIFS($A$5:$A$35,">="&EOMONTH($A13,-1)+1,$A$5:$A$35,"<="&EOMONTH($A13,0)),posicion,COUNTIFS($A$5:$A13,">="&EOMONTH($A13,-1)+1,$A$5:$A13,"<="&EOMONTH($A13,0)),QUOTIENT(meta,semanas)+IF(posicion<=MOD(meta,semanas),1,0)),"") -> 82 | C13: =IFERROR(LET(meta,SUMIFS(Meta!$P$5:$P$16,Meta!$A$5:$A$16,">="&EOMONTH($A13,-1)+1,Meta!$A$5:$A$16,"<="&EOMONTH($A13,0)),semanas,COUNTIFS($A$5:$A$35,">="&EOMONTH($A13,-1)+1,$A$5:$A$35,"<="&EOMONTH($A13,0)),posicion,COUNTIFS($A$5:$A13,">="&EOMONTH($A13,-1)+1,$A$5:$A13,"<="&EOMONTH($A13,0)),QUOTIENT(meta,semanas)+IF(posicion<=MOD(meta,semanas),1,0)),"") -> 10 | D13: =IFERROR(LET(meta,SUMIFS(Meta!$Q$5:$Q$16,Meta!$A$5:$A$16,">="&EOMONTH($A13,-1)+1,Meta!$A$5:$A$16,"<="&EOMONTH($A13,0)),semanas,COUNTIFS($A$5:$A$35,">="&EOMONTH($A13,-1)+1,$A$5:$A$35,"<="&EOMONTH($A13,0)),posicion,COUNTIFS($A$5:$A13,">="&EOMONTH($A13,-1)+1,$A$5:$A13,"<="&EOMONTH($A13,0)),QUOTIENT(meta,semanas)+IF(posicion<=MOD(meta,semanas),1,0)),"") -> 4 | E13: =IFERROR(LET(meta,SUMIFS(Meta!$C$5:$C$16,Meta!$A$5:$A$16,">="&EOMONTH($A13,-1)+1,Meta!$A$5:$A$16,"<="&EOMONTH($A13,0)),semanas,COUNTIFS($A$5:$A$35,">="&EOMONTH($A13,-1)+1,$A$5:$A$35,"<="&EOMONTH($A13,0)),posicion,COUNTIFS($A$5:$A13,">="&EOMONTH($A13,-1)+1,$A$5:$A13,"<="&EOMONTH($A13,0)),QUOTIENT(meta,semanas)+IF(posicion<=MOD(meta,semanas),1,0)),"") -> 3 | F13: =IFERROR(SUMIFS(Meta!$B$5:$B$16,Meta!$A$5:$A$16,">="&EOMONTH($A13,-1)+1,Meta!$A$5:$A$16,"<="&EOMONTH($A13,0))/COUNTIFS($A$5:$A$35,">="&EOMONTH($A13,-1)+1,$A$5:$A$35,"<="&EOMONTH($A13,0)),"") -> 100000 | G13: =COUNTIFS(Data_Ventas!$E$2:$E1001,">="&A13,Data_Ventas!$E$2:$E1001,"<="&A13+6) -> 0 | H13: =COUNTIFS(Data_Ventas!$A$2:$A1001,">="&A13,Data_Ventas!$A$2:$A1001,"<="&A13+6,Data_Ventas!$H$2:$H1001,"Visitó proyecto") -> 0 | I13: =COUNTIFS(Data_Ventas!$A$2:$A1001,">="&A13,Data_Ventas!$A$2:$A1001,"<="&A13+6,Data_Ventas!$H$2:$H1001,"Separado") -> 0 | J13: =COUNTIFS(Data_Ventas!$A$2:$A1001,">="&A13,Data_Ventas!$A$2:$A1001,"<="&A13+6,Data_Ventas!$H$2:$H1001,"Venta") -> 1 | K13: =SUMIFS(Data_Ventas!$N$2:$N1001,Data_Ventas!$A$2:$A1001,">="&A13,Data_Ventas!$A$2:$A1001,"<="&A13+6,Data_Ventas!$H$2:$H1001,"Venta") -> 40000 | L13: =IFERROR(K13/F13,"0%") -> 0.4
A14: =A13+7 -> 46278 | B14: =IFERROR(LET(meta,SUMIFS(Meta!$N$5:$N$16,Meta!$A$5:$A$16,">="&EOMONTH($A14,-1)+1,Meta!$A$5:$A$16,"<="&EOMONTH($A14,0)),semanas,COUNTIFS($A$5:$A$35,">="&EOMONTH($A14,-1)+1,$A$5:$A$35,"<="&EOMONTH($A14,0)),posicion,COUNTIFS($A$5:$A14,">="&EOMONTH($A14,-1)+1,$A$5:$A14,"<="&EOMONTH($A14,0)),QUOTIENT(meta,semanas)+IF(posicion<=MOD(meta,semanas),1,0)),"") -> 81 | C14: =IFERROR(LET(meta,SUMIFS(Meta!$P$5:$P$16,Meta!$A$5:$A$16,">="&EOMONTH($A14,-1)+1,Meta!$A$5:$A$16,"<="&EOMONTH($A14,0)),semanas,COUNTIFS($A$5:$A$35,">="&EOMONTH($A14,-1)+1,$A$5:$A$35,"<="&EOMONTH($A14,0)),posicion,COUNTIFS($A$5:$A14,">="&EOMONTH($A14,-1)+1,$A$5:$A14,"<="&EOMONTH($A14,0)),QUOTIENT(meta,semanas)+IF(posicion<=MOD(meta,semanas),1,0)),"") -> 10 | D14: =IFERROR(LET(meta,SUMIFS(Meta!$Q$5:$Q$16,Meta!$A$5:$A$16,">="&EOMONTH($A14,-1)+1,Meta!$A$5:$A$16,"<="&EOMONTH($A14,0)),semanas,COUNTIFS($A$5:$A$35,">="&EOMONTH($A14,-1)+1,$A$5:$A$35,"<="&EOMONTH($A14,0)),posicion,COUNTIFS($A$5:$A14,">="&EOMONTH($A14,-1)+1,$A$5:$A14,"<="&EOMONTH($A14,0)),QUOTIENT(meta,semanas)+IF(posicion<=MOD(meta,semanas),1,0)),"") -> 3 | E14: =IFERROR(LET(meta,SUMIFS(Meta!$C$5:$C$16,Meta!$A$5:$A$16,">="&EOMONTH($A14,-1)+1,Meta!$A$5:$A$16,"<="&EOMONTH($A14,0)),semanas,COUNTIFS($A$5:$A$35,">="&EOMONTH($A14,-1)+1,$A$5:$A$35,"<="&EOMONTH($A14,0)),posicion,COUNTIFS($A$5:$A14,">="&EOMONTH($A14,-1)+1,$A$5:$A14,"<="&EOMONTH($A14,0)),QUOTIENT(meta,semanas)+IF(posicion<=MOD(meta,semanas),1,0)),"") -> 3 | F14: =IFERROR(SUMIFS(Meta!$B$5:$B$16,Meta!$A$5:$A$16,">="&EOMONTH($A14,-1)+1,Meta!$A$5:$A$16,"<="&EOMONTH($A14,0))/COUNTIFS($A$5:$A$35,">="&EOMONTH($A14,-1)+1,$A$5:$A$35,"<="&EOMONTH($A14,0)),"") -> 100000 | G14: =COUNTIFS(Data_Ventas!$E$2:$E1001,">="&A14,Data_Ventas!$E$2:$E1001,"<="&A14+6) -> 0 | H14: =COUNTIFS(Data_Ventas!$A$2:$A1001,">="&A14,Data_Ventas!$A$2:$A1001,"<="&A14+6,Data_Ventas!$H$2:$H1001,"Visitó proyecto") -> 0 | I14: =COUNTIFS(Data_Ventas!$A$2:$A1001,">="&A14,Data_Ventas!$A$2:$A1001,"<="&A14+6,Data_Ventas!$H$2:$H1001,"Separado") -> 0 | J14: =COUNTIFS(Data_Ventas!$A$2:$A1001,">="&A14,Data_Ventas!$A$2:$A1001,"<="&A14+6,Data_Ventas!$H$2:$H1001,"Venta") -> 0 | K14: =SUMIFS(Data_Ventas!$N$2:$N1001,Data_Ventas!$A$2:$A1001,">="&A14,Data_Ventas!$A$2:$A1001,"<="&A14+6,Data_Ventas!$H$2:$H1001,"Venta") -> 0 | L14: =IFERROR(K14/F14,"0%") -> 0
A15: =A14+7 -> 46285 | B15: =IFERROR(LET(meta,SUMIFS(Meta!$N$5:$N$16,Meta!$A$5:$A$16,">="&EOMONTH($A15,-1)+1,Meta!$A$5:$A$16,"<="&EOMONTH($A15,0)),semanas,COUNTIFS($A$5:$A$35,">="&EOMONTH($A15,-1)+1,$A$5:$A$35,"<="&EOMONTH($A15,0)),posicion,COUNTIFS($A$5:$A15,">="&EOMONTH($A15,-1)+1,$A$5:$A15,"<="&EOMONTH($A15,0)),QUOTIENT(meta,semanas)+IF(posicion<=MOD(meta,semanas),1,0)),"") -> 81 | C15: =IFERROR(LET(meta,SUMIFS(Meta!$P$5:$P$16,Meta!$A$5:$A$16,">="&EOMONTH($A15,-1)+1,Meta!$A$5:$A$16,"<="&EOMONTH($A15,0)),semanas,COUNTIFS($A$5:$A$35,">="&EOMONTH($A15,-1)+1,$A$5:$A$35,"<="&EOMONTH($A15,0)),posicion,COUNTIFS($A$5:$A15,">="&EOMONTH($A15,-1)+1,$A$5:$A15,"<="&EOMONTH($A15,0)),QUOTIENT(meta,semanas)+IF(posicion<=MOD(meta,semanas),1,0)),"") -> 10 | D15: =IFERROR(LET(meta,SUMIFS(Meta!$Q$5:$Q$16,Meta!$A$5:$A$16,">="&EOMONTH($A15,-1)+1,Meta!$A$5:$A$16,"<="&EOMONTH($A15,0)),semanas,COUNTIFS($A$5:$A$35,">="&EOMONTH($A15,-1)+1,$A$5:$A$35,"<="&EOMONTH($A15,0)),posicion,COUNTIFS($A$5:$A15,">="&EOMONTH($A15,-1)+1,$A$5:$A15,"<="&EOMONTH($A15,0)),QUOTIENT(meta,semanas)+IF(posicion<=MOD(meta,semanas),1,0)),"") -> 3 | E15: =IFERROR(LET(meta,SUMIFS(Meta!$C$5:$C$16,Meta!$A$5:$A$16,">="&EOMONTH($A15,-1)+1,Meta!$A$5:$A$16,"<="&EOMONTH($A15,0)),semanas,COUNTIFS($A$5:$A$35,">="&EOMONTH($A15,-1)+1,$A$5:$A$35,"<="&EOMONTH($A15,0)),posicion,COUNTIFS($A$5:$A15,">="&EOMONTH($A15,-1)+1,$A$5:$A15,"<="&EOMONTH($A15,0)),QUOTIENT(meta,semanas)+IF(posicion<=MOD(meta,semanas),1,0)),"") -> 2 | F15: =IFERROR(SUMIFS(Meta!$B$5:$B$16,Meta!$A$5:$A$16,">="&EOMONTH($A15,-1)+1,Meta!$A$5:$A$16,"<="&EOMONTH($A15,0))/COUNTIFS($A$5:$A$35,">="&EOMONTH($A15,-1)+1,$A$5:$A$35,"<="&EOMONTH($A15,0)),"") -> 100000 | G15: =COUNTIFS(Data_Ventas!$E$2:$E1001,">="&A15,Data_Ventas!$E$2:$E1001,"<="&A15+6) -> 0 | H15: =COUNTIFS(Data_Ventas!$A$2:$A1001,">="&A15,Data_Ventas!$A$2:$A1001,"<="&A15+6,Data_Ventas!$H$2:$H1001,"Visitó proyecto") -> 0 | I15: =COUNTIFS(Data_Ventas!$A$2:$A1001,">="&A15,Data_Ventas!$A$2:$A1001,"<="&A15+6,Data_Ventas!$H$2:$H1001,"Separado") -> 0 | J15: =COUNTIFS(Data_Ventas!$A$2:$A1001,">="&A15,Data_Ventas!$A$2:$A1001,"<="&A15+6,Data_Ventas!$H$2:$H1001,"Venta") -> 0 | K15: =SUMIFS(Data_Ventas!$N$2:$N1001,Data_Ventas!$A$2:$A1001,">="&A15,Data_Ventas!$A$2:$A1001,"<="&A15+6,Data_Ventas!$H$2:$H1001,"Venta") -> 0 | L15: =IFERROR(K15/F15,"0%") -> 0
A16: =A15+7 -> 46292 | B16: =IFERROR(LET(meta,SUMIFS(Meta!$N$5:$N$16,Meta!$A$5:$A$16,">="&EOMONTH($A16,-1)+1,Meta!$A$5:$A$16,"<="&EOMONTH($A16,0)),semanas,COUNTIFS($A$5:$A$35,">="&EOMONTH($A16,-1)+1,$A$5:$A$35,"<="&EOMONTH($A16,0)),posicion,COUNTIFS($A$5:$A16,">="&EOMONTH($A16,-1)+1,$A$5:$A16,"<="&EOMONTH($A16,0)),QUOTIENT(meta,semanas)+IF(posicion<=MOD(meta,semanas),1,0)),"") -> 81 | C16: =IFERROR(LET(meta,SUMIFS(Meta!$P$5:$P$16,Meta!$A$5:$A$16,">="&EOMONTH($A16,-1)+1,Meta!$A$5:$A$16,"<="&EOMONTH($A16,0)),semanas,COUNTIFS($A$5:$A$35,">="&EOMONTH($A16,-1)+1,$A$5:$A$35,"<="&EOMONTH($A16,0)),posicion,COUNTIFS($A$5:$A16,">="&EOMONTH($A16,-1)+1,$A$5:$A16,"<="&EOMONTH($A16,0)),QUOTIENT(meta,semanas)+IF(posicion<=MOD(meta,semanas),1,0)),"") -> 9 | D16: =IFERROR(LET(meta,SUMIFS(Meta!$Q$5:$Q$16,Meta!$A$5:$A$16,">="&EOMONTH($A16,-1)+1,Meta!$A$5:$A$16,"<="&EOMONTH($A16,0)),semanas,COUNTIFS($A$5:$A$35,">="&EOMONTH($A16,-1)+1,$A$5:$A$35,"<="&EOMONTH($A16,0)),posicion,COUNTIFS($A$5:$A16,">="&EOMONTH($A16,-1)+1,$A$5:$A16,"<="&EOMONTH($A16,0)),QUOTIENT(meta,semanas)+IF(posicion<=MOD(meta,semanas),1,0)),"") -> 3 | E16: =IFERROR(LET(meta,SUMIFS(Meta!$C$5:$C$16,Meta!$A$5:$A$16,">="&EOMONTH($A16,-1)+1,Meta!$A$5:$A$16,"<="&EOMONTH($A16,0)),semanas,COUNTIFS($A$5:$A$35,">="&EOMONTH($A16,-1)+1,$A$5:$A$35,"<="&EOMONTH($A16,0)),posicion,COUNTIFS($A$5:$A16,">="&EOMONTH($A16,-1)+1,$A$5:$A16,"<="&EOMONTH($A16,0)),QUOTIENT(meta,semanas)+IF(posicion<=MOD(meta,semanas),1,0)),"") -> 2 | F16: =IFERROR(SUMIFS(Meta!$B$5:$B$16,Meta!$A$5:$A$16,">="&EOMONTH($A16,-1)+1,Meta!$A$5:$A$16,"<="&EOMONTH($A16,0))/COUNTIFS($A$5:$A$35,">="&EOMONTH($A16,-1)+1,$A$5:$A$35,"<="&EOMONTH($A16,0)),"") -> 100000 | G16: =COUNTIFS(Data_Ventas!$E$2:$E1001,">="&A16,Data_Ventas!$E$2:$E1001,"<="&A16+6) -> 0 | H16: =COUNTIFS(Data_Ventas!$A$2:$A1001,">="&A16,Data_Ventas!$A$2:$A1001,"<="&A16+6,Data_Ventas!$H$2:$H1001,"Visitó proyecto") -> 0 | I16: =COUNTIFS(Data_Ventas!$A$2:$A1001,">="&A16,Data_Ventas!$A$2:$A1001,"<="&A16+6,Data_Ventas!$H$2:$H1001,"Separado") -> 0 | J16: =COUNTIFS(Data_Ventas!$A$2:$A1001,">="&A16,Data_Ventas!$A$2:$A1001,"<="&A16+6,Data_Ventas!$H$2:$H1001,"Venta") -> 0 | K16: =SUMIFS(Data_Ventas!$N$2:$N1001,Data_Ventas!$A$2:$A1001,">="&A16,Data_Ventas!$A$2:$A1001,"<="&A16+6,Data_Ventas!$H$2:$H1001,"Venta") -> 0 | L16: =IFERROR(K16/F16,"0%") -> 0
A17: =A16+7 -> 46299 | B17: =IFERROR(LET(meta,SUMIFS(Meta!$N$5:$N$16,Meta!$A$5:$A$16,">="&EOMONTH($A17,-1)+1,Meta!$A$5:$A$16,"<="&EOMONTH($A17,0)),semanas,COUNTIFS($A$5:$A$35,">="&EOMONTH($A17,-1)+1,$A$5:$A$35,"<="&EOMONTH($A17,0)),posicion,COUNTIFS($A$5:$A17,">="&EOMONTH($A17,-1)+1,$A$5:$A17,"<="&EOMONTH($A17,0)),QUOTIENT(meta,semanas)+IF(posicion<=MOD(meta,semanas),1,0)),"") -> 82 | C17: =IFERROR(LET(meta,SUMIFS(Meta!$P$5:$P$16,Meta!$A$5:$A$16,">="&EOMONTH($A17,-1)+1,Meta!$A$5:$A$16,"<="&EOMONTH($A17,0)),semanas,COUNTIFS($A$5:$A$35,">="&EOMONTH($A17,-1)+1,$A$5:$A$35,"<="&EOMONTH($A17,0)),posicion,COUNTIFS($A$5:$A17,">="&EOMONTH($A17,-1)+1,$A$5:$A17,"<="&EOMONTH($A17,0)),QUOTIENT(meta,semanas)+IF(posicion<=MOD(meta,semanas),1,0)),"") -> 10 | D17: =IFERROR(LET(meta,SUMIFS(Meta!$Q$5:$Q$16,Meta!$A$5:$A$16,">="&EOMONTH($A17,-1)+1,Meta!$A$5:$A$16,"<="&EOMONTH($A17,0)),semanas,COUNTIFS($A$5:$A$35,">="&EOMONTH($A17,-1)+1,$A$5:$A$35,"<="&EOMONTH($A17,0)),posicion,COUNTIFS($A$5:$A17,">="&EOMONTH($A17,-1)+1,$A$5:$A17,"<="&EOMONTH($A17,0)),QUOTIENT(meta,semanas)+IF(posicion<=MOD(meta,semanas),1,0)),"") -> 4 | E17: =IFERROR(LET(meta,SUMIFS(Meta!$C$5:$C$16,Meta!$A$5:$A$16,">="&EOMONTH($A17,-1)+1,Meta!$A$5:$A$16,"<="&EOMONTH($A17,0)),semanas,COUNTIFS($A$5:$A$35,">="&EOMONTH($A17,-1)+1,$A$5:$A$35,"<="&EOMONTH($A17,0)),posicion,COUNTIFS($A$5:$A17,">="&EOMONTH($A17,-1)+1,$A$5:$A17,"<="&EOMONTH($A17,0)),QUOTIENT(meta,semanas)+IF(posicion<=MOD(meta,semanas),1,0)),"") -> 3 | F17: =IFERROR(SUMIFS(Meta!$B$5:$B$16,Meta!$A$5:$A$16,">="&EOMONTH($A17,-1)+1,Meta!$A$5:$A$16,"<="&EOMONTH($A17,0))/COUNTIFS($A$5:$A$35,">="&EOMONTH($A17,-1)+1,$A$5:$A$35,"<="&EOMONTH($A17,0)),"") -> 100000 | G17: =COUNTIFS(Data_Ventas!$E$2:$E1001,">="&A17,Data_Ventas!$E$2:$E1001,"<="&A17+6) -> 0 | H17: =COUNTIFS(Data_Ventas!$A$2:$A1001,">="&A17,Data_Ventas!$A$2:$A1001,"<="&A17+6,Data_Ventas!$H$2:$H1001,"Visitó proyecto") -> 0 | I17: =COUNTIFS(Data_Ventas!$A$2:$A1001,">="&A17,Data_Ventas!$A$2:$A1001,"<="&A17+6,Data_Ventas!$H$2:$H1001,"Separado") -> 0 | J17: =COUNTIFS(Data_Ventas!$A$2:$A1001,">="&A17,Data_Ventas!$A$2:$A1001,"<="&A17+6,Data_Ventas!$H$2:$H1001,"Venta") -> 0 | K17: =SUMIFS(Data_Ventas!$N$2:$N1001,Data_Ventas!$A$2:$A1001,">="&A17,Data_Ventas!$A$2:$A1001,"<="&A17+6,Data_Ventas!$H$2:$H1001,"Venta") -> 0 | L17: =IFERROR(K17/F17,"0%") -> 0
A18: =A17+7 -> 46306 | B18: =IFERROR(LET(meta,SUMIFS(Meta!$N$5:$N$16,Meta!$A$5:$A$16,">="&EOMONTH($A18,-1)+1,Meta!$A$5:$A$16,"<="&EOMONTH($A18,0)),semanas,COUNTIFS($A$5:$A$35,">="&EOMONTH($A18,-1)+1,$A$5:$A$35,"<="&EOMONTH($A18,0)),posicion,COUNTIFS($A$5:$A18,">="&EOMONTH($A18,-1)+1,$A$5:$A18,"<="&EOMONTH($A18,0)),QUOTIENT(meta,semanas)+IF(posicion<=MOD(meta,semanas),1,0)),"") -> 81 | C18: =IFERROR(LET(meta,SUMIFS(Meta!$P$5:$P$16,Meta!$A$5:$A$16,">="&EOMONTH($A18,-1)+1,Meta!$A$5:$A$16,"<="&EOMONTH($A18,0)),semanas,COUNTIFS($A$5:$A$35,">="&EOMONTH($A18,-1)+1,$A$5:$A$35,"<="&EOMONTH($A18,0)),posicion,COUNTIFS($A$5:$A18,">="&EOMONTH($A18,-1)+1,$A$5:$A18,"<="&EOMONTH($A18,0)),QUOTIENT(meta,semanas)+IF(posicion<=MOD(meta,semanas),1,0)),"") -> 10 | D18: =IFERROR(LET(meta,SUMIFS(Meta!$Q$5:$Q$16,Meta!$A$5:$A$16,">="&EOMONTH($A18,-1)+1,Meta!$A$5:$A$16,"<="&EOMONTH($A18,0)),semanas,COUNTIFS($A$5:$A$35,">="&EOMONTH($A18,-1)+1,$A$5:$A$35,"<="&EOMONTH($A18,0)),posicion,COUNTIFS($A$5:$A18,">="&EOMONTH($A18,-1)+1,$A$5:$A18,"<="&EOMONTH($A18,0)),QUOTIENT(meta,semanas)+IF(posicion<=MOD(meta,semanas),1,0)),"") -> 3 | E18: =IFERROR(LET(meta,SUMIFS(Meta!$C$5:$C$16,Meta!$A$5:$A$16,">="&EOMONTH($A18,-1)+1,Meta!$A$5:$A$16,"<="&EOMONTH($A18,0)),semanas,COUNTIFS($A$5:$A$35,">="&EOMONTH($A18,-1)+1,$A$5:$A$35,"<="&EOMONTH($A18,0)),posicion,COUNTIFS($A$5:$A18,">="&EOMONTH($A18,-1)+1,$A$5:$A18,"<="&EOMONTH($A18,0)),QUOTIENT(meta,semanas)+IF(posicion<=MOD(meta,semanas),1,0)),"") -> 3 | F18: =IFERROR(SUMIFS(Meta!$B$5:$B$16,Meta!$A$5:$A$16,">="&EOMONTH($A18,-1)+1,Meta!$A$5:$A$16,"<="&EOMONTH($A18,0))/COUNTIFS($A$5:$A$35,">="&EOMONTH($A18,-1)+1,$A$5:$A$35,"<="&EOMONTH($A18,0)),"") -> 100000 | G18: =COUNTIFS(Data_Ventas!$E$2:$E1001,">="&A18,Data_Ventas!$E$2:$E1001,"<="&A18+6) -> 0 | H18: =COUNTIFS(Data_Ventas!$A$2:$A1001,">="&A18,Data_Ventas!$A$2:$A1001,"<="&A18+6,Data_Ventas!$H$2:$H1001,"Visitó proyecto") -> 0 | I18: =COUNTIFS(Data_Ventas!$A$2:$A1001,">="&A18,Data_Ventas!$A$2:$A1001,"<="&A18+6,Data_Ventas!$H$2:$H1001,"Separado") -> 0 | J18: =COUNTIFS(Data_Ventas!$A$2:$A1001,">="&A18,Data_Ventas!$A$2:$A1001,"<="&A18+6,Data_Ventas!$H$2:$H1001,"Venta") -> 0 | K18: =SUMIFS(Data_Ventas!$N$2:$N1001,Data_Ventas!$A$2:$A1001,">="&A18,Data_Ventas!$A$2:$A1001,"<="&A18+6,Data_Ventas!$H$2:$H1001,"Venta") -> 0 | L18: =IFERROR(K18/F18,"0%") -> 0
A19: =A18+7 -> 46313 | B19: =IFERROR(LET(meta,SUMIFS(Meta!$N$5:$N$16,Meta!$A$5:$A$16,">="&EOMONTH($A19,-1)+1,Meta!$A$5:$A$16,"<="&EOMONTH($A19,0)),semanas,COUNTIFS($A$5:$A$35,">="&EOMONTH($A19,-1)+1,$A$5:$A$35,"<="&EOMONTH($A19,0)),posicion,COUNTIFS($A$5:$A19,">="&EOMONTH($A19,-1)+1,$A$5:$A19,"<="&EOMONTH($A19,0)),QUOTIENT(meta,semanas)+IF(posicion<=MOD(meta,semanas),1,0)),"") -> 81 | C19: =IFERROR(LET(meta,SUMIFS(Meta!$P$5:$P$16,Meta!$A$5:$A$16,">="&EOMONTH($A19,-1)+1,Meta!$A$5:$A$16,"<="&EOMONTH($A19,0)),semanas,COUNTIFS($A$5:$A$35,">="&EOMONTH($A19,-1)+1,$A$5:$A$35,"<="&EOMONTH($A19,0)),posicion,COUNTIFS($A$5:$A19,">="&EOMONTH($A19,-1)+1,$A$5:$A19,"<="&EOMONTH($A19,0)),QUOTIENT(meta,semanas)+IF(posicion<=MOD(meta,semanas),1,0)),"") -> 10 | D19: =IFERROR(LET(meta,SUMIFS(Meta!$Q$5:$Q$16,Meta!$A$5:$A$16,">="&EOMONTH($A19,-1)+1,Meta!$A$5:$A$16,"<="&EOMONTH($A19,0)),semanas,COUNTIFS($A$5:$A$35,">="&EOMONTH($A19,-1)+1,$A$5:$A$35,"<="&EOMONTH($A19,0)),posicion,COUNTIFS($A$5:$A19,">="&EOMONTH($A19,-1)+1,$A$5:$A19,"<="&EOMONTH($A19,0)),QUOTIENT(meta,semanas)+IF(posicion<=MOD(meta,semanas),1,0)),"") -> 3 | E19: =IFERROR(LET(meta,SUMIFS(Meta!$C$5:$C$16,Meta!$A$5:$A$16,">="&EOMONTH($A19,-1)+1,Meta!$A$5:$A$16,"<="&EOMONTH($A19,0)),semanas,COUNTIFS($A$5:$A$35,">="&EOMONTH($A19,-1)+1,$A$5:$A$35,"<="&EOMONTH($A19,0)),posicion,COUNTIFS($A$5:$A19,">="&EOMONTH($A19,-1)+1,$A$5:$A19,"<="&EOMONTH($A19,0)),QUOTIENT(meta,semanas)+IF(posicion<=MOD(meta,semanas),1,0)),"") -> 2 | F19: =IFERROR(SUMIFS(Meta!$B$5:$B$16,Meta!$A$5:$A$16,">="&EOMONTH($A19,-1)+1,Meta!$A$5:$A$16,"<="&EOMONTH($A19,0))/COUNTIFS($A$5:$A$35,">="&EOMONTH($A19,-1)+1,$A$5:$A$35,"<="&EOMONTH($A19,0)),"") -> 100000 | G19: =COUNTIFS(Data_Ventas!$E$2:$E1001,">="&A19,Data_Ventas!$E$2:$E1001,"<="&A19+6) -> 0 | H19: =COUNTIFS(Data_Ventas!$A$2:$A1001,">="&A19,Data_Ventas!$A$2:$A1001,"<="&A19+6,Data_Ventas!$H$2:$H1001,"Visitó proyecto") -> 0 | I19: =COUNTIFS(Data_Ventas!$A$2:$A1001,">="&A19,Data_Ventas!$A$2:$A1001,"<="&A19+6,Data_Ventas!$H$2:$H1001,"Separado") -> 0 | J19: =COUNTIFS(Data_Ventas!$A$2:$A1001,">="&A19,Data_Ventas!$A$2:$A1001,"<="&A19+6,Data_Ventas!$H$2:$H1001,"Venta") -> 0 | K19: =SUMIFS(Data_Ventas!$N$2:$N1001,Data_Ventas!$A$2:$A1001,">="&A19,Data_Ventas!$A$2:$A1001,"<="&A19+6,Data_Ventas!$H$2:$H1001,"Venta") -> 0 | L19: =IFERROR(K19/F19,"0%") -> 0
A20: =A19+7 -> 46320 | B20: =IFERROR(LET(meta,SUMIFS(Meta!$N$5:$N$16,Meta!$A$5:$A$16,">="&EOMONTH($A20,-1)+1,Meta!$A$5:$A$16,"<="&EOMONTH($A20,0)),semanas,COUNTIFS($A$5:$A$35,">="&EOMONTH($A20,-1)+1,$A$5:$A$35,"<="&EOMONTH($A20,0)),posicion,COUNTIFS($A$5:$A20,">="&EOMONTH($A20,-1)+1,$A$5:$A20,"<="&EOMONTH($A20,0)),QUOTIENT(meta,semanas)+IF(posicion<=MOD(meta,semanas),1,0)),"") -> 81 | C20: =IFERROR(LET(meta,SUMIFS(Meta!$P$5:$P$16,Meta!$A$5:$A$16,">="&EOMONTH($A20,-1)+1,Meta!$A$5:$A$16,"<="&EOMONTH($A20,0)),semanas,COUNTIFS($A$5:$A$35,">="&EOMONTH($A20,-1)+1,$A$5:$A$35,"<="&EOMONTH($A20,0)),posicion,COUNTIFS($A$5:$A20,">="&EOMONTH($A20,-1)+1,$A$5:$A20,"<="&EOMONTH($A20,0)),QUOTIENT(meta,semanas)+IF(posicion<=MOD(meta,semanas),1,0)),"") -> 9 | D20: =IFERROR(LET(meta,SUMIFS(Meta!$Q$5:$Q$16,Meta!$A$5:$A$16,">="&EOMONTH($A20,-1)+1,Meta!$A$5:$A$16,"<="&EOMONTH($A20,0)),semanas,COUNTIFS($A$5:$A$35,">="&EOMONTH($A20,-1)+1,$A$5:$A$35,"<="&EOMONTH($A20,0)),posicion,COUNTIFS($A$5:$A20,">="&EOMONTH($A20,-1)+1,$A$5:$A20,"<="&EOMONTH($A20,0)),QUOTIENT(meta,semanas)+IF(posicion<=MOD(meta,semanas),1,0)),"") -> 3 | E20: =IFERROR(LET(meta,SUMIFS(Meta!$C$5:$C$16,Meta!$A$5:$A$16,">="&EOMONTH($A20,-1)+1,Meta!$A$5:$A$16,"<="&EOMONTH($A20,0)),semanas,COUNTIFS($A$5:$A$35,">="&EOMONTH($A20,-1)+1,$A$5:$A$35,"<="&EOMONTH($A20,0)),posicion,COUNTIFS($A$5:$A20,">="&EOMONTH($A20,-1)+1,$A$5:$A20,"<="&EOMONTH($A20,0)),QUOTIENT(meta,semanas)+IF(posicion<=MOD(meta,semanas),1,0)),"") -> 2 | F20: =IFERROR(SUMIFS(Meta!$B$5:$B$16,Meta!$A$5:$A$16,">="&EOMONTH($A20,-1)+1,Meta!$A$5:$A$16,"<="&EOMONTH($A20,0))/COUNTIFS($A$5:$A$35,">="&EOMONTH($A20,-1)+1,$A$5:$A$35,"<="&EOMONTH($A20,0)),"") -> 100000 | G20: =COUNTIFS(Data_Ventas!$E$2:$E1001,">="&A20,Data_Ventas!$E$2:$E1001,"<="&A20+6) -> 0 | H20: =COUNTIFS(Data_Ventas!$A$2:$A1001,">="&A20,Data_Ventas!$A$2:$A1001,"<="&A20+6,Data_Ventas!$H$2:$H1001,"Visitó proyecto") -> 0 | I20: =COUNTIFS(Data_Ventas!$A$2:$A1001,">="&A20,Data_Ventas!$A$2:$A1001,"<="&A20+6,Data_Ventas!$H$2:$H1001,"Separado") -> 0 | J20: =COUNTIFS(Data_Ventas!$A$2:$A1001,">="&A20,Data_Ventas!$A$2:$A1001,"<="&A20+6,Data_Ventas!$H$2:$H1001,"Venta") -> 0 | K20: =SUMIFS(Data_Ventas!$N$2:$N1001,Data_Ventas!$A$2:$A1001,">="&A20,Data_Ventas!$A$2:$A1001,"<="&A20+6,Data_Ventas!$H$2:$H1001,"Venta") -> 0 | L20: =IFERROR(K20/F20,"0%") -> 0
A21: =A20+7 -> 46327 | B21: =IFERROR(LET(meta,SUMIFS(Meta!$N$5:$N$16,Meta!$A$5:$A$16,">="&EOMONTH($A21,-1)+1,Meta!$A$5:$A$16,"<="&EOMONTH($A21,0)),semanas,COUNTIFS($A$5:$A$35,">="&EOMONTH($A21,-1)+1,$A$5:$A$35,"<="&EOMONTH($A21,0)),posicion,COUNTIFS($A$5:$A21,">="&EOMONTH($A21,-1)+1,$A$5:$A21,"<="&EOMONTH($A21,0)),QUOTIENT(meta,semanas)+IF(posicion<=MOD(meta,semanas),1,0)),"") -> 65 | C21: =IFERROR(LET(meta,SUMIFS(Meta!$P$5:$P$16,Meta!$A$5:$A$16,">="&EOMONTH($A21,-1)+1,Meta!$A$5:$A$16,"<="&EOMONTH($A21,0)),semanas,COUNTIFS($A$5:$A$35,">="&EOMONTH($A21,-1)+1,$A$5:$A$35,"<="&EOMONTH($A21,0)),posicion,COUNTIFS($A$5:$A21,">="&EOMONTH($A21,-1)+1,$A$5:$A21,"<="&EOMONTH($A21,0)),QUOTIENT(meta,semanas)+IF(posicion<=MOD(meta,semanas),1,0)),"") -> 8 | D21: =IFERROR(LET(meta,SUMIFS(Meta!$Q$5:$Q$16,Meta!$A$5:$A$16,">="&EOMONTH($A21,-1)+1,Meta!$A$5:$A$16,"<="&EOMONTH($A21,0)),semanas,COUNTIFS($A$5:$A$35,">="&EOMONTH($A21,-1)+1,$A$5:$A$35,"<="&EOMONTH($A21,0)),posicion,COUNTIFS($A$5:$A21,">="&EOMONTH($A21,-1)+1,$A$5:$A21,"<="&EOMONTH($A21,0)),QUOTIENT(meta,semanas)+IF(posicion<=MOD(meta,semanas),1,0)),"") -> 3 | E21: =IFERROR(LET(meta,SUMIFS(Meta!$C$5:$C$16,Meta!$A$5:$A$16,">="&EOMONTH($A21,-1)+1,Meta!$A$5:$A$16,"<="&EOMONTH($A21,0)),semanas,COUNTIFS($A$5:$A$35,">="&EOMONTH($A21,-1)+1,$A$5:$A$35,"<="&EOMONTH($A21,0)),posicion,COUNTIFS($A$5:$A21,">="&EOMONTH($A21,-1)+1,$A$5:$A21,"<="&EOMONTH($A21,0)),QUOTIENT(meta,semanas)+IF(posicion<=MOD(meta,semanas),1,0)),"") -> 2 | F21: =IFERROR(SUMIFS(Meta!$B$5:$B$16,Meta!$A$5:$A$16,">="&EOMONTH($A21,-1)+1,Meta!$A$5:$A$16,"<="&EOMONTH($A21,0))/COUNTIFS($A$5:$A$35,">="&EOMONTH($A21,-1)+1,$A$5:$A$35,"<="&EOMONTH($A21,0)),"") -> 80000 | G21: =COUNTIFS(Data_Ventas!$E$2:$E1001,">="&A21,Data_Ventas!$E$2:$E1001,"<="&A21+6) -> 0 | H21: =COUNTIFS(Data_Ventas!$A$2:$A1001,">="&A21,Data_Ventas!$A$2:$A1001,"<="&A21+6,Data_Ventas!$H$2:$H1001,"Visitó proyecto") -> 0 | I21: =COUNTIFS(Data_Ventas!$A$2:$A1001,">="&A21,Data_Ventas!$A$2:$A1001,"<="&A21+6,Data_Ventas!$H$2:$H1001,"Separado") -> 0 | J21: =COUNTIFS(Data_Ventas!$A$2:$A1001,">="&A21,Data_Ventas!$A$2:$A1001,"<="&A21+6,Data_Ventas!$H$2:$H1001,"Venta") -> 0 | K21: =SUMIFS(Data_Ventas!$N$2:$N1001,Data_Ventas!$A$2:$A1001,">="&A21,Data_Ventas!$A$2:$A1001,"<="&A21+6,Data_Ventas!$H$2:$H1001,"Venta") -> 0 | L21: =IFERROR(K21/F21,"0%") -> 0
A22: =A21+7 -> 46334 | B22: =IFERROR(LET(meta,SUMIFS(Meta!$N$5:$N$16,Meta!$A$5:$A$16,">="&EOMONTH($A22,-1)+1,Meta!$A$5:$A$16,"<="&EOMONTH($A22,0)),semanas,COUNTIFS($A$5:$A$35,">="&EOMONTH($A22,-1)+1,$A$5:$A$35,"<="&EOMONTH($A22,0)),posicion,COUNTIFS($A$5:$A22,">="&EOMONTH($A22,-1)+1,$A$5:$A22,"<="&EOMONTH($A22,0)),QUOTIENT(meta,semanas)+IF(posicion<=MOD(meta,semanas),1,0)),"") -> 65 | C22: =IFERROR(LET(meta,SUMIFS(Meta!$P$5:$P$16,Meta!$A$5:$A$16,">="&EOMONTH($A22,-1)+1,Meta!$A$5:$A$16,"<="&EOMONTH($A22,0)),semanas,COUNTIFS($A$5:$A$35,">="&EOMONTH($A22,-1)+1,$A$5:$A$35,"<="&EOMONTH($A22,0)),posicion,COUNTIFS($A$5:$A22,">="&EOMONTH($A22,-1)+1,$A$5:$A22,"<="&EOMONTH($A22,0)),QUOTIENT(meta,semanas)+IF(posicion<=MOD(meta,semanas),1,0)),"") -> 8 | D22: =IFERROR(LET(meta,SUMIFS(Meta!$Q$5:$Q$16,Meta!$A$5:$A$16,">="&EOMONTH($A22,-1)+1,Meta!$A$5:$A$16,"<="&EOMONTH($A22,0)),semanas,COUNTIFS($A$5:$A$35,">="&EOMONTH($A22,-1)+1,$A$5:$A$35,"<="&EOMONTH($A22,0)),posicion,COUNTIFS($A$5:$A22,">="&EOMONTH($A22,-1)+1,$A$5:$A22,"<="&EOMONTH($A22,0)),QUOTIENT(meta,semanas)+IF(posicion<=MOD(meta,semanas),1,0)),"") -> 3 | E22: =IFERROR(LET(meta,SUMIFS(Meta!$C$5:$C$16,Meta!$A$5:$A$16,">="&EOMONTH($A22,-1)+1,Meta!$A$5:$A$16,"<="&EOMONTH($A22,0)),semanas,COUNTIFS($A$5:$A$35,">="&EOMONTH($A22,-1)+1,$A$5:$A$35,"<="&EOMONTH($A22,0)),posicion,COUNTIFS($A$5:$A22,">="&EOMONTH($A22,-1)+1,$A$5:$A22,"<="&EOMONTH($A22,0)),QUOTIENT(meta,semanas)+IF(posicion<=MOD(meta,semanas),1,0)),"") -> 2 | F22: =IFERROR(SUMIFS(Meta!$B$5:$B$16,Meta!$A$5:$A$16,">="&EOMONTH($A22,-1)+1,Meta!$A$5:$A$16,"<="&EOMONTH($A22,0))/COUNTIFS($A$5:$A$35,">="&EOMONTH($A22,-1)+1,$A$5:$A$35,"<="&EOMONTH($A22,0)),"") -> 80000 | G22: =COUNTIFS(Data_Ventas!$E$2:$E1001,">="&A22,Data_Ventas!$E$2:$E1001,"<="&A22+6) -> 0 | H22: =COUNTIFS(Data_Ventas!$A$2:$A1001,">="&A22,Data_Ventas!$A$2:$A1001,"<="&A22+6,Data_Ventas!$H$2:$H1001,"Visitó proyecto") -> 0 | I22: =COUNTIFS(Data_Ventas!$A$2:$A1001,">="&A22,Data_Ventas!$A$2:$A1001,"<="&A22+6,Data_Ventas!$H$2:$H1001,"Separado") -> 0 | J22: =COUNTIFS(Data_Ventas!$A$2:$A1001,">="&A22,Data_Ventas!$A$2:$A1001,"<="&A22+6,Data_Ventas!$H$2:$H1001,"Venta") -> 0 | K22: =SUMIFS(Data_Ventas!$N$2:$N1001,Data_Ventas!$A$2:$A1001,">="&A22,Data_Ventas!$A$2:$A1001,"<="&A22+6,Data_Ventas!$H$2:$H1001,"Venta") -> 0 | L22: =IFERROR(K22/F22,"0%") -> 0
A23: =A22+7 -> 46341 | B23: =IFERROR(LET(meta,SUMIFS(Meta!$N$5:$N$16,Meta!$A$5:$A$16,">="&EOMONTH($A23,-1)+1,Meta!$A$5:$A$16,"<="&EOMONTH($A23,0)),semanas,COUNTIFS($A$5:$A$35,">="&EOMONTH($A23,-1)+1,$A$5:$A$35,"<="&EOMONTH($A23,0)),posicion,COUNTIFS($A$5:$A23,">="&EOMONTH($A23,-1)+1,$A$5:$A23,"<="&EOMONTH($A23,0)),QUOTIENT(meta,semanas)+IF(posicion<=MOD(meta,semanas),1,0)),"") -> 65 | C23: =IFERROR(LET(meta,SUMIFS(Meta!$P$5:$P$16,Meta!$A$5:$A$16,">="&EOMONTH($A23,-1)+1,Meta!$A$5:$A$16,"<="&EOMONTH($A23,0)),semanas,COUNTIFS($A$5:$A$35,">="&EOMONTH($A23,-1)+1,$A$5:$A$35,"<="&EOMONTH($A23,0)),posicion,COUNTIFS($A$5:$A23,">="&EOMONTH($A23,-1)+1,$A$5:$A23,"<="&EOMONTH($A23,0)),QUOTIENT(meta,semanas)+IF(posicion<=MOD(meta,semanas),1,0)),"") -> 8 | D23: =IFERROR(LET(meta,SUMIFS(Meta!$Q$5:$Q$16,Meta!$A$5:$A$16,">="&EOMONTH($A23,-1)+1,Meta!$A$5:$A$16,"<="&EOMONTH($A23,0)),semanas,COUNTIFS($A$5:$A$35,">="&EOMONTH($A23,-1)+1,$A$5:$A$35,"<="&EOMONTH($A23,0)),posicion,COUNTIFS($A$5:$A23,">="&EOMONTH($A23,-1)+1,$A$5:$A23,"<="&EOMONTH($A23,0)),QUOTIENT(meta,semanas)+IF(posicion<=MOD(meta,semanas),1,0)),"") -> 3 | E23: =IFERROR(LET(meta,SUMIFS(Meta!$C$5:$C$16,Meta!$A$5:$A$16,">="&EOMONTH($A23,-1)+1,Meta!$A$5:$A$16,"<="&EOMONTH($A23,0)),semanas,COUNTIFS($A$5:$A$35,">="&EOMONTH($A23,-1)+1,$A$5:$A$35,"<="&EOMONTH($A23,0)),posicion,COUNTIFS($A$5:$A23,">="&EOMONTH($A23,-1)+1,$A$5:$A23,"<="&EOMONTH($A23,0)),QUOTIENT(meta,semanas)+IF(posicion<=MOD(meta,semanas),1,0)),"") -> 2 | F23: =IFERROR(SUMIFS(Meta!$B$5:$B$16,Meta!$A$5:$A$16,">="&EOMONTH($A23,-1)+1,Meta!$A$5:$A$16,"<="&EOMONTH($A23,0))/COUNTIFS($A$5:$A$35,">="&EOMONTH($A23,-1)+1,$A$5:$A$35,"<="&EOMONTH($A23,0)),"") -> 80000 | G23: =COUNTIFS(Data_Ventas!$E$2:$E1001,">="&A23,Data_Ventas!$E$2:$E1001,"<="&A23+6) -> 0 | H23: =COUNTIFS(Data_Ventas!$A$2:$A1001,">="&A23,Data_Ventas!$A$2:$A1001,"<="&A23+6,Data_Ventas!$H$2:$H1001,"Visitó proyecto") -> 0 | I23: =COUNTIFS(Data_Ventas!$A$2:$A1001,">="&A23,Data_Ventas!$A$2:$A1001,"<="&A23+6,Data_Ventas!$H$2:$H1001,"Separado") -> 0 | J23: =COUNTIFS(Data_Ventas!$A$2:$A1001,">="&A23,Data_Ventas!$A$2:$A1001,"<="&A23+6,Data_Ventas!$H$2:$H1001,"Venta") -> 0 | K23: =SUMIFS(Data_Ventas!$N$2:$N1001,Data_Ventas!$A$2:$A1001,">="&A23,Data_Ventas!$A$2:$A1001,"<="&A23+6,Data_Ventas!$H$2:$H1001,"Venta") -> 0 | L23: =IFERROR(K23/F23,"0%") -> 0
A24: =A23+7 -> 46348 | B24: =IFERROR(LET(meta,SUMIFS(Meta!$N$5:$N$16,Meta!$A$5:$A$16,">="&EOMONTH($A24,-1)+1,Meta!$A$5:$A$16,"<="&EOMONTH($A24,0)),semanas,COUNTIFS($A$5:$A$35,">="&EOMONTH($A24,-1)+1,$A$5:$A$35,"<="&EOMONTH($A24,0)),posicion,COUNTIFS($A$5:$A24,">="&EOMONTH($A24,-1)+1,$A$5:$A24,"<="&EOMONTH($A24,0)),QUOTIENT(meta,semanas)+IF(posicion<=MOD(meta,semanas),1,0)),"") -> 65 | C24: =IFERROR(LET(meta,SUMIFS(Meta!$P$5:$P$16,Meta!$A$5:$A$16,">="&EOMONTH($A24,-1)+1,Meta!$A$5:$A$16,"<="&EOMONTH($A24,0)),semanas,COUNTIFS($A$5:$A$35,">="&EOMONTH($A24,-1)+1,$A$5:$A$35,"<="&EOMONTH($A24,0)),posicion,COUNTIFS($A$5:$A24,">="&EOMONTH($A24,-1)+1,$A$5:$A24,"<="&EOMONTH($A24,0)),QUOTIENT(meta,semanas)+IF(posicion<=MOD(meta,semanas),1,0)),"") -> 8 | D24: =IFERROR(LET(meta,SUMIFS(Meta!$Q$5:$Q$16,Meta!$A$5:$A$16,">="&EOMONTH($A24,-1)+1,Meta!$A$5:$A$16,"<="&EOMONTH($A24,0)),semanas,COUNTIFS($A$5:$A$35,">="&EOMONTH($A24,-1)+1,$A$5:$A$35,"<="&EOMONTH($A24,0)),posicion,COUNTIFS($A$5:$A24,">="&EOMONTH($A24,-1)+1,$A$5:$A24,"<="&EOMONTH($A24,0)),QUOTIENT(meta,semanas)+IF(posicion<=MOD(meta,semanas),1,0)),"") -> 2 | E24: =IFERROR(LET(meta,SUMIFS(Meta!$C$5:$C$16,Meta!$A$5:$A$16,">="&EOMONTH($A24,-1)+1,Meta!$A$5:$A$16,"<="&EOMONTH($A24,0)),semanas,COUNTIFS($A$5:$A$35,">="&EOMONTH($A24,-1)+1,$A$5:$A$35,"<="&EOMONTH($A24,0)),posicion,COUNTIFS($A$5:$A24,">="&EOMONTH($A24,-1)+1,$A$5:$A24,"<="&EOMONTH($A24,0)),QUOTIENT(meta,semanas)+IF(posicion<=MOD(meta,semanas),1,0)),"") -> 2 | F24: =IFERROR(SUMIFS(Meta!$B$5:$B$16,Meta!$A$5:$A$16,">="&EOMONTH($A24,-1)+1,Meta!$A$5:$A$16,"<="&EOMONTH($A24,0))/COUNTIFS($A$5:$A$35,">="&EOMONTH($A24,-1)+1,$A$5:$A$35,"<="&EOMONTH($A24,0)),"") -> 80000 | G24: =COUNTIFS(Data_Ventas!$E$2:$E1001,">="&A24,Data_Ventas!$E$2:$E1001,"<="&A24+6) -> 0 | H24: =COUNTIFS(Data_Ventas!$A$2:$A1001,">="&A24,Data_Ventas!$A$2:$A1001,"<="&A24+6,Data_Ventas!$H$2:$H1001,"Visitó proyecto") -> 0 | I24: =COUNTIFS(Data_Ventas!$A$2:$A1001,">="&A24,Data_Ventas!$A$2:$A1001,"<="&A24+6,Data_Ventas!$H$2:$H1001,"Separado") -> 0 | J24: =COUNTIFS(Data_Ventas!$A$2:$A1001,">="&A24,Data_Ventas!$A$2:$A1001,"<="&A24+6,Data_Ventas!$H$2:$H1001,"Venta") -> 0 | K24: =SUMIFS(Data_Ventas!$N$2:$N1001,Data_Ventas!$A$2:$A1001,">="&A24,Data_Ventas!$A$2:$A1001,"<="&A24+6,Data_Ventas!$H$2:$H1001,"Venta") -> 0 | L24: =IFERROR(K24/F24,"0%") -> 0
A25: =A24+7 -> 46355 | B25: =IFERROR(LET(meta,SUMIFS(Meta!$N$5:$N$16,Meta!$A$5:$A$16,">="&EOMONTH($A25,-1)+1,Meta!$A$5:$A$16,"<="&EOMONTH($A25,0)),semanas,COUNTIFS($A$5:$A$35,">="&EOMONTH($A25,-1)+1,$A$5:$A$35,"<="&EOMONTH($A25,0)),posicion,COUNTIFS($A$5:$A25,">="&EOMONTH($A25,-1)+1,$A$5:$A25,"<="&EOMONTH($A25,0)),QUOTIENT(meta,semanas)+IF(posicion<=MOD(meta,semanas),1,0)),"") -> 65 | C25: =IFERROR(LET(meta,SUMIFS(Meta!$P$5:$P$16,Meta!$A$5:$A$16,">="&EOMONTH($A25,-1)+1,Meta!$A$5:$A$16,"<="&EOMONTH($A25,0)),semanas,COUNTIFS($A$5:$A$35,">="&EOMONTH($A25,-1)+1,$A$5:$A$35,"<="&EOMONTH($A25,0)),posicion,COUNTIFS($A$5:$A25,">="&EOMONTH($A25,-1)+1,$A$5:$A25,"<="&EOMONTH($A25,0)),QUOTIENT(meta,semanas)+IF(posicion<=MOD(meta,semanas),1,0)),"") -> 7 | D25: =IFERROR(LET(meta,SUMIFS(Meta!$Q$5:$Q$16,Meta!$A$5:$A$16,">="&EOMONTH($A25,-1)+1,Meta!$A$5:$A$16,"<="&EOMONTH($A25,0)),semanas,COUNTIFS($A$5:$A$35,">="&EOMONTH($A25,-1)+1,$A$5:$A$35,"<="&EOMONTH($A25,0)),posicion,COUNTIFS($A$5:$A25,">="&EOMONTH($A25,-1)+1,$A$5:$A25,"<="&EOMONTH($A25,0)),QUOTIENT(meta,semanas)+IF(posicion<=MOD(meta,semanas),1,0)),"") -> 2 | E25: =IFERROR(LET(meta,SUMIFS(Meta!$C$5:$C$16,Meta!$A$5:$A$16,">="&EOMONTH($A25,-1)+1,Meta!$A$5:$A$16,"<="&EOMONTH($A25,0)),semanas,COUNTIFS($A$5:$A$35,">="&EOMONTH($A25,-1)+1,$A$5:$A$35,"<="&EOMONTH($A25,0)),posicion,COUNTIFS($A$5:$A25,">="&EOMONTH($A25,-1)+1,$A$5:$A25,"<="&EOMONTH($A25,0)),QUOTIENT(meta,semanas)+IF(posicion<=MOD(meta,semanas),1,0)),"") -> 2 | F25: =IFERROR(SUMIFS(Meta!$B$5:$B$16,Meta!$A$5:$A$16,">="&EOMONTH($A25,-1)+1,Meta!$A$5:$A$16,"<="&EOMONTH($A25,0))/COUNTIFS($A$5:$A$35,">="&EOMONTH($A25,-1)+1,$A$5:$A$35,"<="&EOMONTH($A25,0)),"") -> 80000 | G25: =COUNTIFS(Data_Ventas!$E$2:$E1001,">="&A25,Data_Ventas!$E$2:$E1001,"<="&A25+6) -> 0 | H25: =COUNTIFS(Data_Ventas!$A$2:$A1001,">="&A25,Data_Ventas!$A$2:$A1001,"<="&A25+6,Data_Ventas!$H$2:$H1001,"Visitó proyecto") -> 0 | I25: =COUNTIFS(Data_Ventas!$A$2:$A1001,">="&A25,Data_Ventas!$A$2:$A1001,"<="&A25+6,Data_Ventas!$H$2:$H1001,"Separado") -> 0 | J25: =COUNTIFS(Data_Ventas!$A$2:$A1001,">="&A25,Data_Ventas!$A$2:$A1001,"<="&A25+6,Data_Ventas!$H$2:$H1001,"Venta") -> 0 | K25: =SUMIFS(Data_Ventas!$N$2:$N1001,Data_Ventas!$A$2:$A1001,">="&A25,Data_Ventas!$A$2:$A1001,"<="&A25+6,Data_Ventas!$H$2:$H1001,"Venta") -> 0 | L25: =IFERROR(K25/F25,"0%") -> 0
A26: =A25+7 -> 46362 | B26: =IFERROR(LET(meta,SUMIFS(Meta!$N$5:$N$16,Meta!$A$5:$A$16,">="&EOMONTH($A26,-1)+1,Meta!$A$5:$A$16,"<="&EOMONTH($A26,0)),semanas,COUNTIFS($A$5:$A$35,">="&EOMONTH($A26,-1)+1,$A$5:$A$35,"<="&EOMONTH($A26,0)),posicion,COUNTIFS($A$5:$A26,">="&EOMONTH($A26,-1)+1,$A$5:$A26,"<="&EOMONTH($A26,0)),QUOTIENT(meta,semanas)+IF(posicion<=MOD(meta,semanas),1,0)),"") -> 82 | C26: =IFERROR(LET(meta,SUMIFS(Meta!$P$5:$P$16,Meta!$A$5:$A$16,">="&EOMONTH($A26,-1)+1,Meta!$A$5:$A$16,"<="&EOMONTH($A26,0)),semanas,COUNTIFS($A$5:$A$35,">="&EOMONTH($A26,-1)+1,$A$5:$A$35,"<="&EOMONTH($A26,0)),posicion,COUNTIFS($A$5:$A26,">="&EOMONTH($A26,-1)+1,$A$5:$A26,"<="&EOMONTH($A26,0)),QUOTIENT(meta,semanas)+IF(posicion<=MOD(meta,semanas),1,0)),"") -> 10 | D26: =IFERROR(LET(meta,SUMIFS(Meta!$Q$5:$Q$16,Meta!$A$5:$A$16,">="&EOMONTH($A26,-1)+1,Meta!$A$5:$A$16,"<="&EOMONTH($A26,0)),semanas,COUNTIFS($A$5:$A$35,">="&EOMONTH($A26,-1)+1,$A$5:$A$35,"<="&EOMONTH($A26,0)),posicion,COUNTIFS($A$5:$A26,">="&EOMONTH($A26,-1)+1,$A$5:$A26,"<="&EOMONTH($A26,0)),QUOTIENT(meta,semanas)+IF(posicion<=MOD(meta,semanas),1,0)),"") -> 4 | E26: =IFERROR(LET(meta,SUMIFS(Meta!$C$5:$C$16,Meta!$A$5:$A$16,">="&EOMONTH($A26,-1)+1,Meta!$A$5:$A$16,"<="&EOMONTH($A26,0)),semanas,COUNTIFS($A$5:$A$35,">="&EOMONTH($A26,-1)+1,$A$5:$A$35,"<="&EOMONTH($A26,0)),posicion,COUNTIFS($A$5:$A26,">="&EOMONTH($A26,-1)+1,$A$5:$A26,"<="&EOMONTH($A26,0)),QUOTIENT(meta,semanas)+IF(posicion<=MOD(meta,semanas),1,0)),"") -> 3 | F26: =IFERROR(SUMIFS(Meta!$B$5:$B$16,Meta!$A$5:$A$16,">="&EOMONTH($A26,-1)+1,Meta!$A$5:$A$16,"<="&EOMONTH($A26,0))/COUNTIFS($A$5:$A$35,">="&EOMONTH($A26,-1)+1,$A$5:$A$35,"<="&EOMONTH($A26,0)),"") -> 100000 | G26: =COUNTIFS(Data_Ventas!$E$2:$E1001,">="&A26,Data_Ventas!$E$2:$E1001,"<="&A26+6) -> 0 | H26: =COUNTIFS(Data_Ventas!$A$2:$A1001,">="&A26,Data_Ventas!$A$2:$A1001,"<="&A26+6,Data_Ventas!$H$2:$H1001,"Visitó proyecto") -> 0 | I26: =COUNTIFS(Data_Ventas!$A$2:$A1001,">="&A26,Data_Ventas!$A$2:$A1001,"<="&A26+6,Data_Ventas!$H$2:$H1001,"Separado") -> 0 | J26: =COUNTIFS(Data_Ventas!$A$2:$A1001,">="&A26,Data_Ventas!$A$2:$A1001,"<="&A26+6,Data_Ventas!$H$2:$H1001,"Venta") -> 0 | K26: =SUMIFS(Data_Ventas!$N$2:$N1001,Data_Ventas!$A$2:$A1001,">="&A26,Data_Ventas!$A$2:$A1001,"<="&A26+6,Data_Ventas!$H$2:$H1001,"Venta") -> 0 | L26: =IFERROR(K26/F26,"0%") -> 0
A27: =A26+7 -> 46369 | B27: =IFERROR(LET(meta,SUMIFS(Meta!$N$5:$N$16,Meta!$A$5:$A$16,">="&EOMONTH($A27,-1)+1,Meta!$A$5:$A$16,"<="&EOMONTH($A27,0)),semanas,COUNTIFS($A$5:$A$35,">="&EOMONTH($A27,-1)+1,$A$5:$A$35,"<="&EOMONTH($A27,0)),posicion,COUNTIFS($A$5:$A27,">="&EOMONTH($A27,-1)+1,$A$5:$A27,"<="&EOMONTH($A27,0)),QUOTIENT(meta,semanas)+IF(posicion<=MOD(meta,semanas),1,0)),"") -> 81 | C27: =IFERROR(LET(meta,SUMIFS(Meta!$P$5:$P$16,Meta!$A$5:$A$16,">="&EOMONTH($A27,-1)+1,Meta!$A$5:$A$16,"<="&EOMONTH($A27,0)),semanas,COUNTIFS($A$5:$A$35,">="&EOMONTH($A27,-1)+1,$A$5:$A$35,"<="&EOMONTH($A27,0)),posicion,COUNTIFS($A$5:$A27,">="&EOMONTH($A27,-1)+1,$A$5:$A27,"<="&EOMONTH($A27,0)),QUOTIENT(meta,semanas)+IF(posicion<=MOD(meta,semanas),1,0)),"") -> 10 | D27: =IFERROR(LET(meta,SUMIFS(Meta!$Q$5:$Q$16,Meta!$A$5:$A$16,">="&EOMONTH($A27,-1)+1,Meta!$A$5:$A$16,"<="&EOMONTH($A27,0)),semanas,COUNTIFS($A$5:$A$35,">="&EOMONTH($A27,-1)+1,$A$5:$A$35,"<="&EOMONTH($A27,0)),posicion,COUNTIFS($A$5:$A27,">="&EOMONTH($A27,-1)+1,$A$5:$A27,"<="&EOMONTH($A27,0)),QUOTIENT(meta,semanas)+IF(posicion<=MOD(meta,semanas),1,0)),"") -> 3 | E27: =IFERROR(LET(meta,SUMIFS(Meta!$C$5:$C$16,Meta!$A$5:$A$16,">="&EOMONTH($A27,-1)+1,Meta!$A$5:$A$16,"<="&EOMONTH($A27,0)),semanas,COUNTIFS($A$5:$A$35,">="&EOMONTH($A27,-1)+1,$A$5:$A$35,"<="&EOMONTH($A27,0)),posicion,COUNTIFS($A$5:$A27,">="&EOMONTH($A27,-1)+1,$A$5:$A27,"<="&EOMONTH($A27,0)),QUOTIENT(meta,semanas)+IF(posicion<=MOD(meta,semanas),1,0)),"") -> 3 | F27: =IFERROR(SUMIFS(Meta!$B$5:$B$16,Meta!$A$5:$A$16,">="&EOMONTH($A27,-1)+1,Meta!$A$5:$A$16,"<="&EOMONTH($A27,0))/COUNTIFS($A$5:$A$35,">="&EOMONTH($A27,-1)+1,$A$5:$A$35,"<="&EOMONTH($A27,0)),"") -> 100000 | G27: =COUNTIFS(Data_Ventas!$E$2:$E1001,">="&A27,Data_Ventas!$E$2:$E1001,"<="&A27+6) -> 0 | H27: =COUNTIFS(Data_Ventas!$A$2:$A1001,">="&A27,Data_Ventas!$A$2:$A1001,"<="&A27+6,Data_Ventas!$H$2:$H1001,"Visitó proyecto") -> 0 | I27: =COUNTIFS(Data_Ventas!$A$2:$A1001,">="&A27,Data_Ventas!$A$2:$A1001,"<="&A27+6,Data_Ventas!$H$2:$H1001,"Separado") -> 0 | J27: =COUNTIFS(Data_Ventas!$A$2:$A1001,">="&A27,Data_Ventas!$A$2:$A1001,"<="&A27+6,Data_Ventas!$H$2:$H1001,"Venta") -> 0 | K27: =SUMIFS(Data_Ventas!$N$2:$N1001,Data_Ventas!$A$2:$A1001,">="&A27,Data_Ventas!$A$2:$A1001,"<="&A27+6,Data_Ventas!$H$2:$H1001,"Venta") -> 0 | L27: =IFERROR(K27/F27,"0%") -> 0
A28: =A27+7 -> 46376 | B28: =IFERROR(LET(meta,SUMIFS(Meta!$N$5:$N$16,Meta!$A$5:$A$16,">="&EOMONTH($A28,-1)+1,Meta!$A$5:$A$16,"<="&EOMONTH($A28,0)),semanas,COUNTIFS($A$5:$A$35,">="&EOMONTH($A28,-1)+1,$A$5:$A$35,"<="&EOMONTH($A28,0)),posicion,COUNTIFS($A$5:$A28,">="&EOMONTH($A28,-1)+1,$A$5:$A28,"<="&EOMONTH($A28,0)),QUOTIENT(meta,semanas)+IF(posicion<=MOD(meta,semanas),1,0)),"") -> 81 | C28: =IFERROR(LET(meta,SUMIFS(Meta!$P$5:$P$16,Meta!$A$5:$A$16,">="&EOMONTH($A28,-1)+1,Meta!$A$5:$A$16,"<="&EOMONTH($A28,0)),semanas,COUNTIFS($A$5:$A$35,">="&EOMONTH($A28,-1)+1,$A$5:$A$35,"<="&EOMONTH($A28,0)),posicion,COUNTIFS($A$5:$A28,">="&EOMONTH($A28,-1)+1,$A$5:$A28,"<="&EOMONTH($A28,0)),QUOTIENT(meta,semanas)+IF(posicion<=MOD(meta,semanas),1,0)),"") -> 10 | D28: =IFERROR(LET(meta,SUMIFS(Meta!$Q$5:$Q$16,Meta!$A$5:$A$16,">="&EOMONTH($A28,-1)+1,Meta!$A$5:$A$16,"<="&EOMONTH($A28,0)),semanas,COUNTIFS($A$5:$A$35,">="&EOMONTH($A28,-1)+1,$A$5:$A$35,"<="&EOMONTH($A28,0)),posicion,COUNTIFS($A$5:$A28,">="&EOMONTH($A28,-1)+1,$A$5:$A28,"<="&EOMONTH($A28,0)),QUOTIENT(meta,semanas)+IF(posicion<=MOD(meta,semanas),1,0)),"") -> 3 | E28: =IFERROR(LET(meta,SUMIFS(Meta!$C$5:$C$16,Meta!$A$5:$A$16,">="&EOMONTH($A28,-1)+1,Meta!$A$5:$A$16,"<="&EOMONTH($A28,0)),semanas,COUNTIFS($A$5:$A$35,">="&EOMONTH($A28,-1)+1,$A$5:$A$35,"<="&EOMONTH($A28,0)),posicion,COUNTIFS($A$5:$A28,">="&EOMONTH($A28,-1)+1,$A$5:$A28,"<="&EOMONTH($A28,0)),QUOTIENT(meta,semanas)+IF(posicion<=MOD(meta,semanas),1,0)),"") -> 2 | F28: =IFERROR(SUMIFS(Meta!$B$5:$B$16,Meta!$A$5:$A$16,">="&EOMONTH($A28,-1)+1,Meta!$A$5:$A$16,"<="&EOMONTH($A28,0))/COUNTIFS($A$5:$A$35,">="&EOMONTH($A28,-1)+1,$A$5:$A$35,"<="&EOMONTH($A28,0)),"") -> 100000 | G28: =COUNTIFS(Data_Ventas!$E$2:$E1001,">="&A28,Data_Ventas!$E$2:$E1001,"<="&A28+6) -> 0 | H28: =COUNTIFS(Data_Ventas!$A$2:$A1001,">="&A28,Data_Ventas!$A$2:$A1001,"<="&A28+6,Data_Ventas!$H$2:$H1001,"Visitó proyecto") -> 0 | I28: =COUNTIFS(Data_Ventas!$A$2:$A1001,">="&A28,Data_Ventas!$A$2:$A1001,"<="&A28+6,Data_Ventas!$H$2:$H1001,"Separado") -> 0 | J28: =COUNTIFS(Data_Ventas!$A$2:$A1001,">="&A28,Data_Ventas!$A$2:$A1001,"<="&A28+6,Data_Ventas!$H$2:$H1001,"Venta") -> 0 | K28: =SUMIFS(Data_Ventas!$N$2:$N1001,Data_Ventas!$A$2:$A1001,">="&A28,Data_Ventas!$A$2:$A1001,"<="&A28+6,Data_Ventas!$H$2:$H1001,"Venta") -> 0 | L28: =IFERROR(K28/F28,"0%") -> 0
A29: =A28+7 -> 46383 | B29: =IFERROR(LET(meta,SUMIFS(Meta!$N$5:$N$16,Meta!$A$5:$A$16,">="&EOMONTH($A29,-1)+1,Meta!$A$5:$A$16,"<="&EOMONTH($A29,0)),semanas,COUNTIFS($A$5:$A$35,">="&EOMONTH($A29,-1)+1,$A$5:$A$35,"<="&EOMONTH($A29,0)),posicion,COUNTIFS($A$5:$A29,">="&EOMONTH($A29,-1)+1,$A$5:$A29,"<="&EOMONTH($A29,0)),QUOTIENT(meta,semanas)+IF(posicion<=MOD(meta,semanas),1,0)),"") -> 81 | C29: =IFERROR(LET(meta,SUMIFS(Meta!$P$5:$P$16,Meta!$A$5:$A$16,">="&EOMONTH($A29,-1)+1,Meta!$A$5:$A$16,"<="&EOMONTH($A29,0)),semanas,COUNTIFS($A$5:$A$35,">="&EOMONTH($A29,-1)+1,$A$5:$A$35,"<="&EOMONTH($A29,0)),posicion,COUNTIFS($A$5:$A29,">="&EOMONTH($A29,-1)+1,$A$5:$A29,"<="&EOMONTH($A29,0)),QUOTIENT(meta,semanas)+IF(posicion<=MOD(meta,semanas),1,0)),"") -> 9 | D29: =IFERROR(LET(meta,SUMIFS(Meta!$Q$5:$Q$16,Meta!$A$5:$A$16,">="&EOMONTH($A29,-1)+1,Meta!$A$5:$A$16,"<="&EOMONTH($A29,0)),semanas,COUNTIFS($A$5:$A$35,">="&EOMONTH($A29,-1)+1,$A$5:$A$35,"<="&EOMONTH($A29,0)),posicion,COUNTIFS($A$5:$A29,">="&EOMONTH($A29,-1)+1,$A$5:$A29,"<="&EOMONTH($A29,0)),QUOTIENT(meta,semanas)+IF(posicion<=MOD(meta,semanas),1,0)),"") -> 3 | E29: =IFERROR(LET(meta,SUMIFS(Meta!$C$5:$C$16,Meta!$A$5:$A$16,">="&EOMONTH($A29,-1)+1,Meta!$A$5:$A$16,"<="&EOMONTH($A29,0)),semanas,COUNTIFS($A$5:$A$35,">="&EOMONTH($A29,-1)+1,$A$5:$A$35,"<="&EOMONTH($A29,0)),posicion,COUNTIFS($A$5:$A29,">="&EOMONTH($A29,-1)+1,$A$5:$A29,"<="&EOMONTH($A29,0)),QUOTIENT(meta,semanas)+IF(posicion<=MOD(meta,semanas),1,0)),"") -> 2 | F29: =IFERROR(SUMIFS(Meta!$B$5:$B$16,Meta!$A$5:$A$16,">="&EOMONTH($A29,-1)+1,Meta!$A$5:$A$16,"<="&EOMONTH($A29,0))/COUNTIFS($A$5:$A$35,">="&EOMONTH($A29,-1)+1,$A$5:$A$35,"<="&EOMONTH($A29,0)),"") -> 100000 | G29: =COUNTIFS(Data_Ventas!$E$2:$E1001,">="&A29,Data_Ventas!$E$2:$E1001,"<="&A29+6) -> 0 | H29: =COUNTIFS(Data_Ventas!$A$2:$A1001,">="&A29,Data_Ventas!$A$2:$A1001,"<="&A29+6,Data_Ventas!$H$2:$H1001,"Visitó proyecto") -> 0 | I29: =COUNTIFS(Data_Ventas!$A$2:$A1001,">="&A29,Data_Ventas!$A$2:$A1001,"<="&A29+6,Data_Ventas!$H$2:$H1001,"Separado") -> 0 | J29: =COUNTIFS(Data_Ventas!$A$2:$A1001,">="&A29,Data_Ventas!$A$2:$A1001,"<="&A29+6,Data_Ventas!$H$2:$H1001,"Venta") -> 0 | K29: =SUMIFS(Data_Ventas!$N$2:$N1001,Data_Ventas!$A$2:$A1001,">="&A29,Data_Ventas!$A$2:$A1001,"<="&A29+6,Data_Ventas!$H$2:$H1001,"Venta") -> 0 | L29: =IFERROR(K29/F29,"0%") -> 0
A30: =A29+7 -> 46390 | B30: =IFERROR(LET(meta,SUMIFS(Meta!$N$5:$N$16,Meta!$A$5:$A$16,">="&EOMONTH($A30,-1)+1,Meta!$A$5:$A$16,"<="&EOMONTH($A30,0)),semanas,COUNTIFS($A$5:$A$35,">="&EOMONTH($A30,-1)+1,$A$5:$A$35,"<="&EOMONTH($A30,0)),posicion,COUNTIFS($A$5:$A30,">="&EOMONTH($A30,-1)+1,$A$5:$A30,"<="&EOMONTH($A30,0)),QUOTIENT(meta,semanas)+IF(posicion<=MOD(meta,semanas),1,0)),"") -> 0 | C30: =IFERROR(LET(meta,SUMIFS(Meta!$P$5:$P$16,Meta!$A$5:$A$16,">="&EOMONTH($A30,-1)+1,Meta!$A$5:$A$16,"<="&EOMONTH($A30,0)),semanas,COUNTIFS($A$5:$A$35,">="&EOMONTH($A30,-1)+1,$A$5:$A$35,"<="&EOMONTH($A30,0)),posicion,COUNTIFS($A$5:$A30,">="&EOMONTH($A30,-1)+1,$A$5:$A30,"<="&EOMONTH($A30,0)),QUOTIENT(meta,semanas)+IF(posicion<=MOD(meta,semanas),1,0)),"") -> 0 | D30: =IFERROR(LET(meta,SUMIFS(Meta!$Q$5:$Q$16,Meta!$A$5:$A$16,">="&EOMONTH($A30,-1)+1,Meta!$A$5:$A$16,"<="&EOMONTH($A30,0)),semanas,COUNTIFS($A$5:$A$35,">="&EOMONTH($A30,-1)+1,$A$5:$A$35,"<="&EOMONTH($A30,0)),posicion,COUNTIFS($A$5:$A30,">="&EOMONTH($A30,-1)+1,$A$5:$A30,"<="&EOMONTH($A30,0)),QUOTIENT(meta,semanas)+IF(posicion<=MOD(meta,semanas),1,0)),"") -> 0 | E30: =IFERROR(LET(meta,SUMIFS(Meta!$C$5:$C$16,Meta!$A$5:$A$16,">="&EOMONTH($A30,-1)+1,Meta!$A$5:$A$16,"<="&EOMONTH($A30,0)),semanas,COUNTIFS($A$5:$A$35,">="&EOMONTH($A30,-1)+1,$A$5:$A$35,"<="&EOMONTH($A30,0)),posicion,COUNTIFS($A$5:$A30,">="&EOMONTH($A30,-1)+1,$A$5:$A30,"<="&EOMONTH($A30,0)),QUOTIENT(meta,semanas)+IF(posicion<=MOD(meta,semanas),1,0)),"") -> 0 | F30: =IFERROR(SUMIFS(Meta!$B$5:$B$16,Meta!$A$5:$A$16,">="&EOMONTH($A30,-1)+1,Meta!$A$5:$A$16,"<="&EOMONTH($A30,0))/COUNTIFS($A$5:$A$35,">="&EOMONTH($A30,-1)+1,$A$5:$A$35,"<="&EOMONTH($A30,0)),"") -> 0 | G30: =COUNTIFS(Data_Ventas!$E$2:$E1001,">="&A30,Data_Ventas!$E$2:$E1001,"<="&A30+6) -> 0 | H30: =COUNTIFS(Data_Ventas!$A$2:$A1001,">="&A30,Data_Ventas!$A$2:$A1001,"<="&A30+6,Data_Ventas!$H$2:$H1001,"Visitó proyecto") -> 0 | I30: =COUNTIFS(Data_Ventas!$A$2:$A1001,">="&A30,Data_Ventas!$A$2:$A1001,"<="&A30+6,Data_Ventas!$H$2:$H1001,"Separado") -> 0 | J30: =COUNTIFS(Data_Ventas!$A$2:$A1001,">="&A30,Data_Ventas!$A$2:$A1001,"<="&A30+6,Data_Ventas!$H$2:$H1001,"Venta") -> 0 | K30: =SUMIFS(Data_Ventas!$N$2:$N1001,Data_Ventas!$A$2:$A1001,">="&A30,Data_Ventas!$A$2:$A1001,"<="&A30+6,Data_Ventas!$H$2:$H1001,"Venta") -> 0 | L30: =IFERROR(K30/F30,"0%") -> 0%
A31: =A30+7 -> 46397 | B31: =IFERROR(LET(meta,SUMIFS(Meta!$N$5:$N$16,Meta!$A$5:$A$16,">="&EOMONTH($A31,-1)+1,Meta!$A$5:$A$16,"<="&EOMONTH($A31,0)),semanas,COUNTIFS($A$5:$A$35,">="&EOMONTH($A31,-1)+1,$A$5:$A$35,"<="&EOMONTH($A31,0)),posicion,COUNTIFS($A$5:$A31,">="&EOMONTH($A31,-1)+1,$A$5:$A31,"<="&EOMONTH($A31,0)),QUOTIENT(meta,semanas)+IF(posicion<=MOD(meta,semanas),1,0)),"") -> 0 | C31: =IFERROR(LET(meta,SUMIFS(Meta!$P$5:$P$16,Meta!$A$5:$A$16,">="&EOMONTH($A31,-1)+1,Meta!$A$5:$A$16,"<="&EOMONTH($A31,0)),semanas,COUNTIFS($A$5:$A$35,">="&EOMONTH($A31,-1)+1,$A$5:$A$35,"<="&EOMONTH($A31,0)),posicion,COUNTIFS($A$5:$A31,">="&EOMONTH($A31,-1)+1,$A$5:$A31,"<="&EOMONTH($A31,0)),QUOTIENT(meta,semanas)+IF(posicion<=MOD(meta,semanas),1,0)),"") -> 0 | D31: =IFERROR(LET(meta,SUMIFS(Meta!$Q$5:$Q$16,Meta!$A$5:$A$16,">="&EOMONTH($A31,-1)+1,Meta!$A$5:$A$16,"<="&EOMONTH($A31,0)),semanas,COUNTIFS($A$5:$A$35,">="&EOMONTH($A31,-1)+1,$A$5:$A$35,"<="&EOMONTH($A31,0)),posicion,COUNTIFS($A$5:$A31,">="&EOMONTH($A31,-1)+1,$A$5:$A31,"<="&EOMONTH($A31,0)),QUOTIENT(meta,semanas)+IF(posicion<=MOD(meta,semanas),1,0)),"") -> 0 | E31: =IFERROR(LET(meta,SUMIFS(Meta!$C$5:$C$16,Meta!$A$5:$A$16,">="&EOMONTH($A31,-1)+1,Meta!$A$5:$A$16,"<="&EOMONTH($A31,0)),semanas,COUNTIFS($A$5:$A$35,">="&EOMONTH($A31,-1)+1,$A$5:$A$35,"<="&EOMONTH($A31,0)),posicion,COUNTIFS($A$5:$A31,">="&EOMONTH($A31,-1)+1,$A$5:$A31,"<="&EOMONTH($A31,0)),QUOTIENT(meta,semanas)+IF(posicion<=MOD(meta,semanas),1,0)),"") -> 0 | F31: =IFERROR(SUMIFS(Meta!$B$5:$B$16,Meta!$A$5:$A$16,">="&EOMONTH($A31,-1)+1,Meta!$A$5:$A$16,"<="&EOMONTH($A31,0))/COUNTIFS($A$5:$A$35,">="&EOMONTH($A31,-1)+1,$A$5:$A$35,"<="&EOMONTH($A31,0)),"") -> 0 | G31: =COUNTIFS(Data_Ventas!$E$2:$E1001,">="&A31,Data_Ventas!$E$2:$E1001,"<="&A31+6) -> 0 | H31: =COUNTIFS(Data_Ventas!$A$2:$A1001,">="&A31,Data_Ventas!$A$2:$A1001,"<="&A31+6,Data_Ventas!$H$2:$H1001,"Visitó proyecto") -> 0 | I31: =COUNTIFS(Data_Ventas!$A$2:$A1001,">="&A31,Data_Ventas!$A$2:$A1001,"<="&A31+6,Data_Ventas!$H$2:$H1001,"Separado") -> 0 | J31: =COUNTIFS(Data_Ventas!$A$2:$A1001,">="&A31,Data_Ventas!$A$2:$A1001,"<="&A31+6,Data_Ventas!$H$2:$H1001,"Venta") -> 0 | K31: =SUMIFS(Data_Ventas!$N$2:$N1001,Data_Ventas!$A$2:$A1001,">="&A31,Data_Ventas!$A$2:$A1001,"<="&A31+6,Data_Ventas!$H$2:$H1001,"Venta") -> 0 | L31: =IFERROR(K31/F31,"0%") -> 0%
A32: =A31+7 -> 46404 | B32: =IFERROR(LET(meta,SUMIFS(Meta!$N$5:$N$16,Meta!$A$5:$A$16,">="&EOMONTH($A32,-1)+1,Meta!$A$5:$A$16,"<="&EOMONTH($A32,0)),semanas,COUNTIFS($A$5:$A$35,">="&EOMONTH($A32,-1)+1,$A$5:$A$35,"<="&EOMONTH($A32,0)),posicion,COUNTIFS($A$5:$A32,">="&EOMONTH($A32,-1)+1,$A$5:$A32,"<="&EOMONTH($A32,0)),QUOTIENT(meta,semanas)+IF(posicion<=MOD(meta,semanas),1,0)),"") -> 0 | C32: =IFERROR(LET(meta,SUMIFS(Meta!$P$5:$P$16,Meta!$A$5:$A$16,">="&EOMONTH($A32,-1)+1,Meta!$A$5:$A$16,"<="&EOMONTH($A32,0)),semanas,COUNTIFS($A$5:$A$35,">="&EOMONTH($A32,-1)+1,$A$5:$A$35,"<="&EOMONTH($A32,0)),posicion,COUNTIFS($A$5:$A32,">="&EOMONTH($A32,-1)+1,$A$5:$A32,"<="&EOMONTH($A32,0)),QUOTIENT(meta,semanas)+IF(posicion<=MOD(meta,semanas),1,0)),"") -> 0 | D32: =IFERROR(LET(meta,SUMIFS(Meta!$Q$5:$Q$16,Meta!$A$5:$A$16,">="&EOMONTH($A32,-1)+1,Meta!$A$5:$A$16,"<="&EOMONTH($A32,0)),semanas,COUNTIFS($A$5:$A$35,">="&EOMONTH($A32,-1)+1,$A$5:$A$35,"<="&EOMONTH($A32,0)),posicion,COUNTIFS($A$5:$A32,">="&EOMONTH($A32,-1)+1,$A$5:$A32,"<="&EOMONTH($A32,0)),QUOTIENT(meta,semanas)+IF(posicion<=MOD(meta,semanas),1,0)),"") -> 0 | E32: =IFERROR(LET(meta,SUMIFS(Meta!$C$5:$C$16,Meta!$A$5:$A$16,">="&EOMONTH($A32,-1)+1,Meta!$A$5:$A$16,"<="&EOMONTH($A32,0)),semanas,COUNTIFS($A$5:$A$35,">="&EOMONTH($A32,-1)+1,$A$5:$A$35,"<="&EOMONTH($A32,0)),posicion,COUNTIFS($A$5:$A32,">="&EOMONTH($A32,-1)+1,$A$5:$A32,"<="&EOMONTH($A32,0)),QUOTIENT(meta,semanas)+IF(posicion<=MOD(meta,semanas),1,0)),"") -> 0 | F32: =IFERROR(SUMIFS(Meta!$B$5:$B$16,Meta!$A$5:$A$16,">="&EOMONTH($A32,-1)+1,Meta!$A$5:$A$16,"<="&EOMONTH($A32,0))/COUNTIFS($A$5:$A$35,">="&EOMONTH($A32,-1)+1,$A$5:$A$35,"<="&EOMONTH($A32,0)),"") -> 0 | G32: =COUNTIFS(Data_Ventas!$E$2:$E1001,">="&A32,Data_Ventas!$E$2:$E1001,"<="&A32+6) -> 0 | H32: =COUNTIFS(Data_Ventas!$A$2:$A1001,">="&A32,Data_Ventas!$A$2:$A1001,"<="&A32+6,Data_Ventas!$H$2:$H1001,"Visitó proyecto") -> 0 | I32: =COUNTIFS(Data_Ventas!$A$2:$A1001,">="&A32,Data_Ventas!$A$2:$A1001,"<="&A32+6,Data_Ventas!$H$2:$H1001,"Separado") -> 0 | J32: =COUNTIFS(Data_Ventas!$A$2:$A1001,">="&A32,Data_Ventas!$A$2:$A1001,"<="&A32+6,Data_Ventas!$H$2:$H1001,"Venta") -> 0 | K32: =SUMIFS(Data_Ventas!$N$2:$N1001,Data_Ventas!$A$2:$A1001,">="&A32,Data_Ventas!$A$2:$A1001,"<="&A32+6,Data_Ventas!$H$2:$H1001,"Venta") -> 0 | L32: =IFERROR(K32/F32,"0%") -> 0%
A33: =A32+7 -> 46411 | B33: =IFERROR(LET(meta,SUMIFS(Meta!$N$5:$N$16,Meta!$A$5:$A$16,">="&EOMONTH($A33,-1)+1,Meta!$A$5:$A$16,"<="&EOMONTH($A33,0)),semanas,COUNTIFS($A$5:$A$35,">="&EOMONTH($A33,-1)+1,$A$5:$A$35,"<="&EOMONTH($A33,0)),posicion,COUNTIFS($A$5:$A33,">="&EOMONTH($A33,-1)+1,$A$5:$A33,"<="&EOMONTH($A33,0)),QUOTIENT(meta,semanas)+IF(posicion<=MOD(meta,semanas),1,0)),"") -> 0 | C33: =IFERROR(LET(meta,SUMIFS(Meta!$P$5:$P$16,Meta!$A$5:$A$16,">="&EOMONTH($A33,-1)+1,Meta!$A$5:$A$16,"<="&EOMONTH($A33,0)),semanas,COUNTIFS($A$5:$A$35,">="&EOMONTH($A33,-1)+1,$A$5:$A$35,"<="&EOMONTH($A33,0)),posicion,COUNTIFS($A$5:$A33,">="&EOMONTH($A33,-1)+1,$A$5:$A33,"<="&EOMONTH($A33,0)),QUOTIENT(meta,semanas)+IF(posicion<=MOD(meta,semanas),1,0)),"") -> 0 | D33: =IFERROR(LET(meta,SUMIFS(Meta!$Q$5:$Q$16,Meta!$A$5:$A$16,">="&EOMONTH($A33,-1)+1,Meta!$A$5:$A$16,"<="&EOMONTH($A33,0)),semanas,COUNTIFS($A$5:$A$35,">="&EOMONTH($A33,-1)+1,$A$5:$A$35,"<="&EOMONTH($A33,0)),posicion,COUNTIFS($A$5:$A33,">="&EOMONTH($A33,-1)+1,$A$5:$A33,"<="&EOMONTH($A33,0)),QUOTIENT(meta,semanas)+IF(posicion<=MOD(meta,semanas),1,0)),"") -> 0 | E33: =IFERROR(LET(meta,SUMIFS(Meta!$C$5:$C$16,Meta!$A$5:$A$16,">="&EOMONTH($A33,-1)+1,Meta!$A$5:$A$16,"<="&EOMONTH($A33,0)),semanas,COUNTIFS($A$5:$A$35,">="&EOMONTH($A33,-1)+1,$A$5:$A$35,"<="&EOMONTH($A33,0)),posicion,COUNTIFS($A$5:$A33,">="&EOMONTH($A33,-1)+1,$A$5:$A33,"<="&EOMONTH($A33,0)),QUOTIENT(meta,semanas)+IF(posicion<=MOD(meta,semanas),1,0)),"") -> 0 | F33: =IFERROR(SUMIFS(Meta!$B$5:$B$16,Meta!$A$5:$A$16,">="&EOMONTH($A33,-1)+1,Meta!$A$5:$A$16,"<="&EOMONTH($A33,0))/COUNTIFS($A$5:$A$35,">="&EOMONTH($A33,-1)+1,$A$5:$A$35,"<="&EOMONTH($A33,0)),"") -> 0 | G33: =COUNTIFS(Data_Ventas!$E$2:$E1001,">="&A33,Data_Ventas!$E$2:$E1001,"<="&A33+6) -> 0 | H33: =COUNTIFS(Data_Ventas!$A$2:$A1001,">="&A33,Data_Ventas!$A$2:$A1001,"<="&A33+6,Data_Ventas!$H$2:$H1001,"Visitó proyecto") -> 0 | I33: =COUNTIFS(Data_Ventas!$A$2:$A1001,">="&A33,Data_Ventas!$A$2:$A1001,"<="&A33+6,Data_Ventas!$H$2:$H1001,"Separado") -> 0 | J33: =COUNTIFS(Data_Ventas!$A$2:$A1001,">="&A33,Data_Ventas!$A$2:$A1001,"<="&A33+6,Data_Ventas!$H$2:$H1001,"Venta") -> 0 | K33: =SUMIFS(Data_Ventas!$N$2:$N1001,Data_Ventas!$A$2:$A1001,">="&A33,Data_Ventas!$A$2:$A1001,"<="&A33+6,Data_Ventas!$H$2:$H1001,"Venta") -> 0 | L33: =IFERROR(K33/F33,"0%") -> 0%
A34: =A33+7 -> 46418 | B34: =IFERROR(LET(meta,SUMIFS(Meta!$N$5:$N$16,Meta!$A$5:$A$16,">="&EOMONTH($A34,-1)+1,Meta!$A$5:$A$16,"<="&EOMONTH($A34,0)),semanas,COUNTIFS($A$5:$A$35,">="&EOMONTH($A34,-1)+1,$A$5:$A$35,"<="&EOMONTH($A34,0)),posicion,COUNTIFS($A$5:$A34,">="&EOMONTH($A34,-1)+1,$A$5:$A34,"<="&EOMONTH($A34,0)),QUOTIENT(meta,semanas)+IF(posicion<=MOD(meta,semanas),1,0)),"") -> 0 | C34: =IFERROR(LET(meta,SUMIFS(Meta!$P$5:$P$16,Meta!$A$5:$A$16,">="&EOMONTH($A34,-1)+1,Meta!$A$5:$A$16,"<="&EOMONTH($A34,0)),semanas,COUNTIFS($A$5:$A$35,">="&EOMONTH($A34,-1)+1,$A$5:$A$35,"<="&EOMONTH($A34,0)),posicion,COUNTIFS($A$5:$A34,">="&EOMONTH($A34,-1)+1,$A$5:$A34,"<="&EOMONTH($A34,0)),QUOTIENT(meta,semanas)+IF(posicion<=MOD(meta,semanas),1,0)),"") -> 0 | D34: =IFERROR(LET(meta,SUMIFS(Meta!$Q$5:$Q$16,Meta!$A$5:$A$16,">="&EOMONTH($A34,-1)+1,Meta!$A$5:$A$16,"<="&EOMONTH($A34,0)),semanas,COUNTIFS($A$5:$A$35,">="&EOMONTH($A34,-1)+1,$A$5:$A$35,"<="&EOMONTH($A34,0)),posicion,COUNTIFS($A$5:$A34,">="&EOMONTH($A34,-1)+1,$A$5:$A34,"<="&EOMONTH($A34,0)),QUOTIENT(meta,semanas)+IF(posicion<=MOD(meta,semanas),1,0)),"") -> 0 | E34: =IFERROR(LET(meta,SUMIFS(Meta!$C$5:$C$16,Meta!$A$5:$A$16,">="&EOMONTH($A34,-1)+1,Meta!$A$5:$A$16,"<="&EOMONTH($A34,0)),semanas,COUNTIFS($A$5:$A$35,">="&EOMONTH($A34,-1)+1,$A$5:$A$35,"<="&EOMONTH($A34,0)),posicion,COUNTIFS($A$5:$A34,">="&EOMONTH($A34,-1)+1,$A$5:$A34,"<="&EOMONTH($A34,0)),QUOTIENT(meta,semanas)+IF(posicion<=MOD(meta,semanas),1,0)),"") -> 0 | F34: =IFERROR(SUMIFS(Meta!$B$5:$B$16,Meta!$A$5:$A$16,">="&EOMONTH($A34,-1)+1,Meta!$A$5:$A$16,"<="&EOMONTH($A34,0))/COUNTIFS($A$5:$A$35,">="&EOMONTH($A34,-1)+1,$A$5:$A$35,"<="&EOMONTH($A34,0)),"") -> 0 | G34: =COUNTIFS(Data_Ventas!$E$2:$E1001,">="&A34,Data_Ventas!$E$2:$E1001,"<="&A34+6) -> 0 | H34: =COUNTIFS(Data_Ventas!$A$2:$A1001,">="&A34,Data_Ventas!$A$2:$A1001,"<="&A34+6,Data_Ventas!$H$2:$H1001,"Visitó proyecto") -> 0 | I34: =COUNTIFS(Data_Ventas!$A$2:$A1001,">="&A34,Data_Ventas!$A$2:$A1001,"<="&A34+6,Data_Ventas!$H$2:$H1001,"Separado") -> 0 | J34: =COUNTIFS(Data_Ventas!$A$2:$A1001,">="&A34,Data_Ventas!$A$2:$A1001,"<="&A34+6,Data_Ventas!$H$2:$H1001,"Venta") -> 0 | K34: =SUMIFS(Data_Ventas!$N$2:$N1001,Data_Ventas!$A$2:$A1001,">="&A34,Data_Ventas!$A$2:$A1001,"<="&A34+6,Data_Ventas!$H$2:$H1001,"Venta") -> 0 | L34: =IFERROR(K34/F34,"0%") -> 0%
A35: =A34+7 -> 46425 | B35: =IFERROR(LET(meta,SUMIFS(Meta!$N$5:$N$16,Meta!$A$5:$A$16,">="&EOMONTH($A35,-1)+1,Meta!$A$5:$A$16,"<="&EOMONTH($A35,0)),semanas,COUNTIFS($A$5:$A$35,">="&EOMONTH($A35,-1)+1,$A$5:$A$35,"<="&EOMONTH($A35,0)),posicion,COUNTIFS($A$5:$A35,">="&EOMONTH($A35,-1)+1,$A$5:$A35,"<="&EOMONTH($A35,0)),QUOTIENT(meta,semanas)+IF(posicion<=MOD(meta,semanas),1,0)),"") -> 0 | C35: =IFERROR(LET(meta,SUMIFS(Meta!$P$5:$P$16,Meta!$A$5:$A$16,">="&EOMONTH($A35,-1)+1,Meta!$A$5:$A$16,"<="&EOMONTH($A35,0)),semanas,COUNTIFS($A$5:$A$35,">="&EOMONTH($A35,-1)+1,$A$5:$A$35,"<="&EOMONTH($A35,0)),posicion,COUNTIFS($A$5:$A35,">="&EOMONTH($A35,-1)+1,$A$5:$A35,"<="&EOMONTH($A35,0)),QUOTIENT(meta,semanas)+IF(posicion<=MOD(meta,semanas),1,0)),"") -> 0 | D35: =IFERROR(LET(meta,SUMIFS(Meta!$Q$5:$Q$16,Meta!$A$5:$A$16,">="&EOMONTH($A35,-1)+1,Meta!$A$5:$A$16,"<="&EOMONTH($A35,0)),semanas,COUNTIFS($A$5:$A$35,">="&EOMONTH($A35,-1)+1,$A$5:$A$35,"<="&EOMONTH($A35,0)),posicion,COUNTIFS($A$5:$A35,">="&EOMONTH($A35,-1)+1,$A$5:$A35,"<="&EOMONTH($A35,0)),QUOTIENT(meta,semanas)+IF(posicion<=MOD(meta,semanas),1,0)),"") -> 0 | E35: =IFERROR(LET(meta,SUMIFS(Meta!$C$5:$C$16,Meta!$A$5:$A$16,">="&EOMONTH($A35,-1)+1,Meta!$A$5:$A$16,"<="&EOMONTH($A35,0)),semanas,COUNTIFS($A$5:$A$35,">="&EOMONTH($A35,-1)+1,$A$5:$A$35,"<="&EOMONTH($A35,0)),posicion,COUNTIFS($A$5:$A35,">="&EOMONTH($A35,-1)+1,$A$5:$A35,"<="&EOMONTH($A35,0)),QUOTIENT(meta,semanas)+IF(posicion<=MOD(meta,semanas),1,0)),"") -> 0 | F35: =IFERROR(SUMIFS(Meta!$B$5:$B$16,Meta!$A$5:$A$16,">="&EOMONTH($A35,-1)+1,Meta!$A$5:$A$16,"<="&EOMONTH($A35,0))/COUNTIFS($A$5:$A$35,">="&EOMONTH($A35,-1)+1,$A$5:$A$35,"<="&EOMONTH($A35,0)),"") -> 0 | G35: =COUNTIFS(Data_Ventas!$E$2:$E1001,">="&A35,Data_Ventas!$E$2:$E1001,"<="&A35+6) -> 0 | H35: =COUNTIFS(Data_Ventas!$A$2:$A1001,">="&A35,Data_Ventas!$A$2:$A1001,"<="&A35+6,Data_Ventas!$H$2:$H1001,"Visitó proyecto") -> 0 | I35: =COUNTIFS(Data_Ventas!$A$2:$A1001,">="&A35,Data_Ventas!$A$2:$A1001,"<="&A35+6,Data_Ventas!$H$2:$H1001,"Separado") -> 0 | J35: =COUNTIFS(Data_Ventas!$A$2:$A1001,">="&A35,Data_Ventas!$A$2:$A1001,"<="&A35+6,Data_Ventas!$H$2:$H1001,"Venta") -> 0 | K35: =SUMIFS(Data_Ventas!$N$2:$N1001,Data_Ventas!$A$2:$A1001,">="&A35,Data_Ventas!$A$2:$A1001,"<="&A35+6,Data_Ventas!$H$2:$H1001,"Venta") -> 0 | L35: =IFERROR(K35/F35,"0%") -> 0%

Sheet eventos
A1: EVENTOS DE CONVERSIÓN — CALENDARIO, PRESUPUESTO, VENTAS, CASH-IN Y ROI
A3: Evento_ID | B3: Fecha | C3: Evento | D3: Tipo | E3: Proyecto | F3: Meta registrados | G3: Registrados real | H3: Meta asistentes | I3: Asistentes real | J3: % asistencia real | K3: Conversión meta | L3: Ventas unid. real | M3: Ticket esperado | N3: Venta proyectada S/ | O3: Venta real S/ | P3: Presupuesto | Q3: Costo real | R3: Cash-in proyectado | S3: Cash-in real | T3: ROI proyectado | U3: ROI real | V3: Venta/S/ costo | W3: Cash-in/S/ costo
A4: EV-001 | B4: 46288 | C4: Visita Proyecto de Prelanzamiento | D4: Visita proyecto | E4: Paraiso de Santa Maria | J4: =IFERROR(I4/G4,"") | N4: =H4*K4*M4 -> 0 | T4: =IFERROR((N4-P4)/P4,"") | U4: =IFERROR((O4-Q4)/Q4,"") | V4: =IFERROR(O4/Q4,"") | W4: =IFERROR(S4/Q4,"")
A5: EV-002 | B5: 46292 | C5: Visita Proyecto de Prelanzamiento | D5: Visita proyecto | E5: Paraiso de Santa Maria | J5: =IFERROR(I5/G5,"") | N5: =H5*K5*M5 -> 0 | T5: =IFERROR((N5-P5)/P5,"") | U5: =IFERROR((O5-Q5)/Q5,"") | V5: =IFERROR(O5/Q5,"") | W5: =IFERROR(S5/Q5,"")
A6: EV-003 | B6: 46295 | C6: Visita Proyecto de Prelanzamiento | D6: Visita proyecto | E6: Paraiso de Santa Maria | J6: =IFERROR(I6/G6,"") | N6: =H6*K6*M6 -> 0 | T6: =IFERROR((N6-P6)/P6,"") | U6: =IFERROR((O6-Q6)/Q6,"") | V6: =IFERROR(O6/Q6,"") | W6: =IFERROR(S6/Q6,"")
A7: EV-004 | B7: 46299 | C7: Visita Proyecto de Prelanzamiento | D7: Visita proyecto | E7: Paraiso de Santa Maria | J7: =IFERROR(I7/G7,"") | N7: =H7*K7*M7 -> 0 | T7: =IFERROR((N7-P7)/P7,"") | U7: =IFERROR((O7-Q7)/Q7,"") | V7: =IFERROR(O7/Q7,"") | W7: =IFERROR(S7/Q7,"")
A8: EV-005 | B8: 46302 | C8: Visita Proyecto de Prelanzamiento | D8: Visita proyecto | E8: Paraiso de Santa Maria | J8: =IFERROR(I8/G8,"") | N8: =H8*K8*M8 -> 0 | T8: =IFERROR((N8-P8)/P8,"") | U8: =IFERROR((O8-Q8)/Q8,"") | V8: =IFERROR(O8/Q8,"") | W8: =IFERROR(S8/Q8,"")
A9: EV-006 | B9: 46306 | C9: Visita Proyecto de Prelanzamiento | D9: Visita proyecto | E9: Paraiso de Santa Maria | J9: =IFERROR(I9/G9,"") | N9: =H9*K9*M9 -> 0 | T9: =IFERROR((N9-P9)/P9,"") | U9: =IFERROR((O9-Q9)/Q9,"") | V9: =IFERROR(O9/Q9,"") | W9: =IFERROR(S9/Q9,"")
A10: EV-007 | B10: 46309 | C10: Visita Proyecto de Prelanzamiento | D10: Visita proyecto | E10: Paraiso de Santa Maria | J10: =IFERROR(I10/G10,"") | N10: =H10*K10*M10 -> 0 | T10: =IFERROR((N10-P10)/P10,"") | U10: =IFERROR((O10-Q10)/Q10,"") | V10: =IFERROR(O10/Q10,"") | W10: =IFERROR(S10/Q10,"")
A11: EV-008 | B11: 46311 | C11: Coctel de inversionistas - Pre lanzamiento Oficial de Paraiso de Santa Maria | D11: Coctel Inversionista | E11: Paraiso de Santa Maria | F11: 80 | G11: 60 | H11: 40 | I11: 40 | J11: =IFERROR(I11/G11,"") -> 0.66666667 | K11: 0.12 | M11: 39000 | N11: =H11*K11*M11 -> 187200 | O11: 200000 | P11: 6000 | Q11: 5600 | R11: 84525 | S11: 76000 | T11: =IFERROR((N11-P11)/P11,"") -> 30.2 | U11: =IFERROR((O11-Q11)/Q11,"") -> 34.714286 | V11: =IFERROR(O11/Q11,"") -> 35.714286 | W11: =IFERROR(S11/Q11,"") -> 13.571429
A12: EV-009 | B12: 46313 | C12: Cierre de Pre-Lanzamiento | D12: Evento Proyecto | E12: Paraiso de Santa Maria | F12: 90 | G12: 82 | H12: 50 | I12: 48 | J12: =IFERROR(I12/G12,"") -> 0.58536585 | K12: 0.14 | N12: =H12*K12*M12 -> 0 | O12: 287500 | P12: 8000 | Q12: 7600 | R12: 140875 | S12: 90000 | T12: =IFERROR((N12-P12)/P12,"") -> -1 | U12: =IFERROR((O12-Q12)/Q12,"") -> 36.828947 | V12: =IFERROR(O12/Q12,"") -> 37.828947 | W12: =IFERROR(S12/Q12,"") -> 11.842105
A13: EV-010 | B13: 46316 | C13: Visita Cierre de Prelanzamiento | D13: Visita proyecto | E13: Paraiso de Santa Maria | N13: =H13*K13*M13 -> 0 | T13: =IFERROR((N13-P13)/P13,"") | U13: =IFERROR((O13-Q13)/Q13,"") | V13: =IFERROR(O13/Q13,"") | W13: =IFERROR(S13/Q13,"")
A14: EV-011 | B14: 46320 | C14: Gran Lanzamiento - Proyecto Paraiso de Santa Maria | D14: Evento Proyecto | E14: Paraiso de Santa Maria | N14: =H14*K14*M14 -> 0 | T14: =IFERROR((N14-P14)/P14,"") | U14: =IFERROR((O14-Q14)/Q14,"") | V14: =IFERROR(O14/Q14,"") | W14: =IFERROR(S14/Q14,"")
A15: EV-012 | B15: 46323 | C15: Visita Proyecto lanzamiento | D15: Visita proyecto | E15: Paraiso de Santa Maria | N15: =H15*K15*M15 -> 0 | T15: =IFERROR((N15-P15)/P15,"") | U15: =IFERROR((O15-Q15)/Q15,"") | V15: =IFERROR(O15/Q15,"") | W15: =IFERROR(S15/Q15,"")
A16: EV-013 | B16: 46326 | C16: Visita Proyecto lanzamiento | D16: Visita proyecto | E16: Paraiso de Santa Maria | N16: =H16*K16*M16 -> 0 | T16: =IFERROR((N16-P16)/P16,"") | U16: =IFERROR((O16-Q16)/Q16,"") | V16: =IFERROR(O16/Q16,"") | W16: =IFERROR(S16/Q16,"")
A17: EV-014 | B17: 46330 | C17: Visita Proyecto lanzamiento | D17: Visita proyecto | E17: Paraiso de Santa Maria | N17: =H17*K17*M17 -> 0 | T17: =IFERROR((N17-P17)/P17,"") | U17: =IFERROR((O17-Q17)/Q17,"") | V17: =IFERROR(O17/Q17,"") | W17: =IFERROR(S17/Q17,"")
A18: EV-015 | B18: 46334 | C18: Visita Proyecto lanzamiento | D18: Visita proyecto | E18: Paraiso de Santa Maria | N18: =H18*K18*M18 -> 0 | T18: =IFERROR((N18-P18)/P18,"") | U18: =IFERROR((O18-Q18)/Q18,"") | V18: =IFERROR(O18/Q18,"") | W18: =IFERROR(S18/Q18,"")
A19: EV-016 | B19: 46337 | C19: Visita Proyecto lanzamiento | D19: Visita proyecto | E19: Paraiso de Santa Maria | N19: =H19*K19*M19 -> 0 | T19: =IFERROR((N19-P19)/P19,"") | U19: =IFERROR((O19-Q19)/Q19,"") | V19: =IFERROR(O19/Q19,"") | W19: =IFERROR(S19/Q19,"")
A20: EV-017 | B20: 46341 | C20: Visita Proyecto lanzamiento | D20: Visita proyecto | E20: Paraiso de Santa Maria | N20: =H20*K20*M20 -> 0 | T20: =IFERROR((N20-P20)/P20,"") | U20: =IFERROR((O20-Q20)/Q20,"") | V20: =IFERROR(O20/Q20,"") | W20: =IFERROR(S20/Q20,"")
A21: EV-018 | B21: 46344 | C21: Visita Proyecto lanzamiento | D21: Visita proyecto | E21: Paraiso de Santa Maria | N21: =H21*K21*M21 -> 0 | T21: =IFERROR((N21-P21)/P21,"") | U21: =IFERROR((O21-Q21)/Q21,"") | V21: =IFERROR(O21/Q21,"") | W21: =IFERROR(S21/Q21,"")
A22: EV-019 | B22: 46346 | C22: Coctel de inversionistas - Cierre de Preventa Paraiso de Santa Maria | D22: Coctel Inversionista | E22: Paraiso de Santa Maria | N22: =H22*K22*M22 -> 0 | T22: =IFERROR((N22-P22)/P22,"") | U22: =IFERROR((O22-Q22)/Q22,"") | V22: =IFERROR(O22/Q22,"") | W22: =IFERROR(S22/Q22,"")
A23: EV-020 | B23: 46348 | C23: Visita Proyecto lanzamiento | D23: Visita proyecto | E23: Paraiso de Santa Maria | N23: =H23*K23*M23 -> 0 | T23: =IFERROR((N23-P23)/P23,"") | U23: =IFERROR((O23-Q23)/Q23,"") | V23: =IFERROR(O23/Q23,"") | W23: =IFERROR(S23/Q23,"")
A24: EV-021 | B24: 46351 | C24: Visita Proyecto lanzamiento | D24: Visita proyecto | E24: Paraiso de Santa Maria | N24: =H24*K24*M24 -> 0 | T24: =IFERROR((N24-P24)/P24,"") | U24: =IFERROR((O24-Q24)/Q24,"") | V24: =IFERROR(O24/Q24,"") | W24: =IFERROR(S24/Q24,"")
A25: EV-022 | B25: 46355 | C25: Gran Cierra Puertas 2026 | D25: Evento Proyecto | E25: Paraiso de Santa Maria | J25: =IFERROR(I25/G25,"") | N25: =H25*K25*M25 -> 0 | T25: =IFERROR((N25-P25)/P25,"") | U25: =IFERROR((O25-Q25)/Q25,"") | V25: =IFERROR(O25/Q25,"") | W25: =IFERROR(S25/Q25,"")
A26: EV-023 | B26: 46358 | C26: Visita Proyecto lanzamiento | D26: Visita proyecto | E26: Paraiso de Santa Maria | N26: =H26*K26*M26 -> 0 | T26: =IFERROR((N26-P26)/P26,"") | U26: =IFERROR((O26-Q26)/Q26,"") | V26: =IFERROR(O26/Q26,"") | W26: =IFERROR(S26/Q26,"")
A27: EV-024 | B27: 46362 | C27: Visita Proyecto lanzamiento | D27: Visita proyecto | E27: Paraiso de Santa Maria | N27: =H27*K27*M27 -> 0 | T27: =IFERROR((N27-P27)/P27,"") | U27: =IFERROR((O27-Q27)/Q27,"") | V27: =IFERROR(O27/Q27,"") | W27: =IFERROR(S27/Q27,"")
A28: EV-025 | B28: 46365 | C28: Visita Proyecto lanzamiento | D28: Visita proyecto | E28: Paraiso de Santa Maria | N28: =H28*K28*M28 -> 0 | T28: =IFERROR((N28-P28)/P28,"") | U28: =IFERROR((O28-Q28)/Q28,"") | V28: =IFERROR(O28/Q28,"") | W28: =IFERROR(S28/Q28,"")
A29: EV-026 | B29: 46369 | C29: Gran Evento Navideño y Cierre de Año | D29: Evento Proyecto | E29: Paraiso de Santa Maria | J29: =IFERROR(I29/G29,"") | N29: =H29*K29*M29 -> 0 | T29: =IFERROR((N29-P29)/P29,"") | U29: =IFERROR((O29-Q29)/Q29,"") | V29: =IFERROR(O29/Q29,"") | W29: =IFERROR(S29/Q29,"")
A30: EV-027 | B30: 46372 | C30: Visita Proyecto lanzamiento | D30: Visita proyecto | E30: Paraiso de Santa Maria | N30: =H30*K30*M30 -> 0 | T30: =IFERROR((N30-P30)/P30,"") | U30: =IFERROR((O30-Q30)/Q30,"") | V30: =IFERROR(O30/Q30,"") | W30: =IFERROR(S30/Q30,"")
A31: EV-028 | B31: 46376 | C31: Visita Proyecto lanzamiento | D31: Visita proyecto | E31: Paraiso de Santa Maria | N31: =H31*K31*M31 -> 0 | T31: =IFERROR((N31-P31)/P31,"") | U31: =IFERROR((O31-Q31)/Q31,"") | V31: =IFERROR(O31/Q31,"") | W31: =IFERROR(S31/Q31,"")
A32: EV-029 | B32: 46383 | C32: Visita Proyecto lanzamiento | D32: Visita proyecto | E32: Paraiso de Santa Maria | N32: =H32*K32*M32 -> 0 | T32: =IFERROR((N32-P32)/P32,"") | U32: =IFERROR((O32-Q32)/Q32,"") | V32: =IFERROR(O32/Q32,"") | W32: =IFERROR(S32/Q32,"")
T33: =IFERROR((N33-P33)/P33,"") | U33: =IFERROR((O33-Q33)/Q33,"") | V33: =IFERROR(O33/Q33,"") | W33: =IFERROR(S33/Q33,"")

Sheet Asesores
A1: RESULTADOS POR VENDEDOR
A2: Desde | B2: =Dashboard!C5 -> 45930 | D2: Hasta | E2: =Dashboard!E5 -> 46295
A4: Vendedor | B4: Lider | C4: Estado | D4: Fecha ingreso | E4: Meta Unid Mensual | F4: Meta S/. Mensual | G4: Meta Unid Acumulada | H4: Meta S/. acumulada | I4: Leads | J4: Agendados | K4: Visitas | L4: Separaciones | M4: Ventas Cant | N4: Venta S/. | O4: % meta venta | P4: Conv. Lead→Venta | Q4: Conv. Visita→Venta | R4: Venta/lead S/ | S4: ticket promedio | T4: desc. promo | U4: Cash-in S/. | V4: Cash-in % | W4: Inicial promedio % | X4: % descto | Y4: % cancelaciones | Z4: consolidación % | AA4: Dias de cierre | AB4: Ranking | AC4: estado | AD4: calidad vendedor | AF4: Cumplimiento Meta | AG4: Score Comercial | AI4: productividad por asesor; | AJ4: tiempo de respuesta al lead.
A5: Vicente Quispe | B5: JeanPaul Campos | C5: Activo | E5: 3 | F5: =E5*Configuracion!$B$15 -> 120000 | G5: =ROUNDUP((DATEDIF($B$2,$E$2,"m")+(DAY($E$2)/DAY(EOMONTH($E$2,0))))*E5,0) -> 39 | H5: =G5*Configuracion!$B$15 -> 1560000 | I5: =COUNTIFS(Data_Ventas!$E$2:$E958,A5,Data_Ventas!$A$2:$A958,">="&$B$2,Data_Ventas!$A$2:$A958,"<="&$E$2) -> 2 | J5: =COUNTIFS(Data_Ventas!$E$2:$E958,A5,Data_Ventas!$A$2:$A958,">="&$B$2,Data_Ventas!$A$2:$A958,"<="&$E$2,Data_Ventas!$H$2:$H958,"Visitó proyecto") -> 0 | K5: =COUNTIFS(Data_Ventas!$E$2:$E958,A5,Data_Ventas!$A$2:$A958,">="&$B$2,Data_Ventas!$A$2:$A958,"<="&$E$2,Data_Ventas!$H$2:$H958,"Visitó proyecto") -> 0 | L5: =COUNTIFS(Data_Ventas!$E$2:$E958,A5,Data_Ventas!$A$2:$A958,">="&$B$2,Data_Ventas!$A$2:$A958,"<="&$E$2,Data_Ventas!$H$2:$H958,"Separado") -> 0 | M5: =COUNTIFS(Data_Ventas!$E$2:$E958,A5,Data_Ventas!$A$2:$A958,">="&$B$2,Data_Ventas!$A$2:$A958,"<="&$E$2,Data_Ventas!$H$2:$H958,"Venta") -> 1 | N5: =SUMIFS(Data_Ventas!$N$2:$N958,Data_Ventas!$E$2:$E958,A5,Data_Ventas!$A$2:$A958,">="&$B$2,Data_Ventas!$A$2:$A958,"<="&$E$2,Data_Ventas!$H$2:$H958,"Venta") -> 40000 | O5: =N5/H5 -> 0.025641026 | P5: =IFERROR(M5/I5,0) -> 0.5 | Q5: =IFERROR(M5/K5,0) -> 0 | R5: =IFERROR(N5/I5,0) -> 20000 | S5: =IFERROR(N5/M5,0) -> 40000 | T5: =SUMIFS(Data_Ventas!$O$2:$O958,Data_Ventas!$E$2:$E958,A5,Data_Ventas!$A$2:$A958,">="&$B$2,Data_Ventas!$A$2:$A958,"<="&$E$2,Data_Ventas!$H$2:$H958,"Venta") -> 0 | U5: =SUMIFS(Data_Ventas!$R$2:$R958,Data_Ventas!$E$2:$E958,A5,Data_Ventas!$A$2:$A958,">="&$B$2,Data_Ventas!$A$2:$A958,"<="&$E$2,Data_Ventas!$H$2:$H958,"Venta") -> 5000 | V5: =IFERROR(U5/N5,"0%") -> 0.125 | W5: =IFERROR((SUMIFS(Data_Ventas!$R$2:$R958,Data_Ventas!$E$2:$E958,A5,Data_Ventas!$A$2:$A958,">="&$B$2,Data_Ventas!$A$2:$A958,"<="&$E$2,Data_Ventas!$H$2:$H958,"Venta",Data_Ventas!$Q$2:$Q958,Dashboard!$B$34))/(SUMIFS(Data_Ventas!$N$2:$N958,Data_Ventas!$E$2:$E958,A5,Data_Ventas!$A$2:$A958,">="&$B$2,Data_Ventas!$A$2:$A958,"<="&$E$2,Data_Ventas!$H$2:$H958,"Venta",Data_Ventas!$Q$2:$Q958,Dashboard!$B$34)),"0%") -> 0.125 | X5: =IFERROR((SUMIFS(Data_Ventas!$O$2:$O958,Data_Ventas!$E$2:$E958,A5,Data_Ventas!$A$2:$A958,">="&$B$2,Data_Ventas!$A$2:$A958,"<="&$E$2,Data_Ventas!$H$2:$H958,"Venta"))/(SUMIFS(Data_Ventas!$M$2:$M958,Data_Ventas!$E$2:$E958,A5,Data_Ventas!$A$2:$A958,">="&$B$2,Data_Ventas!$A$2:$A958,"<="&$E$2,Data_Ventas!$H$2:$H958,"Venta")),"0%") -> 0 | Y5: =IFERROR(N5/(SUMIFS(Data_Ventas!$N$2:$N958,Data_Ventas!$E$2:$E958,A5,Data_Ventas!$A$2:$A958,">="&$B$2,Data_Ventas!$A$2:$A958,"<="&$E$2,Data_Ventas!$H$2:$H958,"Venta Perdida")),0%) -> 1 | Z5: =IFERROR(N5/(N5+(SUMIFS(Data_Ventas!$N$2:$N958,Data_Ventas!$E$2:$E958,A5,Data_Ventas!$A$2:$A958,">="&$B$2,Data_Ventas!$A$2:$A958,"<="&$E$2,Data_Ventas!$H$2:$H958,"Venta Perdida"))),"0%") -> 0.5 | AB5: =_xlfn.RANK.EQ(N5,$N$5:$N$14,0)+COUNTIF($N$5:N5,N5)-1 -> 5 | AC5: =IF(Q5>=0.18,"🟢",IF(Q5>=0.14,"🟡","🔴")) -> 🔴 | AD5: =((MIN(V5/Configuracion!$B$20,1)*30%)+(MIN(W5/Configuracion!$B$21,1)*20%)+(MAX(0,1-(X5/Configuracion!$B$22)*20%)*20%)+(IF(Y5=0,1,MIN(Configuracion!$B$23/Y5,1))*20%)+(MIN(Z5/Configuracion!$B$24,1)*10%))*100 -> 49.477444 | AE5: =IF(AD5>=90,"🟢 Ventas de alta calidad",IF(AD5>=80,"🟡 Ventas calidad aceptable, revisar",IF(AD5>=70,"🟠 Venta calidad débil","🔴 Mala calidad comercial"))) -> 🔴 Mala calidad comercial | AF5: =IFERROR((N5/H5)*100,"") -> 2.5641026 | AG5: =(AF5*60%)+(40%*AD5) -> 21.329439
A6: Alfredo Caceda | B6: Vicente Quispe | C6: Activo | E6: 3 | F6: =E6*Configuracion!$B$15 -> 120000 | G6: =ROUNDUP((DATEDIF($B$2,$E$2,"m")+(DAY($E$2)/DAY(EOMONTH($E$2,0))))*E6,0) -> 39 | H6: =G6*Configuracion!$B$15 -> 1560000 | I6: =COUNTIFS(Data_Ventas!$E$2:$E958,A6,Data_Ventas!$A$2:$A958,">="&$B$2,Data_Ventas!$A$2:$A958,"<="&$E$2) -> 3 | J6: =COUNTIFS(Data_Ventas!$E$2:$E958,A6,Data_Ventas!$A$2:$A958,">="&$B$2,Data_Ventas!$A$2:$A958,"<="&$E$2,Data_Ventas!$H$2:$H958,"Visitó proyecto") -> 0 | K6: =COUNTIFS(Data_Ventas!$E$2:$E958,A6,Data_Ventas!$A$2:$A958,">="&$B$2,Data_Ventas!$A$2:$A958,"<="&$E$2,Data_Ventas!$H$2:$H958,"Visitó proyecto") -> 0 | L6: =COUNTIFS(Data_Ventas!$E$2:$E958,A6,Data_Ventas!$A$2:$A958,">="&$B$2,Data_Ventas!$A$2:$A958,"<="&$E$2,Data_Ventas!$H$2:$H958,"Separado") -> 0 | M6: =COUNTIFS(Data_Ventas!$E$2:$E958,A6,Data_Ventas!$A$2:$A958,">="&$B$2,Data_Ventas!$A$2:$A958,"<="&$E$2,Data_Ventas!$H$2:$H958,"Venta") -> 3 | N6: =SUMIFS(Data_Ventas!$N$2:$N958,Data_Ventas!$E$2:$E958,A6,Data_Ventas!$A$2:$A958,">="&$B$2,Data_Ventas!$A$2:$A958,"<="&$E$2,Data_Ventas!$H$2:$H958,"Venta") -> 125000 | O6: =N6/H6 -> 0.080128205 | P6: =IFERROR(M6/I6,0) -> 1 | Q6: =IFERROR(M6/K6,0) -> 0 | R6: =IFERROR(N6/I6,0) -> 41666.667 | S6: =IFERROR(N6/M6,0) -> 41666.667 | T6: =SUMIFS(Data_Ventas!$O$2:$O958,Data_Ventas!$E$2:$E958,A6,Data_Ventas!$A$2:$A958,">="&$B$2,Data_Ventas!$A$2:$A958,"<="&$E$2,Data_Ventas!$H$2:$H958,"Venta") -> 0 | U6: =SUMIFS(Data_Ventas!$R$2:$R958,Data_Ventas!$E$2:$E958,A6,Data_Ventas!$A$2:$A958,">="&$B$2,Data_Ventas!$A$2:$A958,"<="&$E$2,Data_Ventas!$H$2:$H958,"Venta") -> 8250 | V6: =IFERROR(U6/N6,"0%") -> 0.066 | W6: =IFERROR((SUMIFS(Data_Ventas!$R$2:$R958,Data_Ventas!$E$2:$E958,A6,Data_Ventas!$A$2:$A958,">="&$B$2,Data_Ventas!$A$2:$A958,"<="&$E$2,Data_Ventas!$H$2:$H958,"Venta",Data_Ventas!$Q$2:$Q958,Dashboard!$B$34))/(SUMIFS(Data_Ventas!$N$2:$N958,Data_Ventas!$E$2:$E958,A6,Data_Ventas!$A$2:$A958,">="&$B$2,Data_Ventas!$A$2:$A958,"<="&$E$2,Data_Ventas!$H$2:$H958,"Venta",Data_Ventas!$Q$2:$Q958,Dashboard!$B$34)),"0%") -> 0.066 | X6: =IFERROR((SUMIFS(Data_Ventas!$O$2:$O958,Data_Ventas!$E$2:$E958,A6,Data_Ventas!$A$2:$A958,">="&$B$2,Data_Ventas!$A$2:$A958,"<="&$E$2,Data_Ventas!$H$2:$H958,"Venta"))/(SUMIFS(Data_Ventas!$M$2:$M958,Data_Ventas!$E$2:$E958,A6,Data_Ventas!$A$2:$A958,">="&$B$2,Data_Ventas!$A$2:$A958,"<="&$E$2,Data_Ventas!$H$2:$H958,"Venta")),"0%") -> 0 | Y6: =IFERROR(N6/(SUMIFS(Data_Ventas!$N$2:$N958,Data_Ventas!$E$2:$E958,A6,Data_Ventas!$A$2:$A958,">="&$B$2,Data_Ventas!$A$2:$A958,"<="&$E$2,Data_Ventas!$H$2:$H958,"Venta Perdida")),0%) -> 0 | Z6: =IFERROR(N6/(N6+(SUMIFS(Data_Ventas!$N$2:$N958,Data_Ventas!$E$2:$E958,A6,Data_Ventas!$A$2:$A958,">="&$B$2,Data_Ventas!$A$2:$A958,"<="&$E$2,Data_Ventas!$H$2:$H958,"Venta Perdida"))),"0%") -> 1 | AB6: =_xlfn.RANK.EQ(N6,$N$5:$N$14,0)+COUNTIF($N$5:N6,N6)-1 -> 3 | AC6: =IF(Q6>=0.18,"🟢",IF(Q6>=0.14,"🟡","🔴")) -> 🔴 | AD6: =((MIN(V6/Configuracion!$B$20,1)*30%)+(MIN(W6/Configuracion!$B$21,1)*20%)+(MAX(0,1-(X6/Configuracion!$B$22)*20%)*20%)+(IF(Y6=0,1,MIN(Configuracion!$B$23/Y6,1))*20%)+(MIN(Z6/Configuracion!$B$24,1)*10%))*100 -> 62.257143 | AE6: =IF(AD6>=90,"🟢 Ventas de alta calidad",IF(AD6>=80,"🟡 Ventas calidad aceptable, revisar",IF(AD6>=70,"🟠 Venta calidad débil","🔴 Mala calidad comercial"))) -> 🔴 Mala calidad comercial | AF6: =IFERROR((N6/H6)*100,"") -> 8.0128205 | AG6: =(AF6*60%)+(40%*AD6) -> 29.710549
A7: Jhovana | B7: Alfredo Caceda | C7: Activo | E7: 3 | F7: =E7*Configuracion!$B$15 -> 120000 | G7: =ROUNDUP((DATEDIF($B$2,$E$2,"m")+(DAY($E$2)/DAY(EOMONTH($E$2,0))))*E7,0) -> 39 | H7: =G7*Configuracion!$B$15 -> 1560000 | I7: =COUNTIFS(Data_Ventas!$E$2:$E958,A7,Data_Ventas!$A$2:$A958,">="&$B$2,Data_Ventas!$A$2:$A958,"<="&$E$2) -> 0 | J7: =COUNTIFS(Data_Ventas!$E$2:$E958,A7,Data_Ventas!$A$2:$A958,">="&$B$2,Data_Ventas!$A$2:$A958,"<="&$E$2,Data_Ventas!$H$2:$H958,"Visitó proyecto") -> 0 | K7: =COUNTIFS(Data_Ventas!$E$2:$E958,A7,Data_Ventas!$A$2:$A958,">="&$B$2,Data_Ventas!$A$2:$A958,"<="&$E$2,Data_Ventas!$H$2:$H958,"Visitó proyecto") -> 0 | L7: =COUNTIFS(Data_Ventas!$E$2:$E958,A7,Data_Ventas!$A$2:$A958,">="&$B$2,Data_Ventas!$A$2:$A958,"<="&$E$2,Data_Ventas!$H$2:$H958,"Separado") -> 0 | M7: =COUNTIFS(Data_Ventas!$E$2:$E958,A7,Data_Ventas!$A$2:$A958,">="&$B$2,Data_Ventas!$A$2:$A958,"<="&$E$2,Data_Ventas!$H$2:$H958,"Venta") -> 0 | N7: =SUMIFS(Data_Ventas!$N$2:$N958,Data_Ventas!$E$2:$E958,A7,Data_Ventas!$A$2:$A958,">="&$B$2,Data_Ventas!$A$2:$A958,"<="&$E$2,Data_Ventas!$H$2:$H958,"Venta") -> 0 | O7: =N7/H7 -> 0 | P7: =IFERROR(M7/I7,0) -> 0 | Q7: =IFERROR(M7/K7,0) -> 0 | R7: =IFERROR(N7/I7,0) -> 0 | S7: =IFERROR(N7/M7,0) -> 0 | T7: =SUMIFS(Data_Ventas!$O$2:$O958,Data_Ventas!$E$2:$E958,A7,Data_Ventas!$A$2:$A958,">="&$B$2,Data_Ventas!$A$2:$A958,"<="&$E$2,Data_Ventas!$H$2:$H958,"Venta") -> 0 | U7: =SUMIFS(Data_Ventas!$R$2:$R958,Data_Ventas!$E$2:$E958,A7,Data_Ventas!$A$2:$A958,">="&$B$2,Data_Ventas!$A$2:$A958,"<="&$E$2,Data_Ventas!$H$2:$H958,"Venta") -> 0 | V7: =IFERROR(U7/N7,"0%") -> 0% | W7: =IFERROR((SUMIFS(Data_Ventas!$R$2:$R958,Data_Ventas!$E$2:$E958,A7,Data_Ventas!$A$2:$A958,">="&$B$2,Data_Ventas!$A$2:$A958,"<="&$E$2,Data_Ventas!$H$2:$H958,"Venta",Data_Ventas!$Q$2:$Q958,Dashboard!$B$34))/(SUMIFS(Data_Ventas!$N$2:$N958,Data_Ventas!$E$2:$E958,A7,Data_Ventas!$A$2:$A958,">="&$B$2,Data_Ventas!$A$2:$A958,"<="&$E$2,Data_Ventas!$H$2:$H958,"Venta",Data_Ventas!$Q$2:$Q958,Dashboard!$B$34)),"0%") -> 0% | X7: =IFERROR((SUMIFS(Data_Ventas!$O$2:$O958,Data_Ventas!$E$2:$E958,A7,Data_Ventas!$A$2:$A958,">="&$B$2,Data_Ventas!$A$2:$A958,"<="&$E$2,Data_Ventas!$H$2:$H958,"Venta"))/(SUMIFS(Data_Ventas!$M$2:$M958,Data_Ventas!$E$2:$E958,A7,Data_Ventas!$A$2:$A958,">="&$B$2,Data_Ventas!$A$2:$A958,"<="&$E$2,Data_Ventas!$H$2:$H958,"Venta")),"0%") -> 0% | Y7: =IFERROR(N7/(SUMIFS(Data_Ventas!$N$2:$N958,Data_Ventas!$E$2:$E958,A7,Data_Ventas!$A$2:$A958,">="&$B$2,Data_Ventas!$A$2:$A958,"<="&$E$2,Data_Ventas!$H$2:$H958,"Venta Perdida")),0%) -> 0 | Z7: =IFERROR(N7/(N7+(SUMIFS(Data_Ventas!$N$2:$N958,Data_Ventas!$E$2:$E958,A7,Data_Ventas!$A$2:$A958,">="&$B$2,Data_Ventas!$A$2:$A958,"<="&$E$2,Data_Ventas!$H$2:$H958,"Venta Perdida"))),"0%") -> 0% | AB7: =_xlfn.RANK.EQ(N7,$N$5:$N$14,0)+COUNTIF($N$5:N7,N7)-1 -> 6 | AC7: =IF(Q7>=0.18,"🟢",IF(Q7>=0.14,"🟡","🔴")) -> 🔴 | AD7: =((MIN(V7/Configuracion!$B$20,1)*30%)+(MIN(W7/Configuracion!$B$21,1)*20%)+(MAX(0,1-(X7/Configuracion!$B$22)*20%)*20%)+(IF(Y7=0,1,MIN(Configuracion!$B$23/Y7,1))*20%)+(MIN(Z7/Configuracion!$B$24,1)*10%))*100 -> 40 | AE7: =IF(AD7>=90,"🟢 Ventas de alta calidad",IF(AD7>=80,"🟡 Ventas calidad aceptable, revisar",IF(AD7>=70,"🟠 Venta calidad débil","🔴 Mala calidad comercial"))) -> 🔴 Mala calidad comercial | AF7: =IFERROR((N7/H7)*100,"") -> 0 | AG7: =(AF7*60%)+(40%*AD7) -> 16
A8: JeanPaul Campos | C8: Activo | E8: 3 | F8: =E8*Configuracion!$B$15 -> 120000 | G8: =ROUNDUP((DATEDIF($B$2,$E$2,"m")+(DAY($E$2)/DAY(EOMONTH($E$2,0))))*E8,0) -> 39 | H8: =G8*Configuracion!$B$15 -> 1560000 | I8: =COUNTIFS(Data_Ventas!$E$2:$E958,A8,Data_Ventas!$A$2:$A958,">="&$B$2,Data_Ventas!$A$2:$A958,"<="&$E$2) -> 3 | J8: =COUNTIFS(Data_Ventas!$E$2:$E958,A8,Data_Ventas!$A$2:$A958,">="&$B$2,Data_Ventas!$A$2:$A958,"<="&$E$2,Data_Ventas!$H$2:$H958,"Visitó proyecto") -> 0 | K8: =COUNTIFS(Data_Ventas!$E$2:$E958,A8,Data_Ventas!$A$2:$A958,">="&$B$2,Data_Ventas!$A$2:$A958,"<="&$E$2,Data_Ventas!$H$2:$H958,"Visitó proyecto") -> 0 | L8: =COUNTIFS(Data_Ventas!$E$2:$E958,A8,Data_Ventas!$A$2:$A958,">="&$B$2,Data_Ventas!$A$2:$A958,"<="&$E$2,Data_Ventas!$H$2:$H958,"Separado") -> 0 | M8: =COUNTIFS(Data_Ventas!$E$2:$E958,A8,Data_Ventas!$A$2:$A958,">="&$B$2,Data_Ventas!$A$2:$A958,"<="&$E$2,Data_Ventas!$H$2:$H958,"Venta") -> 3 | N8: =SUMIFS(Data_Ventas!$N$2:$N958,Data_Ventas!$E$2:$E958,A8,Data_Ventas!$A$2:$A958,">="&$B$2,Data_Ventas!$A$2:$A958,"<="&$E$2,Data_Ventas!$H$2:$H958,"Venta") -> 168224.5 | O8: =N8/H8 -> 0.10783622 | P8: =IFERROR(M8/I8,0) -> 1 | Q8: =IFERROR(M8/K8,0) -> 0 | R8: =IFERROR(N8/I8,0) -> 56074.833 | S8: =IFERROR(N8/M8,0) -> 56074.833 | T8: =SUMIFS(Data_Ventas!$O$2:$O958,Data_Ventas!$E$2:$E958,A8,Data_Ventas!$A$2:$A958,">="&$B$2,Data_Ventas!$A$2:$A958,"<="&$E$2,Data_Ventas!$H$2:$H958,"Venta") -> 0 | U8: =SUMIFS(Data_Ventas!$R$2:$R958,Data_Ventas!$E$2:$E958,A8,Data_Ventas!$A$2:$A958,">="&$B$2,Data_Ventas!$A$2:$A958,"<="&$E$2,Data_Ventas!$H$2:$H958,"Venta") -> 104360 | V8: =IFERROR(U8/N8,"0%") -> 0.62036148 | W8: =IFERROR((SUMIFS(Data_Ventas!$R$2:$R958,Data_Ventas!$E$2:$E958,A8,Data_Ventas!$A$2:$A958,">="&$B$2,Data_Ventas!$A$2:$A958,"<="&$E$2,Data_Ventas!$H$2:$H958,"Venta",Data_Ventas!$Q$2:$Q958,Dashboard!$B$34))/(SUMIFS(Data_Ventas!$N$2:$N958,Data_Ventas!$E$2:$E958,A8,Data_Ventas!$A$2:$A958,">="&$B$2,Data_Ventas!$A$2:$A958,"<="&$E$2,Data_Ventas!$H$2:$H958,"Venta",Data_Ventas!$Q$2:$Q958,Dashboard!$B$34)),"0%") -> 0.015416753 | X8: =IFERROR((SUMIFS(Data_Ventas!$O$2:$O958,Data_Ventas!$E$2:$E958,A8,Data_Ventas!$A$2:$A958,">="&$B$2,Data_Ventas!$A$2:$A958,"<="&$E$2,Data_Ventas!$H$2:$H958,"Venta"))/(SUMIFS(Data_Ventas!$M$2:$M958,Data_Ventas!$E$2:$E958,A8,Data_Ventas!$A$2:$A958,">="&$B$2,Data_Ventas!$A$2:$A958,"<="&$E$2,Data_Ventas!$H$2:$H958,"Venta")),"0%") -> 0 | Y8: =IFERROR(N8/(SUMIFS(Data_Ventas!$N$2:$N958,Data_Ventas!$E$2:$E958,A8,Data_Ventas!$A$2:$A958,">="&$B$2,Data_Ventas!$A$2:$A958,"<="&$E$2,Data_Ventas!$H$2:$H958,"Venta Perdida")),0%) -> 0 | Z8: =IFERROR(N8/(N8+(SUMIFS(Data_Ventas!$N$2:$N958,Data_Ventas!$E$2:$E958,A8,Data_Ventas!$A$2:$A958,">="&$B$2,Data_Ventas!$A$2:$A958,"<="&$E$2,Data_Ventas!$H$2:$H958,"Venta Perdida"))),"0%") -> 1 | AB8: =_xlfn.RANK.EQ(N8,$N$5:$N$14,0)+COUNTIF($N$5:N8,N8)-1 -> 2 | AC8: =IF(Q8>=0.18,"🟢",IF(Q8>=0.14,"🟡","🔴")) -> 🔴 | AD8: =((MIN(V8/Configuracion!$B$20,1)*30%)+(MIN(W8/Configuracion!$B$21,1)*20%)+(MAX(0,1-(X8/Configuracion!$B$22)*20%)*20%)+(IF(Y8=0,1,MIN(Configuracion!$B$23/Y8,1))*20%)+(MIN(Z8/Configuracion!$B$24,1)*10%))*100 -> 81.541675 | AE8: =IF(AD8>=90,"🟢 Ventas de alta calidad",IF(AD8>=80,"🟡 Ventas calidad aceptable, revisar",IF(AD8>=70,"🟠 Venta calidad débil","🔴 Mala calidad comercial"))) -> 🟡 Ventas calidad aceptable, revisar | AF8: =IFERROR((N8/H8)*100,"") -> 10.783622 | AG8: =(AF8*60%)+(40%*AD8) -> 39.086843
A9: Ingrid Villegas | B9: JeanPaul Campos | C9: Activo | E9: 3 | F9: =E9*Configuracion!$B$15 -> 120000 | G9: =ROUNDUP((DATEDIF($B$2,$E$2,"m")+(DAY($E$2)/DAY(EOMONTH($E$2,0))))*E9,0) -> 39 | H9: =G9*Configuracion!$B$15 -> 1560000 | I9: =COUNTIFS(Data_Ventas!$E$2:$E958,A9,Data_Ventas!$A$2:$A958,">="&$B$2,Data_Ventas!$A$2:$A958,"<="&$E$2) -> 0 | J9: =COUNTIFS(Data_Ventas!$E$2:$E958,A9,Data_Ventas!$A$2:$A958,">="&$B$2,Data_Ventas!$A$2:$A958,"<="&$E$2,Data_Ventas!$H$2:$H958,"Visitó proyecto") -> 0 | K9: =COUNTIFS(Data_Ventas!$E$2:$E958,A9,Data_Ventas!$A$2:$A958,">="&$B$2,Data_Ventas!$A$2:$A958,"<="&$E$2,Data_Ventas!$H$2:$H958,"Visitó proyecto") -> 0 | L9: =COUNTIFS(Data_Ventas!$E$2:$E958,A9,Data_Ventas!$A$2:$A958,">="&$B$2,Data_Ventas!$A$2:$A958,"<="&$E$2,Data_Ventas!$H$2:$H958,"Separado") -> 0 | M9: =COUNTIFS(Data_Ventas!$E$2:$E958,A9,Data_Ventas!$A$2:$A958,">="&$B$2,Data_Ventas!$A$2:$A958,"<="&$E$2,Data_Ventas!$H$2:$H958,"Venta") -> 0 | N9: =SUMIFS(Data_Ventas!$N$2:$N958,Data_Ventas!$E$2:$E958,A9,Data_Ventas!$A$2:$A958,">="&$B$2,Data_Ventas!$A$2:$A958,"<="&$E$2,Data_Ventas!$H$2:$H958,"Venta") -> 0 | O9: =N9/H9 -> 0 | P9: =IFERROR(M9/I9,0) -> 0 | Q9: =IFERROR(M9/K9,0) -> 0 | R9: =IFERROR(N9/I9,0) -> 0 | S9: =IFERROR(N9/M9,0) -> 0 | T9: =SUMIFS(Data_Ventas!$O$2:$O958,Data_Ventas!$E$2:$E958,A9,Data_Ventas!$A$2:$A958,">="&$B$2,Data_Ventas!$A$2:$A958,"<="&$E$2,Data_Ventas!$H$2:$H958,"Venta") -> 0 | U9: =SUMIFS(Data_Ventas!$R$2:$R958,Data_Ventas!$E$2:$E958,A9,Data_Ventas!$A$2:$A958,">="&$B$2,Data_Ventas!$A$2:$A958,"<="&$E$2,Data_Ventas!$H$2:$H958,"Venta") -> 0 | V9: =IFERROR(U9/N9,"0%") -> 0% | W9: =IFERROR((SUMIFS(Data_Ventas!$R$2:$R958,Data_Ventas!$E$2:$E958,A9,Data_Ventas!$A$2:$A958,">="&$B$2,Data_Ventas!$A$2:$A958,"<="&$E$2,Data_Ventas!$H$2:$H958,"Venta",Data_Ventas!$Q$2:$Q958,Dashboard!$B$34))/(SUMIFS(Data_Ventas!$N$2:$N958,Data_Ventas!$E$2:$E958,A9,Data_Ventas!$A$2:$A958,">="&$B$2,Data_Ventas!$A$2:$A958,"<="&$E$2,Data_Ventas!$H$2:$H958,"Venta",Data_Ventas!$Q$2:$Q958,Dashboard!$B$34)),"0%") -> 0% | X9: =IFERROR((SUMIFS(Data_Ventas!$O$2:$O958,Data_Ventas!$E$2:$E958,A9,Data_Ventas!$A$2:$A958,">="&$B$2,Data_Ventas!$A$2:$A958,"<="&$E$2,Data_Ventas!$H$2:$H958,"Venta"))/(SUMIFS(Data_Ventas!$M$2:$M958,Data_Ventas!$E$2:$E958,A9,Data_Ventas!$A$2:$A958,">="&$B$2,Data_Ventas!$A$2:$A958,"<="&$E$2,Data_Ventas!$H$2:$H958,"Venta")),"0%") -> 0% | Y9: =IFERROR(N9/(SUMIFS(Data_Ventas!$N$2:$N958,Data_Ventas!$E$2:$E958,A9,Data_Ventas!$A$2:$A958,">="&$B$2,Data_Ventas!$A$2:$A958,"<="&$E$2,Data_Ventas!$H$2:$H958,"Venta Perdida")),0%) -> 0 | Z9: =IFERROR(N9/(N9+(SUMIFS(Data_Ventas!$N$2:$N958,Data_Ventas!$E$2:$E958,A9,Data_Ventas!$A$2:$A958,">="&$B$2,Data_Ventas!$A$2:$A958,"<="&$E$2,Data_Ventas!$H$2:$H958,"Venta Perdida"))),"0%") -> 0% | AB9: =_xlfn.RANK.EQ(N9,$N$5:$N$14,0)+COUNTIF($N$5:N9,N9)-1 -> 7 | AC9: =IF(Q9>=0.18,"🟢",IF(Q9>=0.14,"🟡","🔴")) -> 🔴 | AD9: =((MIN(V9/Configuracion!$B$20,1)*30%)+(MIN(W9/Configuracion!$B$21,1)*20%)+(MAX(0,1-(X9/Configuracion!$B$22)*20%)*20%)+(IF(Y9=0,1,MIN(Configuracion!$B$23/Y9,1))*20%)+(MIN(Z9/Configuracion!$B$24,1)*10%))*100 -> 40 | AE9: =IF(AD9>=90,"🟢 Ventas de alta calidad",IF(AD9>=80,"🟡 Ventas calidad aceptable, revisar",IF(AD9>=70,"🟠 Venta calidad débil","🔴 Mala calidad comercial"))) -> 🔴 Mala calidad comercial | AF9: =IFERROR((N9/H9)*100,"") -> 0 | AG9: =(AF9*60%)+(40%*AD9) -> 16
A10: Josue | B10: Vicente Quispe | C10: No activo | E10: 3 | F10: =E10*Configuracion!$B$15 -> 120000 | G10: =ROUNDUP((DATEDIF($B$2,$E$2,"m")+(DAY($E$2)/DAY(EOMONTH($E$2,0))))*E10,0) -> 39 | H10: =G10*Configuracion!$B$15 -> 1560000 | I10: =COUNTIFS(Data_Ventas!$E$2:$E958,A10,Data_Ventas!$A$2:$A958,">="&$B$2,Data_Ventas!$A$2:$A958,"<="&$E$2) -> 0 | J10: =COUNTIFS(Data_Ventas!$E$2:$E958,A10,Data_Ventas!$A$2:$A958,">="&$B$2,Data_Ventas!$A$2:$A958,"<="&$E$2,Data_Ventas!$H$2:$H958,"Visitó proyecto") -> 0 | K10: =COUNTIFS(Data_Ventas!$E$2:$E958,A10,Data_Ventas!$A$2:$A958,">="&$B$2,Data_Ventas!$A$2:$A958,"<="&$E$2,Data_Ventas!$H$2:$H958,"Visitó proyecto") -> 0 | L10: =COUNTIFS(Data_Ventas!$E$2:$E958,A10,Data_Ventas!$A$2:$A958,">="&$B$2,Data_Ventas!$A$2:$A958,"<="&$E$2,Data_Ventas!$H$2:$H958,"Separado") -> 0 | M10: =COUNTIFS(Data_Ventas!$E$2:$E958,A10,Data_Ventas!$A$2:$A958,">="&$B$2,Data_Ventas!$A$2:$A958,"<="&$E$2,Data_Ventas!$H$2:$H958,"Venta") -> 0 | N10: =SUMIFS(Data_Ventas!$N$2:$N958,Data_Ventas!$E$2:$E958,A10,Data_Ventas!$A$2:$A958,">="&$B$2,Data_Ventas!$A$2:$A958,"<="&$E$2,Data_Ventas!$H$2:$H958,"Venta") -> 0 | O10: =N10/H10 -> 0 | P10: =IFERROR(M10/I10,0) -> 0 | Q10: =IFERROR(M10/K10,0) -> 0 | R10: =IFERROR(N10/I10,0) -> 0 | S10: =IFERROR(N10/M10,0) -> 0 | T10: =SUMIFS(Data_Ventas!$O$2:$O958,Data_Ventas!$E$2:$E958,A10,Data_Ventas!$A$2:$A958,">="&$B$2,Data_Ventas!$A$2:$A958,"<="&$E$2,Data_Ventas!$H$2:$H958,"Venta") -> 0 | U10: =SUMIFS(Data_Ventas!$R$2:$R958,Data_Ventas!$E$2:$E958,A10,Data_Ventas!$A$2:$A958,">="&$B$2,Data_Ventas!$A$2:$A958,"<="&$E$2,Data_Ventas!$H$2:$H958,"Venta") -> 0 | V10: =IFERROR(U10/N10,"0%") -> 0% | W10: =IFERROR((SUMIFS(Data_Ventas!$R$2:$R958,Data_Ventas!$E$2:$E958,A10,Data_Ventas!$A$2:$A958,">="&$B$2,Data_Ventas!$A$2:$A958,"<="&$E$2,Data_Ventas!$H$2:$H958,"Venta",Data_Ventas!$Q$2:$Q958,Dashboard!$B$34))/(SUMIFS(Data_Ventas!$N$2:$N958,Data_Ventas!$E$2:$E958,A10,Data_Ventas!$A$2:$A958,">="&$B$2,Data_Ventas!$A$2:$A958,"<="&$E$2,Data_Ventas!$H$2:$H958,"Venta",Data_Ventas!$Q$2:$Q958,Dashboard!$B$34)),"0%") -> 0% | X10: =IFERROR((SUMIFS(Data_Ventas!$O$2:$O958,Data_Ventas!$E$2:$E958,A10,Data_Ventas!$A$2:$A958,">="&$B$2,Data_Ventas!$A$2:$A958,"<="&$E$2,Data_Ventas!$H$2:$H958,"Venta"))/(SUMIFS(Data_Ventas!$M$2:$M958,Data_Ventas!$E$2:$E958,A10,Data_Ventas!$A$2:$A958,">="&$B$2,Data_Ventas!$A$2:$A958,"<="&$E$2,Data_Ventas!$H$2:$H958,"Venta")),"0%") -> 0% | Y10: =IFERROR(N10/(SUMIFS(Data_Ventas!$N$2:$N958,Data_Ventas!$E$2:$E958,A10,Data_Ventas!$A$2:$A958,">="&$B$2,Data_Ventas!$A$2:$A958,"<="&$E$2,Data_Ventas!$H$2:$H958,"Venta Perdida")),0%) -> 0 | Z10: =IFERROR(N10/(N10+(SUMIFS(Data_Ventas!$N$2:$N958,Data_Ventas!$E$2:$E958,A10,Data_Ventas!$A$2:$A958,">="&$B$2,Data_Ventas!$A$2:$A958,"<="&$E$2,Data_Ventas!$H$2:$H958,"Venta Perdida"))),"0%") -> 0% | AB10: =_xlfn.RANK.EQ(N10,$N$5:$N$14,0)+COUNTIF($N$5:N10,N10)-1 -> 8 | AC10: =IF(Q10>=0.18,"🟢",IF(Q10>=0.14,"🟡","🔴")) -> 🔴 | AD10: =((MIN(V10/Configuracion!$B$20,1)*30%)+(MIN(W10/Configuracion!$B$21,1)*20%)+(MAX(0,1-(X10/Configuracion!$B$22)*20%)*20%)+(IF(Y10=0,1,MIN(Configuracion!$B$23/Y10,1))*20%)+(MIN(Z10/Configuracion!$B$24,1)*10%))*100 -> 40 | AE10: =IF(AD10>=90,"🟢 Ventas de alta calidad",IF(AD10>=80,"🟡 Ventas calidad aceptable, revisar",IF(AD10>=70,"🟠 Venta calidad débil","🔴 Mala calidad comercial"))) -> 🔴 Mala calidad comercial | AF10: =IFERROR((N10/H10)*100,"") -> 0 | AG10: =(AF10*60%)+(40%*AD10) -> 16
A11: Jose Carrillo | B11: JeanPaul Campos | C11: Activo | E11: 3 | F11: =E11*Configuracion!$B$15 -> 120000 | G11: =ROUNDUP((DATEDIF($B$2,$E$2,"m")+(DAY($E$2)/DAY(EOMONTH($E$2,0))))*E11,0) -> 39 | H11: =G11*Configuracion!$B$15 -> 1560000 | I11: =COUNTIFS(Data_Ventas!$E$2:$E958,A11,Data_Ventas!$A$2:$A958,">="&$B$2,Data_Ventas!$A$2:$A958,"<="&$E$2) -> 0 | J11: =COUNTIFS(Data_Ventas!$E$2:$E958,A11,Data_Ventas!$A$2:$A958,">="&$B$2,Data_Ventas!$A$2:$A958,"<="&$E$2,Data_Ventas!$H$2:$H958,"Visitó proyecto") -> 0 | K11: =COUNTIFS(Data_Ventas!$E$2:$E958,A11,Data_Ventas!$A$2:$A958,">="&$B$2,Data_Ventas!$A$2:$A958,"<="&$E$2,Data_Ventas!$H$2:$H958,"Visitó proyecto") -> 0 | L11: =COUNTIFS(Data_Ventas!$E$2:$E958,A11,Data_Ventas!$A$2:$A958,">="&$B$2,Data_Ventas!$A$2:$A958,"<="&$E$2,Data_Ventas!$H$2:$H958,"Separado") -> 0 | M11: =COUNTIFS(Data_Ventas!$E$2:$E958,A11,Data_Ventas!$A$2:$A958,">="&$B$2,Data_Ventas!$A$2:$A958,"<="&$E$2,Data_Ventas!$H$2:$H958,"Venta") -> 0 | N11: =SUMIFS(Data_Ventas!$N$2:$N958,Data_Ventas!$E$2:$E958,A11,Data_Ventas!$A$2:$A958,">="&$B$2,Data_Ventas!$A$2:$A958,"<="&$E$2,Data_Ventas!$H$2:$H958,"Venta") -> 0 | O11: =N11/H11 -> 0 | P11: =IFERROR(M11/I11,0) -> 0 | Q11: =IFERROR(M11/K11,0) -> 0 | R11: =IFERROR(N11/I11,0) -> 0 | S11: =IFERROR(N11/M11,0) -> 0 | T11: =SUMIFS(Data_Ventas!$O$2:$O958,Data_Ventas!$E$2:$E958,A11,Data_Ventas!$A$2:$A958,">="&$B$2,Data_Ventas!$A$2:$A958,"<="&$E$2,Data_Ventas!$H$2:$H958,"Venta") -> 0 | U11: =SUMIFS(Data_Ventas!$R$2:$R958,Data_Ventas!$E$2:$E958,A11,Data_Ventas!$A$2:$A958,">="&$B$2,Data_Ventas!$A$2:$A958,"<="&$E$2,Data_Ventas!$H$2:$H958,"Venta") -> 0 | V11: =IFERROR(U11/N11,"0%") -> 0% | W11: =IFERROR((SUMIFS(Data_Ventas!$R$2:$R958,Data_Ventas!$E$2:$E958,A11,Data_Ventas!$A$2:$A958,">="&$B$2,Data_Ventas!$A$2:$A958,"<="&$E$2,Data_Ventas!$H$2:$H958,"Venta",Data_Ventas!$Q$2:$Q958,Dashboard!$B$34))/(SUMIFS(Data_Ventas!$N$2:$N958,Data_Ventas!$E$2:$E958,A11,Data_Ventas!$A$2:$A958,">="&$B$2,Data_Ventas!$A$2:$A958,"<="&$E$2,Data_Ventas!$H$2:$H958,"Venta",Data_Ventas!$Q$2:$Q958,Dashboard!$B$34)),"0%") -> 0% | X11: =IFERROR((SUMIFS(Data_Ventas!$O$2:$O958,Data_Ventas!$E$2:$E958,A11,Data_Ventas!$A$2:$A958,">="&$B$2,Data_Ventas!$A$2:$A958,"<="&$E$2,Data_Ventas!$H$2:$H958,"Venta"))/(SUMIFS(Data_Ventas!$M$2:$M958,Data_Ventas!$E$2:$E958,A11,Data_Ventas!$A$2:$A958,">="&$B$2,Data_Ventas!$A$2:$A958,"<="&$E$2,Data_Ventas!$H$2:$H958,"Venta")),"0%") -> 0% | Y11: =IFERROR(N11/(SUMIFS(Data_Ventas!$N$2:$N958,Data_Ventas!$E$2:$E958,A11,Data_Ventas!$A$2:$A958,">="&$B$2,Data_Ventas!$A$2:$A958,"<="&$E$2,Data_Ventas!$H$2:$H958,"Venta Perdida")),0%) -> 0 | Z11: =IFERROR(N11/(N11+(SUMIFS(Data_Ventas!$N$2:$N958,Data_Ventas!$E$2:$E958,A11,Data_Ventas!$A$2:$A958,">="&$B$2,Data_Ventas!$A$2:$A958,"<="&$E$2,Data_Ventas!$H$2:$H958,"Venta Perdida"))),"0%") -> 0% | AB11: =_xlfn.RANK.EQ(N11,$N$5:$N$14,0)+COUNTIF($N$5:N11,N11)-1 -> 9 | AC11: =IF(Q11>=0.18,"🟢",IF(Q11>=0.14,"🟡","🔴")) -> 🔴 | AD11: =((MIN(V11/Configuracion!$B$20,1)*30%)+(MIN(W11/Configuracion!$B$21,1)*20%)+(MAX(0,1-(X11/Configuracion!$B$22)*20%)*20%)+(IF(Y11=0,1,MIN(Configuracion!$B$23/Y11,1))*20%)+(MIN(Z11/Configuracion!$B$24,1)*10%))*100 -> 40 | AE11: =IF(AD11>=90,"🟢 Ventas de alta calidad",IF(AD11>=80,"🟡 Ventas calidad aceptable, revisar",IF(AD11>=70,"🟠 Venta calidad débil","🔴 Mala calidad comercial"))) -> 🔴 Mala calidad comercial | AF11: =IFERROR((N11/H11)*100,"") -> 0 | AG11: =(AF11*60%)+(40%*AD11) -> 16
A12: Herberth | B12: JeanPaul Campos | C12: Activo | E12: 3 | F12: =E12*Configuracion!$B$15 -> 120000 | G12: =ROUNDUP((DATEDIF($B$2,$E$2,"m")+(DAY($E$2)/DAY(EOMONTH($E$2,0))))*E12,0) -> 39 | H12: =G12*Configuracion!$B$15 -> 1560000 | I12: =COUNTIFS(Data_Ventas!$E$2:$E958,A12,Data_Ventas!$A$2:$A958,">="&$B$2,Data_Ventas!$A$2:$A958,"<="&$E$2) -> 0 | J12: =COUNTIFS(Data_Ventas!$E$2:$E958,A12,Data_Ventas!$A$2:$A958,">="&$B$2,Data_Ventas!$A$2:$A958,"<="&$E$2,Data_Ventas!$H$2:$H958,"Visitó proyecto") -> 0 | K12: =COUNTIFS(Data_Ventas!$E$2:$E958,A12,Data_Ventas!$A$2:$A958,">="&$B$2,Data_Ventas!$A$2:$A958,"<="&$E$2,Data_Ventas!$H$2:$H958,"Visitó proyecto") -> 0 | L12: =COUNTIFS(Data_Ventas!$E$2:$E958,A12,Data_Ventas!$A$2:$A958,">="&$B$2,Data_Ventas!$A$2:$A958,"<="&$E$2,Data_Ventas!$H$2:$H958,"Separado") -> 0 | M12: =COUNTIFS(Data_Ventas!$E$2:$E958,A12,Data_Ventas!$A$2:$A958,">="&$B$2,Data_Ventas!$A$2:$A958,"<="&$E$2,Data_Ventas!$H$2:$H958,"Venta") -> 0 | N12: =SUMIFS(Data_Ventas!$N$2:$N958,Data_Ventas!$E$2:$E958,A12,Data_Ventas!$A$2:$A958,">="&$B$2,Data_Ventas!$A$2:$A958,"<="&$E$2,Data_Ventas!$H$2:$H958,"Venta") -> 0 | O12: =N12/H12 -> 0 | P12: =IFERROR(M12/I12,0) -> 0 | Q12: =IFERROR(M12/K12,0) -> 0 | R12: =IFERROR(N12/I12,0) -> 0 | S12: =IFERROR(N12/M12,0) -> 0 | T12: =SUMIFS(Data_Ventas!$O$2:$O958,Data_Ventas!$E$2:$E958,A12,Data_Ventas!$A$2:$A958,">="&$B$2,Data_Ventas!$A$2:$A958,"<="&$E$2,Data_Ventas!$H$2:$H958,"Venta") -> 0 | U12: =SUMIFS(Data_Ventas!$R$2:$R958,Data_Ventas!$E$2:$E958,A12,Data_Ventas!$A$2:$A958,">="&$B$2,Data_Ventas!$A$2:$A958,"<="&$E$2,Data_Ventas!$H$2:$H958,"Venta") -> 0 | V12: =IFERROR(U12/N12,"0%") -> 0% | W12: =IFERROR((SUMIFS(Data_Ventas!$R$2:$R958,Data_Ventas!$E$2:$E958,A12,Data_Ventas!$A$2:$A958,">="&$B$2,Data_Ventas!$A$2:$A958,"<="&$E$2,Data_Ventas!$H$2:$H958,"Venta",Data_Ventas!$Q$2:$Q958,Dashboard!$B$34))/(SUMIFS(Data_Ventas!$N$2:$N958,Data_Ventas!$E$2:$E958,A12,Data_Ventas!$A$2:$A958,">="&$B$2,Data_Ventas!$A$2:$A958,"<="&$E$2,Data_Ventas!$H$2:$H958,"Venta",Data_Ventas!$Q$2:$Q958,Dashboard!$B$34)),"0%") -> 0% | X12: =IFERROR((SUMIFS(Data_Ventas!$O$2:$O958,Data_Ventas!$E$2:$E958,A12,Data_Ventas!$A$2:$A958,">="&$B$2,Data_Ventas!$A$2:$A958,"<="&$E$2,Data_Ventas!$H$2:$H958,"Venta"))/(SUMIFS(Data_Ventas!$M$2:$M958,Data_Ventas!$E$2:$E958,A12,Data_Ventas!$A$2:$A958,">="&$B$2,Data_Ventas!$A$2:$A958,"<="&$E$2,Data_Ventas!$H$2:$H958,"Venta")),"0%") -> 0% | Y12: =IFERROR(N12/(SUMIFS(Data_Ventas!$N$2:$N958,Data_Ventas!$E$2:$E958,A12,Data_Ventas!$A$2:$A958,">="&$B$2,Data_Ventas!$A$2:$A958,"<="&$E$2,Data_Ventas!$H$2:$H958,"Venta Perdida")),0%) -> 0 | Z12: =IFERROR(N12/(N12+(SUMIFS(Data_Ventas!$N$2:$N958,Data_Ventas!$E$2:$E958,A12,Data_Ventas!$A$2:$A958,">="&$B$2,Data_Ventas!$A$2:$A958,"<="&$E$2,Data_Ventas!$H$2:$H958,"Venta Perdida"))),"0%") -> 0% | AB12: =_xlfn.RANK.EQ(N12,$N$5:$N$14,0)+COUNTIF($N$5:N12,N12)-1 -> 10 | AC12: =IF(Q12>=0.18,"🟢",IF(Q12>=0.14,"🟡","🔴")) -> 🔴 | AD12: =((MIN(V12/Configuracion!$B$20,1)*30%)+(MIN(W12/Configuracion!$B$21,1)*20%)+(MAX(0,1-(X12/Configuracion!$B$22)*20%)*20%)+(IF(Y12=0,1,MIN(Configuracion!$B$23/Y12,1))*20%)+(MIN(Z12/Configuracion!$B$24,1)*10%))*100 -> 40 | AE12: =IF(AD12>=90,"🟢 Ventas de alta calidad",IF(AD12>=80,"🟡 Ventas calidad aceptable, revisar",IF(AD12>=70,"🟠 Venta calidad débil","🔴 Mala calidad comercial"))) -> 🔴 Mala calidad comercial | AF12: =IFERROR((N12/H12)*100,"") -> 0 | AG12: =(AF12*60%)+(40%*AD12) -> 16
A13: Juan Carlos Paredes | B13: JeanPaul Campos | C13: Activo | E13: 3 | F13: =E13*Configuracion!$B$15 -> 120000 | G13: =ROUNDUP((DATEDIF($B$2,$E$2,"m")+(DAY($E$2)/DAY(EOMONTH($E$2,0))))*E13,0) -> 39 | H13: =G13*Configuracion!$B$15 -> 1560000 | I13: =COUNTIFS(Data_Ventas!$E$2:$E958,A13,Data_Ventas!$A$2:$A958,">="&$B$2,Data_Ventas!$A$2:$A958,"<="&$E$2) -> 6 | J13: =COUNTIFS(Data_Ventas!$E$2:$E958,A13,Data_Ventas!$A$2:$A958,">="&$B$2,Data_Ventas!$A$2:$A958,"<="&$E$2,Data_Ventas!$H$2:$H958,"Visitó proyecto") -> 0 | K13: =COUNTIFS(Data_Ventas!$E$2:$E958,A13,Data_Ventas!$A$2:$A958,">="&$B$2,Data_Ventas!$A$2:$A958,"<="&$E$2,Data_Ventas!$H$2:$H958,"Visitó proyecto") -> 0 | L13: =COUNTIFS(Data_Ventas!$E$2:$E958,A13,Data_Ventas!$A$2:$A958,">="&$B$2,Data_Ventas!$A$2:$A958,"<="&$E$2,Data_Ventas!$H$2:$H958,"Separado") -> 0 | M13: =COUNTIFS(Data_Ventas!$E$2:$E958,A13,Data_Ventas!$A$2:$A958,">="&$B$2,Data_Ventas!$A$2:$A958,"<="&$E$2,Data_Ventas!$H$2:$H958,"Venta") -> 6 | N13: =SUMIFS(Data_Ventas!$N$2:$N958,Data_Ventas!$E$2:$E958,A13,Data_Ventas!$A$2:$A958,">="&$B$2,Data_Ventas!$A$2:$A958,"<="&$E$2,Data_Ventas!$H$2:$H958,"Venta") -> 367200 | O13: =N13/H13 -> 0.23538462 | P13: =IFERROR(M13/I13,0) -> 1 | Q13: =IFERROR(M13/K13,0) -> 0 | R13: =IFERROR(N13/I13,0) -> 61200 | S13: =IFERROR(N13/M13,0) -> 61200 | T13: =SUMIFS(Data_Ventas!$O$2:$O958,Data_Ventas!$E$2:$E958,A13,Data_Ventas!$A$2:$A958,">="&$B$2,Data_Ventas!$A$2:$A958,"<="&$E$2,Data_Ventas!$H$2:$H958,"Venta") -> 0 | U13: =SUMIFS(Data_Ventas!$R$2:$R958,Data_Ventas!$E$2:$E958,A13,Data_Ventas!$A$2:$A958,">="&$B$2,Data_Ventas!$A$2:$A958,"<="&$E$2,Data_Ventas!$H$2:$H958,"Venta") -> 40800 | V13: =IFERROR(U13/N13,"0%") -> 0.11111111 | W13: =IFERROR((SUMIFS(Data_Ventas!$R$2:$R958,Data_Ventas!$E$2:$E958,A13,Data_Ventas!$A$2:$A958,">="&$B$2,Data_Ventas!$A$2:$A958,"<="&$E$2,Data_Ventas!$H$2:$H958,"Venta",Data_Ventas!$Q$2:$Q958,Dashboard!$B$34))/(SUMIFS(Data_Ventas!$N$2:$N958,Data_Ventas!$E$2:$E958,A13,Data_Ventas!$A$2:$A958,">="&$B$2,Data_Ventas!$A$2:$A958,"<="&$E$2,Data_Ventas!$H$2:$H958,"Venta",Data_Ventas!$Q$2:$Q958,Dashboard!$B$34)),"0%") -> 0.11111111 | X13: =IFERROR((SUMIFS(Data_Ventas!$O$2:$O958,Data_Ventas!$E$2:$E958,A13,Data_Ventas!$A$2:$A958,">="&$B$2,Data_Ventas!$A$2:$A958,"<="&$E$2,Data_Ventas!$H$2:$H958,"Venta"))/(SUMIFS(Data_Ventas!$M$2:$M958,Data_Ventas!$E$2:$E958,A13,Data_Ventas!$A$2:$A958,">="&$B$2,Data_Ventas!$A$2:$A958,"<="&$E$2,Data_Ventas!$H$2:$H958,"Venta")),"0%") -> 0 | Y13: =IFERROR(N13/(SUMIFS(Data_Ventas!$N$2:$N958,Data_Ventas!$E$2:$E958,A13,Data_Ventas!$A$2:$A958,">="&$B$2,Data_Ventas!$A$2:$A958,"<="&$E$2,Data_Ventas!$H$2:$H958,"Venta Perdida")),0%) -> 0 | Z13: =IFERROR(N13/(N13+(SUMIFS(Data_Ventas!$N$2:$N958,Data_Ventas!$E$2:$E958,A13,Data_Ventas!$A$2:$A958,">="&$B$2,Data_Ventas!$A$2:$A958,"<="&$E$2,Data_Ventas!$H$2:$H958,"Venta Perdida"))),"0%") -> 1 | AB13: =_xlfn.RANK.EQ(N13,$N$5:$N$14,0)+COUNTIF($N$5:N13,N13)-1 -> 1 | AC13: =IF(Q13>=0.18,"🟢",IF(Q13>=0.14,"🟡","🔴")) -> 🔴 | AD13: =((MIN(V13/Configuracion!$B$20,1)*30%)+(MIN(W13/Configuracion!$B$21,1)*20%)+(MAX(0,1-(X13/Configuracion!$B$22)*20%)*20%)+(IF(Y13=0,1,MIN(Configuracion!$B$23/Y13,1))*20%)+(MIN(Z13/Configuracion!$B$24,1)*10%))*100 -> 70.634921 | AE13: =IF(AD13>=90,"🟢 Ventas de alta calidad",IF(AD13>=80,"🟡 Ventas calidad aceptable, revisar",IF(AD13>=70,"🟠 Venta calidad débil","🔴 Mala calidad comercial"))) -> 🟠 Venta calidad débil | AF13: =IFERROR((N13/H13)*100,"") -> 23.538462 | AG13: =(AF13*60%)+(40%*AD13) -> 42.377045
A14: Karina | B14: Vicente Quispe | C14: No activo | E14: 3 | F14: =E14*Configuracion!$B$15 -> 120000 | G14: =ROUNDUP((DATEDIF($B$2,$E$2,"m")+(DAY($E$2)/DAY(EOMONTH($E$2,0))))*E14,0) -> 39 | H14: =G14*Configuracion!$B$15 -> 1560000 | I14: =COUNTIFS(Data_Ventas!$E$2:$E958,A14,Data_Ventas!$A$2:$A958,">="&$B$2,Data_Ventas!$A$2:$A958,"<="&$E$2) -> 1 | J14: =COUNTIFS(Data_Ventas!$E$2:$E958,A14,Data_Ventas!$A$2:$A958,">="&$B$2,Data_Ventas!$A$2:$A958,"<="&$E$2,Data_Ventas!$H$2:$H958,"Visitó proyecto") -> 0 | K14: =COUNTIFS(Data_Ventas!$E$2:$E958,A14,Data_Ventas!$A$2:$A958,">="&$B$2,Data_Ventas!$A$2:$A958,"<="&$E$2,Data_Ventas!$H$2:$H958,"Visitó proyecto") -> 0 | L14: =COUNTIFS(Data_Ventas!$E$2:$E958,A14,Data_Ventas!$A$2:$A958,">="&$B$2,Data_Ventas!$A$2:$A958,"<="&$E$2,Data_Ventas!$H$2:$H958,"Separado") -> 0 | M14: =COUNTIFS(Data_Ventas!$E$2:$E958,A14,Data_Ventas!$A$2:$A958,">="&$B$2,Data_Ventas!$A$2:$A958,"<="&$E$2,Data_Ventas!$H$2:$H958,"Venta") -> 1 | N14: =SUMIFS(Data_Ventas!$N$2:$N958,Data_Ventas!$E$2:$E958,A14,Data_Ventas!$A$2:$A958,">="&$B$2,Data_Ventas!$A$2:$A958,"<="&$E$2,Data_Ventas!$H$2:$H958,"Venta") -> 42000 | O14: =N14/H14 -> 0.026923077 | P14: =IFERROR(M14/I14,0) -> 1 | Q14: =IFERROR(M14/K14,0) -> 0 | R14: =IFERROR(N14/I14,0) -> 42000 | S14: =IFERROR(N14/M14,0) -> 42000 | T14: =SUMIFS(Data_Ventas!$O$2:$O958,Data_Ventas!$E$2:$E958,A14,Data_Ventas!$A$2:$A958,">="&$B$2,Data_Ventas!$A$2:$A958,"<="&$E$2,Data_Ventas!$H$2:$H958,"Venta") -> 0 | U14: =SUMIFS(Data_Ventas!$R$2:$R958,Data_Ventas!$E$2:$E958,A14,Data_Ventas!$A$2:$A958,">="&$B$2,Data_Ventas!$A$2:$A958,"<="&$E$2,Data_Ventas!$H$2:$H958,"Venta") -> 30000 | V14: =IFERROR(U14/N14,"0%") -> 0.71428571 | W14: =IFERROR((SUMIFS(Data_Ventas!$R$2:$R958,Data_Ventas!$E$2:$E958,A14,Data_Ventas!$A$2:$A958,">="&$B$2,Data_Ventas!$A$2:$A958,"<="&$E$2,Data_Ventas!$H$2:$H958,"Venta",Data_Ventas!$Q$2:$Q958,Dashboard!$B$34))/(SUMIFS(Data_Ventas!$N$2:$N958,Data_Ventas!$E$2:$E958,A14,Data_Ventas!$A$2:$A958,">="&$B$2,Data_Ventas!$A$2:$A958,"<="&$E$2,Data_Ventas!$H$2:$H958,"Venta",Data_Ventas!$Q$2:$Q958,Dashboard!$B$34)),"0%") -> 0.71428571 | X14: =IFERROR((SUMIFS(Data_Ventas!$O$2:$O958,Data_Ventas!$E$2:$E958,A14,Data_Ventas!$A$2:$A958,">="&$B$2,Data_Ventas!$A$2:$A958,"<="&$E$2,Data_Ventas!$H$2:$H958,"Venta"))/(SUMIFS(Data_Ventas!$M$2:$M958,Data_Ventas!$E$2:$E958,A14,Data_Ventas!$A$2:$A958,">="&$B$2,Data_Ventas!$A$2:$A958,"<="&$E$2,Data_Ventas!$H$2:$H958,"Venta")),"0%") -> 0 | Y14: =IFERROR(N14/(SUMIFS(Data_Ventas!$N$2:$N958,Data_Ventas!$E$2:$E958,A14,Data_Ventas!$A$2:$A958,">="&$B$2,Data_Ventas!$A$2:$A958,"<="&$E$2,Data_Ventas!$H$2:$H958,"Venta Perdida")),0%) -> 0 | Z14: =IFERROR(N14/(N14+(SUMIFS(Data_Ventas!$N$2:$N958,Data_Ventas!$E$2:$E958,A14,Data_Ventas!$A$2:$A958,">="&$B$2,Data_Ventas!$A$2:$A958,"<="&$E$2,Data_Ventas!$H$2:$H958,"Venta Perdida"))),"0%") -> 1 | AB14: =_xlfn.RANK.EQ(N14,$N$5:$N$14,0)+COUNTIF($N$5:N14,N14)-1 -> 4 | AC14: =IF(Q14>=0.18,"🟢",IF(Q14>=0.14,"🟡","🔴")) -> 🔴 | AD14: =((MIN(V14/Configuracion!$B$20,1)*30%)+(MIN(W14/Configuracion!$B$21,1)*20%)+(MAX(0,1-(X14/Configuracion!$B$22)*20%)*20%)+(IF(Y14=0,1,MIN(Configuracion!$B$23/Y14,1))*20%)+(MIN(Z14/Configuracion!$B$24,1)*10%))*100 -> 100 | AE14: =IF(AD14>=90,"🟢 Ventas de alta calidad",IF(AD14>=80,"🟡 Ventas calidad aceptable, revisar",IF(AD14>=70,"🟠 Venta calidad débil","🔴 Mala calidad comercial"))) -> 🟢 Ventas de alta calidad | AF14: =IFERROR((N14/H14)*100,"") -> 2.6923077 | AG14: =(AF14*60%)+(40%*AD14) -> 41.615385

Sheet Costos
A2: GASTOS COMERCIALES — PRESUPUESTO, REAL Y EFICIENCIA
A4: Gasto_ID | B4: Fecha | C4: Área | D4: Categoría | E4: Detalle / Evento | F4: Presupuesto | G4: Real | H4: Variación S/ | I4: Variación % | J4: Responsable
A5: G-001 | B5: 46266 | C5: CSO | D5: Sueldos | E5: Equipo comercial | F5: 22000 | G5: 22000 | H5: =G5-F5 -> 0 | I5: =IFERROR(H5/F5,0) -> 0 | J5: CSO
A6: G-002 | B6: 46295 | C6: CSO | D6: Comisiones | E6: Comisiones de ventas | F6: 26000 | G6: 24500 | H6: =G6-F6 -> -1500 | I6: =IFERROR(H6/F6,0) -> -0.057692308 | J6: CSO
A7: G-003 | B7: 46270 | C7: CSO | D7: Movilidad | E7: Visitas a proyecto | F7: 4500 | G7: 3900 | H7: =G7-F7 -> -600 | I7: =IFERROR(H7/F7,0) -> -0.13333333 | J7: CSO
A8: G-004 | B8: 46270 | C8: CSO | D8: Alimentación | E8: Eventos y visitas | F8: 3000 | G8: 2750 | H8: =G8-F8 -> -250 | I8: =IFERROR(H8/F8,0) -> -0.083333333 | J8: CSO
A9: G-005 | B9: 46266 | C9: CSO | D9: CRM | E9: Licencias comerciales | F9: 1800 | G9: 1800 | H9: =G9-F9 -> 0 | I9: =IFERROR(H9/F9,0) -> 0 | J9: CTO/CSO
A10: G-006 | B10: 46266 | C10: CSO | D10: Capacitación | E10: Clínicas de cierre | F10: 2500 | G10: 1800 | H10: =G10-F10 -> -700 | I10: =IFERROR(H10/F10,0) -> -0.28 | J10: CSO/CHRO
A11: G-007 | B11: 46271 | C11: CSO | D11: Eventos | E11: EV-001 | F11: 6000 | G11: 5600 | H11: =G11-F11 -> -400 | I11: =IFERROR(H11/F11,0) -> -0.066666667 | J11: CSO
A12: G-008 | B12: 46278 | C12: CSO | D12: Eventos | E12: EV-002 | F12: 8000 | G12: 7600 | H12: =G12-F12 -> -400 | I12: =IFERROR(H12/F12,0) -> -0.05 | J12: CSO
A13: G-009 | B13: 46285 | C13: CSO | D13: Eventos | E13: EV-003 | F13: 10000 | G13: 0 | H13: =G13-F13 -> -10000 | I13: =IFERROR(H13/F13,0) -> -1 | J13: CSO
A14: G-010 | B14: 46292 | C14: CSO | D14: Eventos | E14: EV-004 | F14: 12000 | G14: 0 | H14: =G14-F14 -> -12000 | I14: =IFERROR(H14/F14,0) -> -1 | J14: CSO
A15: G-011 | B15: 46266 | C15: CMO | D15: Publicidad | E15: Meta Ads | F15: 28000 | G15: 21000 | H15: =G15-F15 -> -7000 | I15: =IFERROR(H15/F15,0) -> -0.25 | J15: CMO
A16: G-012 | B16: 46266 | C16: CMO | D16: Publicidad | E16: TikTok Ads | F16: 9000 | G16: 7000 | H16: =G16-F16 -> -2000 | I16: =IFERROR(H16/F16,0) -> -0.22222222 | J16: CMO
A17: G-013 | B17: 46266 | C17: CMO | D17: Producción | E17: Creativos | F17: 6000 | G17: 5200 | H17: =G17-F17 -> -800 | I17: =IFERROR(H17/F17,0) -> -0.13333333 | J17: CMO

Sheet Data_Ventas
A1: Fecha_Lead | B1: Lead_ID | C1: Cliente | D1: Telefono | E1: Vendedor | F1: Fuente | G1: Proyecto | H1: Estado_CRM | I1: Monto_Separacion | J1: Observaciones | K1: Manzana | L1: Lote | M1: Precio Lista | N1: Precio venta | O1: Dscto S/. | P1: Dscto % | Q1: Tipo de Venta | R1: Inicial | S1: Saldo | T1: Fecha firma | U1: Dias cierre
A2: 45994 | C2: Agustina | E2: Juan Carlos Paredes | F2: Referido | G2: Paraiso de Santa Maria | H2: Venta | K2: H | L2: 8 | M2: =18000*3.4 -> 61200 | N2: =18000*3.4 -> 61200 | O2: =M2-N2 -> 0 | P2: =IFERROR(O2/M2,0) -> 0 | Q2: Financiado | R2: =2000*3.4 -> 6800 | S2: =N2-R2 -> 54400 | T2: 45994 | U2: =IF(T2-A2>0,T2-A2,"0") -> 0
A3: 45994 | C3: Agustina | E3: Juan Carlos Paredes | F3: Referido | G3: Paraiso de Santa Maria | H3: Venta | K3: H | L3: 9 | M3: =18000*3.4 -> 61200 | N3: =18000*3.4 -> 61200 | O3: =M3-N3 -> 0 | P3: =IFERROR(O3/M3,0) -> 0 | Q3: Financiado | R3: =2000*3.4 -> 6800 | S3: =N3-R3 -> 54400 | T3: 45994 | U3: =IF(T3-A3>0,T3-A3,"0") -> 0
A4: 46018 | C4: Anita Chang | E4: JeanPaul Campos | F4: Referido | G4: Paraiso de Santa Maria | H4: Venta | K4: P | L4: 2 | M4: 64864.5 | N4: 64864.5 | O4: =M4-N4 -> 0 | P4: =IFERROR(O4/M4,0) -> 0 | Q4: Financiado | R4: 1000 | S4: =N4-R4 -> 63864.5 | T4: 46018 | U4: =IF(T4-A4>0,T4-A4,"0") -> 0
A5: 46038 | C5: Agustina | E5: Juan Carlos Paredes | F5: Referido | G5: Paraiso de Santa Maria | H5: Venta | K5: L | L5: 10 | M5: =18000*3.4 -> 61200 | N5: =18000*3.4 -> 61200 | O5: =M5-N5 -> 0 | P5: =IFERROR(O5/M5,0) -> 0 | Q5: Financiado | R5: =2000*3.4 -> 6800 | S5: =N5-R5 -> 54400 | T5: 46038 | U5: =IF(T5-A5>0,T5-A5,"0") -> 0
A6: 46038 | C6: Agustina | E6: Juan Carlos Paredes | F6: Referido | G6: Paraiso de Santa Maria | H6: Venta | K6: L | L6: 11 | M6: =18000*3.4 -> 61200 | N6: =18000*3.4 -> 61200 | O6: =M6-N6 -> 0 | P6: =IFERROR(O6/M6,0) -> 0 | Q6: Financiado | R6: =2000*3.4 -> 6800 | S6: =N6-R6 -> 54400 | T6: 46038 | U6: =IF(T6-A6>0,T6-A6,"0") -> 0
A7: 46027 | C7: Sebastiana | E7: Juan Carlos Paredes | F7: Referido | G7: Paraiso de Santa Maria | H7: Venta | K7: H | L7: 7 | M7: =18000*3.4 -> 61200 | N7: =18000*3.4 -> 61200 | O7: =M7-N7 -> 0 | P7: =IFERROR(O7/M7,0) -> 0 | Q7: Financiado | R7: =2000*3.4 -> 6800 | S7: =N7-R7 -> 54400 | T7: 46027 | U7: =IF(T7-A7>0,T7-A7,"0") -> 0
A8: 46027 | C8: Sebastiana | E8: Juan Carlos Paredes | F8: Referido | G8: Paraiso de Santa Maria | H8: Venta | K8: H | L8: 6 | M8: =18000*3.4 -> 61200 | N8: =18000*3.4 -> 61200 | O8: =M8-N8 -> 0 | P8: =IFERROR(O8/M8,0) -> 0 | Q8: Financiado | R8: =2000*3.4 -> 6800 | S8: =N8-R8 -> 54400 | T8: 46027 | U8: =IF(T8-A8>0,T8-A8,"0") -> 0
A9: 46063 | C9: Celidonio | E9: JeanPaul Campos | F9: Referido | G9: Paraiso de Santa Maria | H9: Venta | K9: P | L9: 5 | M9: =15400*3.4 -> 52360 | N9: =15400*3.4 -> 52360 | O9: =M9-N9 -> 0 | P9: =IFERROR(O9/M9,0) -> 0 | Q9: Contado | R9: =15400*3.4 -> 52360 | S9: =N9-R9 -> 0 | T9: 46063 | U9: =IF(T9-A9>0,T9-A9,"0") -> 0
A10: 46095 | C10: Fabian de la Cruz | E10: JeanPaul Campos | F10: Publicidad pagada | G10: Paraiso de Santa Maria | H10: Venta | K10: M | L10: 15 | M10: 51000 | N10: 51000 | O10: =M10-N10 -> 0 | P10: =IFERROR(O10/M10,0) -> 0 | Q10: Contado | R10: 51000 | S10: =N10-R10 -> 0 | T10: 46095 | U10: =IF(T10-A10>0,T10-A10,"0") -> 0
A11: 46208 | C11: Dionicia Chate | E11: Karina | F11: Referido | G11: Paraiso de Santa Maria | H11: Venta | K11: L | L11: 7 | M11: 42000 | N11: 42000 | O11: =M11-N11 -> 0 | P11: =IFERROR(O11/M11,0) -> 0 | Q11: Financiado | R11: 30000 | S11: =N11-R11 -> 12000 | T11: 46211 | U11: =IF(T11-A11>0,T11-A11,"0") -> 3
A12: 46254 | C12: Abraham | E12: Alfredo Caceda | F12: Referido | G12: Paraiso de Santa Maria | H12: Venta | K12: L | L12: 12 | M12: 55000 | N12: 55000 | O12: =M12-N12 -> 0 | P12: =IFERROR(O12/M12,0) -> 0 | Q12: Financiado | R12: 1250 | S12: =N12-R12 -> 53750 | T12: 46255 | U12: =IF(T12-A12>0,T12-A12,"0") -> 1
A13: 46271 | E13: Vicente Quispe | F13: Referido | G13: Paraiso de Santa Maria | H13: Venta | I13: 500 | K13: M | L13: 10 | M13: 40000 | N13: 40000 | O13: =M13-N13 -> 0 | P13: =IFERROR(O13/M13,0) -> 0 | Q13: Financiado | R13: 5000 | S13: =N13-R13 -> 35000 | T13: 46276 | U13: =IF(T13-A13>0,T13-A13,"0") -> 5
A14: 46271 | E14: Vicente Quispe | F14: Referido | G14: Paraiso de Santa Maria | H14: Venta Perdida | I14: 500 | J14: El cliente no puede comprar por salud | K14: M | L14: 11 | M14: 40000 | N14: 40000 | O14: =M14-N14 -> 0 | P14: =IFERROR(O14/M14,0) -> 0 | Q14: Financiado | R14: 5000 | S14: =N14-R14 -> 35000 | U14: =IF(T14-A14>0,T14-A14,"0") -> 0
A15: 46264 | C15: Juan | E15: Alfredo Caceda | F15: Referido | G15: Paraiso de Santa Maria | H15: Venta | I15: 300 | K15: L | L15: 8 | M15: 35000 | N15: 35000 | O15: =M15-N15 -> 0 | P15: =IFERROR(O15/M15,0) -> 0 | Q15: Financiado | R15: 3500 | S15: =N15-R15 -> 31500 | T15: 46288 | U15: =IF(T15-A15>0,T15-A15,"0") -> 24
A16: 46264 | C16: Juan | E16: Alfredo Caceda | F16: Referido | G16: Paraiso de Santa Maria | H16: Venta | I16: 300 | K16: L | L16: 9 | M16: 35000 | N16: 35000 | O16: =M16-N16 -> 0 | P16: =IFERROR(O16/M16,0) -> 0 | Q16: Financiado | R16: 3500 | S16: =N16-R16 -> 31500 | T16: 46288 | U16: =IF(T16-A16>0,T16-A16,"0") -> 24
O17: =M17-N17 -> 0 | P17: =IFERROR(O17/M17,0) -> 0 | S17: =N17-R17 -> 0 | U17: =IF(T17-A17>0,T17-A17,"0") -> 0
O18: =M18-N18 -> 0 | P18: =IFERROR(O18/M18,0) -> 0 | S18: =N18-R18 -> 0 | U18: =IF(T18-A18>0,T18-A18,"0") -> 0
O19: =M19-N19 -> 0 | P19: =IFERROR(O19/M19,0) -> 0 | S19: =N19-R19 -> 0 | U19: =IF(T19-A19>0,T19-A19,"0") -> 0
O20: =M20-N20 -> 0 | P20: =IFERROR(O20/M20,0) -> 0 | S20: =N20-R20 -> 0 | U20: =IF(T20-A20>0,T20-A20,"0") -> 0
O21: =M21-N21 -> 0 | P21: =IFERROR(O21/M21,0) -> 0 | S21: =N21-R21 -> 0 | U21: =IF(T21-A21>0,T21-A21,"0") -> 0
O22: =M22-N22 -> 0 | P22: =IFERROR(O22/M22,0) -> 0 | S22: =N22-R22 -> 0 | U22: =IF(T22-A22>0,T22-A22,"0") -> 0
O23: =M23-N23 -> 0 | P23: =IFERROR(O23/M23,0) -> 0 | S23: =N23-R23 -> 0 | U23: =IF(T23-A23>0,T23-A23,"0") -> 0
O24: =M24-N24 -> 0 | P24: =IFERROR(O24/M24,0) -> 0 | S24: =N24-R24 -> 0 | U24: =IF(T24-A24>0,T24-A24,"0") -> 0
O25: =M25-N25 -> 0 | P25: =IFERROR(O25/M25,0) -> 0 | S25: =N25-R25 -> 0 | U25: =IF(T25-A25>0,T25-A25,"0") -> 0
O26: =M26-N26 -> 0 | P26: =IFERROR(O26/M26,0) -> 0 | S26: =N26-R26 -> 0 | U26: =IF(T26-A26>0,T26-A26,"0") -> 0
O27: =M27-N27 -> 0 | P27: =IFERROR(O27/M27,0) -> 0 | S27: =N27-R27 -> 0 | U27: =IF(T27-A27>0,T27-A27,"0") -> 0
O28: =M28-N28 -> 0 | P28: =IFERROR(O28/M28,0) -> 0 | S28: =N28-R28 -> 0 | U28: =IF(T28-A28>0,T28-A28,"0") -> 0
... O1013: =M1013-N1013 -> 0 | P1013: =IFERROR(O1013/M1013,0) -> 0 | S1013: =N1013-R1013 -> 0 | U1013: =IF(T1013-A1013>0,T1013-A1013,"0") -> 0

Sheet Data_Cotiz
A1: Fecha_Lead | B1: Lead_ID | C1: Cliente | D1: Telefono | E1: Vendedor | F1: Fuente | G1: Proyecto | H1: Estado_CRM | I1: Monto_Separacion | J1: Observaciones | K1: Manzana | L1: Lote | M1: Precio Lista | N1: Precio venta | O1: Dscto S/. | P1: Dscto % | Q1: Tipo de Venta | R1: Inicial | S1: Saldo | T1: Fecha firma | U1: Dias cierre
C2: Jorge | E2: Jose Carrillo | F2: Referido | G2: Paraiso de Santa Maria | H2: Listo para Comprar | O2: =M2-N2 -> 0 | P2: =IFERROR(O2/M2,0) -> 0 | S2: =N2-R2 -> 0 | U2: =IF(T2-A2>0,T2-A2,"0") -> 0
H3: Separado | O3: =M3-N3 -> 0 | P3: =IFERROR(O3/M3,0) -> 0 | S3: =N3-R3 -> 0 | U3: =IF(T3-A3>0,T3-A3,"0") -> 0
O4: =M4-N4 -> 0 | P4: =IFERROR(O4/M4,0) -> 0 | S4: =N4-R4 -> 0 | U4: =IF(T4-A4>0,T4-A4,"0") -> 0
O5: =M5-N5 -> 0 | P5: =IFERROR(O5/M5,0) -> 0 | S5: =N5-R5 -> 0 | U5: =IF(T5-A5>0,T5-A5,"0") -> 0
O6: =M6-N6 -> 0 | P6: =IFERROR(O6/M6,0) -> 0 | S6: =N6-R6 -> 0 | U6: =IF(T6-A6>0,T6-A6,"0") -> 0
O7: =M7-N7 -> 0 | P7: =IFERROR(O7/M7,0) -> 0 | S7: =N7-R7 -> 0 | U7: =IF(T7-A7>0,T7-A7,"0") -> 0
O8: =M8-N8 -> 0 | P8: =IFERROR(O8/M8,0) -> 0 | S8: =N8-R8 -> 0 | U8: =IF(T8-A8>0,T8-A8,"0") -> 0
O9: =M9-N9 -> 0 | P9: =IFERROR(O9/M9,0) -> 0 | S9: =N9-R9 -> 0 | U9: =IF(T9-A9>0,T9-A9,"0") -> 0
O10: =M10-N10 -> 0 | P10: =IFERROR(O10/M10,0) -> 0 | S10: =N10-R10 -> 0 | U10: =IF(T10-A10>0,T10-A10,"0") -> 0
O11: =M11-N11 -> 0 | P11: =IFERROR(O11/M11,0) -> 0 | S11: =N11-R11 -> 0 | U11: =IF(T11-A11>0,T11-A11,"0") -> 0
O12: =M12-N12 -> 0 | P12: =IFERROR(O12/M12,0) -> 0 | S12: =N12-R12 -> 0 | U12: =IF(T12-A12>0,T12-A12,"0") -> 0
O13: =M13-N13 -> 0 | P13: =IFERROR(O13/M13,0) -> 0 | S13: =N13-R13 -> 0 | U13: =IF(T13-A13>0,T13-A13,"0") -> 0
O14: =M14-N14 -> 0 | P14: =IFERROR(O14/M14,0) -> 0 | S14: =N14-R14 -> 0 | U14: =IF(T14-A14>0,T14-A14,"0") -> 0
O15: =M15-N15 -> 0 | P15: =IFERROR(O15/M15,0) -> 0 | S15: =N15-R15 -> 0 | U15: =IF(T15-A15>0,T15-A15,"0") -> 0
... O1013: =M1013-N1013 -> 0 | P1013: =IFERROR(O1013/M1013,0) -> 0 | S1013: =N1013-R1013 -> 0 | U1013: =IF(T1013-A1013>0,T1013-A1013,"0") -> 0

Sheet Data_Leads
A1: Fecha_Lead | B1: Lead_ID | C1: Cliente | D1: Telefono | E1: Vendedor | F1: Estado_CRM | G1: Lote Cotizado | H1: Monto_Cotizado | I1: Observaciones | J1: Fuente | K1: Proyecto | L1: Campaña
A2: 46276 | B2: 27508172 | C2: Edwin Peñaranda | D2: +51989722861 | E2: Alfredo Caceda | F2: REALIZAR INVITACION | H2: 0 | J2: Publicidad pagada | K2: Paraiso de Santa Maria
A3: 46275 | B3: 27504990 | C3: Miguel | D3: +51913827092 | E3: Jhovana Valdez | F3: NO CONTESTA - por confirmar | H3: 0 | J3: Publicidad pagada | K3: Paraiso de Santa Maria
A4: 46275 | B4: 27503286 | C4: Cuadra | D4: +51960639204 | E4: Jhovana Valdez | F4: NO CONTESTA - por confirmar | H4: 0 | J4: Publicidad pagada | K4: Paraiso de Santa Maria
A5: 46275 | B5: 27500988 | C5: Ed | D5: +51935401262 | E5: Alfredo Caceda | F5: seguimiento | H5: 0 | J5: Publicidad pagada | K5: Paraiso de Santa Maria
A6: 46274 | B6: 27495078 | C6: Abel | D6: +51944198815 | E6: JOSUE VICENTE | F6: NO CONTESTA - por confirmar | H6: 0 | J6: Publicidad pagada | K6: Paraiso de Santa Maria
A7: 46274 | B7: 27491474 | C7: Daniel | D7: +51975951607 | E7: Jhovana Valdez | F7: NO CONTESTA - por confirmar | H7: 0 | J7: Publicidad pagada | K7: Paraiso de Santa Maria
A8: 46274 | B8: 27490982 | C8: elgatolopezventura | D8: +51984277457 | E8: Jhovana Valdez | F8: NO CONTESTA - por confirmar | H8: 0 | J8: Publicidad pagada | K8: Paraiso de Santa Maria
A9: 46273 | B9: 27490278 | C9: Rafahel | D9: +51997336310 | E9: Jhovana Valdez | F9: NO CONTESTA - por confirmar | H9: 0 | J9: Publicidad pagada | K9: Paraiso de Santa Maria
A10: 46273 | B10: 27489846 | C10: Escorpion | D10: +51991197253 | E10: Alfredo Caceda | F10: seguimiento | H10: 0 | J10: Publicidad pagada | K10: Paraiso de Santa Maria
A11: 46273 | B11: 27489492 | C11: Alicia Mary Álvarez | D11: +51991267597 | E11: Alfredo Caceda | F11: seguimiento | H11: 0 | J11: Publicidad pagada | K11: Paraiso de Santa Maria
A12: 46273 | B12: 27489120 | C12: Hily Solis V | D12: +51992771534 | E12: Jhovana Valdez | F12: NO CONTESTA - por confirmar | H12: 0 | J12: Publicidad pagada | K12: Paraiso de Santa Maria
A13: 46273 | B13: 27488582 | C13: Roque Yeny | D13: +51990407924 | E13: Alfredo Caceda | F13: seguimiento | H13: 0 | J13: Publicidad pagada | K13: Paraiso de Santa Maria
... A24: 46269 | B24: 27459970 | C24: Yeni | D24: +51975711907 | E24: Jhovana Valdez | F24: INTERESADo | H24: 0 | J24: Publicidad pagada | K24: Paraiso de Santa Maria
A25: 46269 | B25: 27459388 | C25: 51997750239 | D25: +51997750239 | E25: Alfredo Caceda | F25: seguimiento | H25: 0 | J25: Publicidad pagada | K25: Paraiso de Santa Maria
A26: 46269 | B26: 27457172 | C26: Pedro Blades | D26: +51994676008 | E26: Alfredo Caceda | F26: INTERESADo | H26: 0 | J26: Publicidad pagada | K26: Paraiso de Santa Maria
A27: 46269 | B27: 27457096 | C27: A | D27: +51949368948 | E27: Jhovana Valdez | F27: NO CONTESTA - por confirmar | H27: 0 | J27: Publicidad pagada | K27: Paraiso de Santa Maria
A28: 46269 | B28: 27456248 | C28: floresvargasgodofre | D28: +51954593158 | E28: Alfredo Caceda | F28: INTERESADo | H28: 0 | J28: Publicidad pagada | K28: Paraiso de Santa Maria
A29: 46269 | B29: 27456224 | C29: Jo | D29: +51924402574 | E29: Jhovana Valdez | F29: respondieron LLAMADA/ WHATSAPP | H29: 0 | J29: Publicidad pagada | K29: Paraiso de Santa Maria
A30: 46268 | B30: 27454762 | C30: miguelasaro22@gmail.Com | D30: +51972775733 | E30: Alfredo Caceda | F30: INTERESADo | H30: 0 | J30: Publicidad pagada | K30: Paraiso de Santa Maria
A31: 46268 | B31: 27454460 | C31: 160269franciscolopez | D31: +51922290873 | E31: Alfredo Caceda | F31: AGENDO VISITA al proyecto | H31: 0 | J31: Publicidad pagada | K31: Paraiso de Santa Maria
A32: 46268 | B32: 27454414 | C32: .... | D32: +51936145516 | E32: Jhovana Valdez | F32: NO CONTESTA - por confirmar | H32: 0 | J32: Publicidad pagada | K32: Paraiso de Santa Maria
A33: 46268 | B33: 27454236 | C33: Rodolfo Pacora Vera | D33: +51983883608 | E33: Alfredo Caceda | F33: seguimiento | H33: 0 | J33: Publicidad pagada | K33: Paraiso de Santa Maria
A34: 46268 | B34: 27452144 | C34: Ysabel | D34: +51976793315 | E34: Jhovana Valdez | F34: NO CONTESTA - por confirmar | H34: 0 | J34: Publicidad pagada | K34: Paraiso de Santa Maria
A35: 46268 | B35: 27452108 | C35: Nazaria | D35: +51921334385 | E35: Alfredo Caceda | F35: respondieron LLAMADA/ WHATSAPP | H35: 0 | J35: Publicidad pagada | K35: Paraiso de Santa Maria
A36: 46268 | B36: 27451782 | C36: Flor Zapata | D36: +51995501108 | E36: Alfredo Caceda | F36: seguimiento | H36: 0 | J36: Publicidad pagada | K36: Paraiso de Santa Maria
A37: 46268 | B37: 27451758 | C37: Flor | D37: +51945610605 | E37: Jhovana Valdez | F37: NO CONTESTA - por confirmar | H37: 0 | J37: Publicidad pagada | K37: Paraiso de Santa Maria
... A40: 46268 | B40: 27448178 | C40: Esmm | D40: +51929421014 | E40: JOSUE VICENTE | F40: NO CONTESTA - por confirmar | H40: 0 | J40: Publicidad pagada | K40: Paraiso de Santa Maria
A41: 46268 | B41: 27447988 | C41: yo.se.q.t.gusto | E41: JOSUE VICENTE | F41: NO CONTESTA - por confirmar | H41: 0 | J41: Publicidad pagada | K41: Paraiso de Santa Maria
A42: 46267 | B42: 27446648 | C42: TRECEX | D42: +51998240775 | E42: Jhovana Valdez | F42: NO CONTESTA - por confirmar | H42: 0 | J42: Publicidad pagada | K42: Paraiso de Santa Maria
A43: 46267 | B43: 27446078 | C43: JairS_Villanueva | E43: JOSUE VICENTE | F43: NO CONTESTA - por confirmar | H43: 0 | J43: Publicidad pagada | K43: Paraiso de Santa Maria
A44: 46267 | B44: 27445964 | C44: Victor Orellana | D44: +51966684285 | E44: Jhovana Valdez | F44: respondieron LLAMADA/ WHATSAPP | H44: 0 | J44: Publicidad pagada | K44: Paraiso de Santa Maria
A45: 46267 | B45: 27445826 | C45: Jota | D45: +51994888010 | E45: Alfredo Caceda | F45: INTERESADo | H45: 0 | J45: Publicidad pagada | K45: Paraiso de Santa Maria
A46: 46267 | B46: 27445050 | C46: Renzo | D46: +51953309338 | E46: Alfredo Caceda | F46: seguimiento | H46: 0 | J46: Publicidad pagada | K46: Paraiso de Santa Maria
A47: 46267 | B47: 27444932 | C47: Manuel Medina | D47: +51955802523 | E47: Jhovana Valdez | F47: NO CONTESTA - por confirmar | H47: 0 | J47: Publicidad pagada | K47: Paraiso de Santa Maria
A48: 46267 | B48: 27444232 | C48: jorgechavezleano | D48: +51900888094 | E48: Alfredo Caceda | F48: AGENDO VISITA al proyecto | H48: 0 | J48: Publicidad pagada | K48: Paraiso de Santa Maria
A49: 46267 | B49: 27442990 | C49: alarconmurgamanuel | D49: +51915937281 | E49: Jhovana Valdez | F49: NO CONTESTA - por confirmar | H49: 0 | J49: Publicidad pagada | K49: Paraiso de Santa Maria
A50: 46267 | B50: 27441586 | C50: andycerpa20 | E50: Alfredo Caceda | F50: seguimiento | H50: 0 | J50: Publicidad pagada | K50: Paraiso de Santa Maria
A51: 46267 | B51: 27441178 | C51: Mary Arevalo | D51: +51973704543 | E51: Alfredo Caceda | F51: AGENDO VISITA al proyecto | H51: 0 | J51: Publicidad pagada | K51: Paraiso de Santa Maria
A52: 46267 | B52: 27440046 | C52: Liliana | D52: +51988436172 | E52: Jhovana Valdez | F52: NO CONTESTA - por confirmar | H52: 0 | J52: Publicidad pagada | K52: Paraiso de Santa Maria
A53: 46266 | B53: 27438356 | C53: Ronaldo | D53: +51916307964 | E53: Alfredo Caceda | F53: seguimiento | H53: 0 | J53: Publicidad pagada | K53: Paraiso de Santa Maria
A54: 46266 | B54: 27437318 | C54: marinaportilla336 | D54: +51980595168 | E54: Jhovana Valdez | F54: NO CONTESTA - por confirmar | H54: 0 | J54: Publicidad pagada | K54: Paraiso de Santa Maria
A55: 46266 | B55: 27436154 | C55: GBP & A3 GROUP | D55: +16056056259 | E55: JOSUE VICENTE | F55: NO CONTESTA 3V | H55: 0 | J55: Publicidad pagada | K55: Paraiso de Santa Maria
A56: 46266 | B56: 27435856 | C56: Sonia Canales | D56: +51924395991 | E56: Alfredo Caceda | F56: seguimiento | H56: 0 | J56: Publicidad pagada | K56: Paraiso de Santa Maria
A57: 46266 | B57: 27431546 | C57: Chandru | D57: +51981511949 | E57: Jhovana Valdez | F57: AGENDO VISITA al proyecto | H57: 0 | J57: Publicidad pagada | K57: Paraiso de Santa Maria
A58: 46266 | B58: 27430866 | C58: ® S A N C H E Z | D58: +51987856879 | E58: JOSUE VICENTE | F58: NO CONTESTA 3V | H58: 0 | J58: Publicidad pagada | K58: Paraiso de Santa Maria
A59: 46266 | B59: 27424636 | C59: Roxana | D59: +51953126887 | E59: Jhovana Valdez | F59: NO CONTESTA - por confirmar | H59: 0 | J59: Publicidad pagada | K59: Paraiso de Santa Maria
A60: 46266 | B60: 27424576 | C60: Jose carlos☺️ | D60: +51970550928 | E60: JOSUE VICENTE | F60: NO CONTESTA - por confirmar | H60: 0 | J60: Publicidad pagada | K60: Paraiso de Santa Maria
A61: 46266 | B61: 27424436 | C61: Rouss | D61: +51980627507 | E61: Alfredo Caceda | F61: AGENDO VISITA al proyecto | H61: 0 | J61: Publicidad pagada | K61: Paraiso de Santa Maria
A62: 46265 | B62: 27423390 | C62: Verouska Atkins | D62: +51958229338 | E62: Jhovana Valdez | F62: INTERESADo | H62: 0 | J62: Publicidad pagada | K62: Paraiso de Santa Maria
A63: 46265 | B63: 27423334 | D63: +51931478715 | E63: Alfredo Caceda | F63: INTERESADo | H63: 0 | J63: Publicidad pagada | K63: Paraiso de Santa Maria
A64: 46265 | B64: 27422088 | C64: ALP REPUESTOS | D64: +51944732917 | E64: Jhovana Valdez | F64: NO CONTESTA - por confirmar | H64: 0 | J64: Publicidad pagada | K64: Paraiso de Santa Maria
A65: 46265 | B65: 27421904 | C65: Frank | D65: +51966793237 | E65: JOSUE VICENTE | F65: AGENDO VISITA al proyecto | H65: 0 | J65: Publicidad pagada | K65: Paraiso de Santa Maria
A66: 46265 | B66: 27421902 | C66: ef6558865 | D66: +51923477403 | E66: Alfredo Caceda | F66: INTERESADo | H66: 0 | J66: Publicidad pagada | K66: Paraiso de Santa Maria
A67: 46265 | B67: 27421688 | C67: David | D67: +51981289933 | E67: Jhovana Valdez | F67: INTERESADo | H67: 0 | J67: Publicidad pagada | K67: Paraiso de Santa Maria
A68: 46265 | B68: 27421320 | C68: magalygina27 | D68: +51908679576 | E68: JOSUE VICENTE | F68: NO CONTESTA - por confirmar | H68: 0 | J68: Publicidad pagada | K68: Paraiso de Santa Maria
A69: 46265 | B69: 27420684 | C69: AlexandraFernandez04 | E69: Jhovana Valdez | F69: NO CONTESTA - por confirmar | H69: 0 | J69: Publicidad pagada | K69: Paraiso de Santa Maria
A70: 46265 | B70: 27420334 | C70: Cindy Ajalcriña | D70: +51952525162 | E70: Ingrid Villegas | F70: NO CONTESTA - por confirmar | H70: 0 | J70: Publicidad pagada | K70: Paraiso de Santa Maria
A71: 46265 | B71: 27418510 | C71: Miguel Angel | D71: +51987158544 | E71: JOSUE VICENTE | F71: NO CONTESTA 3V | H71: 0 | J71: Publicidad pagada | K71: Paraiso de Santa Maria
A72: 46265 | B72: 27418320 | D72: +51906650721 | E72: Jhovana Valdez | F72: NO CONTESTA - por confirmar | H72: 0 | J72: Publicidad pagada | K72: Paraiso de Santa Maria
A73: 46265 | B73: 27418202 | C73: Soledad | D73: +51912499294 | E73: Alfredo Caceda | F73: seguimiento | H73: 0 | J73: Publicidad pagada | K73: Paraiso de Santa Maria
A74: 46265 | B74: 27418090 | C74: Chmb..⚽❤️ | D74: +51987901953 | E74: Jhovana Valdez | F74: NO CONTESTA - por confirmar | H74: 0 | J74: Publicidad pagada | K74: Paraiso de Santa Maria
A75: 46265 | B75: 27417760 | C75: JR-EVENTOS | D75: +51945926827 | E75: Ingrid Villegas | F75: NO CONTESTA - por confirmar | H75: 0 | J75: Publicidad pagada | K75: Paraiso de Santa Maria
A76: 46265 | B76: 27412182 | C76: jamescollantes | D76: +51952243230 | E76: Alfredo Caceda | F76: INTERESADo | H76: 0 | J76: Publicidad pagada | K76: Paraiso de Santa Maria
A77: 46265 | B77: 27412126 | C77: Jvanito | D77: +51997836587 | E77: Jhovana Valdez | F77: NO CONTESTA - por confirmar | H77: 0 | J77: Publicidad pagada | K77: Paraiso de Santa Maria
A78: 46265 | B78: 27411906 | C78: Luz Igual conocimiento | D78: +51980695761 | E78: Alfredo Caceda | F78: INTERESADo | H78: 0 | J78: Publicidad pagada | K78: Paraiso de Santa Maria
A79: 46265 | B79: 27411692 | C79: distribuidor autorizado | D79: +51982868839 | E79: Jhovana Valdez | F79: NO CONTESTA - por confirmar | H79: 0 | J79: Publicidad pagada | K79: Paraiso de Santa Maria
A80: 46265 | B80: 27410686 | C80: radioorooficial | D80: +51991367423 | E80: Ingrid Villegas | F80: NO CONTESTA - por confirmar | H80: 0 | J80: Publicidad pagada | K80: Paraiso de Santa Maria
A81: 46265 | B81: 27410658 | C81: Luis Nicho | D81: +51914035699 | E81: Alfredo Caceda | F81: seguimiento | H81: 0 | J81: Publicidad pagada | K81: Paraiso de Santa Maria
A82: 46265 | B82: 27410086 | C82: Felipe | D82: +51994499821 | E82: Jhovana Valdez | F82: seguimiento | H82: 0 | J82: Publicidad pagada | K82: Paraiso de Santa Maria
A83: 46265 | B83: 27409984 | C83: JOSE RONDOY | D83: +51917989993 | E83: Alfredo Caceda | F83: seguimiento | H83: 0 | J83: Publicidad pagada | K83: Paraiso de Santa Maria
A84: 46265 | B84: 27408494 | C84: David | D84: +51960650896 | E84: Jhovana Valdez | F84: NO CONTESTA - por confirmar | H84: 0 | J84: Publicidad pagada | K84: Paraiso de Santa Maria
A85: 46264 | B85: 27408002 | D85: +51918730846 | E85: Alfredo Caceda | F85: INTERESADo | H85: 0 | J85: Publicidad pagada | K85: Paraiso de Santa Maria
A86: 46264 | B86: 27407780 | C86: Mari Espinoza | D86: +51997142131 | E86: Alfredo Caceda | F86: seguimiento | H86: 0 | J86: Publicidad pagada | K86: Paraiso de Santa Maria
A87: 46264 | B87: 27407326 | C87: Olinda | D87: +51986782240 | E87: Jhovana Valdez | F87: NO CONTESTA - por confirmar | H87: 0 | J87: Publicidad pagada | K87: Paraiso de Santa Maria
A88: 46264 | B88: 27406908 | C88: ⚠️ | D88: +51994274134 | E88: Alfredo Caceda | F88: seguimiento | H88: 0 | J88: Publicidad pagada | K88: Paraiso de Santa Maria
A89: 46264 | B89: 27405910 | C89: CONCESIONARIO A & E | D89: +51907735224 | E89: Jhovana Valdez | F89: NO CONTESTA - por confirmar | H89: 0 | J89: Publicidad pagada | K89: Paraiso de Santa Maria
A90: 46264 | B90: 27405800 | C90: tu gato | D90: +51925276331 | E90: Alfredo Caceda | F90: INTERESADo | H90: 0 | J90: Publicidad pagada | K90: Paraiso de Santa Maria
A91: 46264 | B91: 27405288 | C91: . | D91: +51982176415 | E91: Alfredo Caceda | F91: seguimiento | H91: 0 | J91: Publicidad pagada | K91: Paraiso de Santa Maria
A92: 46264 | B92: 27404670 | C92: ant | D92: +51957693482 | E92: Jhovana Valdez | F92: NO CONTESTA - por confirmar | H92: 0 | J92: Publicidad pagada | K92: Paraiso de Santa Maria
A93: 46264 | B93: 27403888 | D93: +51980825565 | E93: Alfredo Caceda | F93: seguimiento | H93: 0 | J93: Publicidad pagada | K93: Paraiso de Santa Maria
A94: 46264 | B94: 27403816 | C94: Marta Roca | D94: +51928339025 | E94: Jhovana Valdez | F94: NO CONTESTA - por confirmar | H94: 0 | J94: Publicidad pagada | K94: Paraiso de Santa Maria
A95: 46264 | B95: 27403676 | C95: JeanR_Ventas03 | E95: Alfredo Caceda | F95: INTERESADo | H95: 0 | J95: Publicidad pagada | K95: Paraiso de Santa Maria
A96: 46264 | B96: 27403446 | C96: Honorio | D96: +51961095411 | E96: Alfredo Caceda | F96: seguimiento | H96: 0 | J96: Publicidad pagada | K96: Paraiso de Santa Maria
A97: 46264 | B97: 27403310 | C97: Benny | D97: +51976836819 | E97: Jhovana Valdez | F97: NO CONTESTA - por confirmar | H97: 0 | J97: Publicidad pagada | K97: Paraiso de Santa Maria
A98: 46264 | B98: 27403074 | C98: Vilma García Caldas | D98: +51943046560 | E98: Alfredo Caceda | F98: INTERESADo | H98: 0 | J98: Publicidad pagada | K98: Paraiso de Santa Maria
A99: 46264 | B99: 27402990 | D99: +51935812338 | E99: Jhovana Valdez | F99: NO CONTESTA - por confirmar | H99: 0 | J99: Publicidad pagada | K99: Paraiso de Santa Maria
A100: 46263 | B100: 27402270 | C100: clavijocarmen581 | D100: +51980588207 | E100: JOSUE VICENTE | F100: NO CONTESTA - por confirmar | H100: 0 | J100: Publicidad pagada | K100: Paraiso de Santa Maria
A101: 46263 | B101: 27401686 | C101: Yoli | D101: +51986891695 | E101: Alfredo Caceda | F101: respondieron LLAMADA/ WHATSAPP | H101: 0 | J101: Publicidad pagada | K101: Paraiso de Santa Maria
A102: 46263 | B102: 27401222 | D102: +51971230640 | E102: Jhovana Valdez | F102: NO CONTESTA - por confirmar | H102: 0 | J102: Publicidad pagada | K102: Paraiso de Santa Maria
A103: 46263 | B103: 27400904 | C103: Víct_Chz | D103: +51951607931 | E103: JOSUE VICENTE | F103: REALIZAR INVITACION | H103: 0 | J103: Publicidad pagada | K103: Paraiso de Santa Maria
A104: 46263 | B104: 27400874 | C104: Paolo Cesar⚽️ | D104: +51925984169 | E104: Jhovana Valdez | F104: NO CONTESTA - por confirmar | H104: 0 | J104: Publicidad pagada | K104: Paraiso de Santa Maria
A105: 46263 | B105: 27400600 | C105: José | D105: +51938343522 | E105: JOSUE VICENTE | F105: AGENDO VISITA al proyecto | H105: 0 | J105: Publicidad pagada | K105: Paraiso de Santa Maria
A106: 46263 | B106: 27400060 | C106: Juan | D106: +51916922640 | E106: Alfredo Caceda | F106: INTERESADo | H106: 0 | J106: Publicidad pagada | K106: Paraiso de Santa Maria
A107: 46263 | B107: 27399760 | C107: … | D107: +51987981129 | E107: Jhovana Valdez | F107: NO CONTESTA - por confirmar | H107: 0 | J107: Publicidad pagada | K107: Paraiso de Santa Maria
A108: 46263 | B108: 27399702 | C108: Janet | D108: +51982906151 | E108: JOSUE VICENTE | F108: REALIZAR INVITACION | H108: 0 | J108: Publicidad pagada | K108: Paraiso de Santa Maria
A109: 46263 | B109: 27399658 | C109: Catalina Santana | D109: +51933454577 | E109: Jhovana Valdez | F109: NO CONTESTA - por confirmar | H109: 0 | J109: Publicidad pagada | K109: Paraiso de Santa Maria
A110: 46263 | B110: 27399000 | C110: Bertha | D110: +51920497554 | E110: JOSUE VICENTE | F110: REALIZAR INVITACION | H110: 0 | J110: Publicidad pagada | K110: Paraiso de Santa Maria
A111: 46263 | B111: 27398662 | C111: Lucianita | D111: +51923866535 | E111: Jhovana Valdez | F111: AGENDO VISITA al proyecto | H111: 0 | J111: Publicidad pagada | K111: Paraiso de Santa Maria
A112: 46263 | B112: 27397674 | C112: jaime Espino | D112: +51999112572 | E112: JOSUE VICENTE | F112: REALIZAR INVITACION | H112: 0 | J112: Publicidad pagada | K112: Paraiso de Santa Maria
...

Sheet Inventario
A1: INVENTARIO COMERCIAL — ABSORCIÓN, AGING, HEATMAP Y PRICING
A3: Lote | B3: Manzana | C3: Etapa | D3: m2 | E3: Precio lista | F3: Precio actual | G3: Estado | H3: Fecha liberación | I3: Fecha venta | J3: Días disponible | K3: Aging | L3: N° visitas | M3: N° cotizaciones | N3: Demanda | O3: Próximo precio | P3: Trigger precio
A4: L-001 | B4: M-01 | C4: Etapa 1 | D4: 130 | E4: 52500 | F4: 52500 | G4: Vendido | H4: 45931 | I4: 46266 | J4: 335d | K4: >90 | L4: 3 | M4: 2 | N4: Baja | O4: 55125 | P4: Cada 20 lotes vendidos
A5: L-002 | B5: M-01 | C5: Etapa 1 | D5: 140 | E5: 55000 | F5: 55000 | G5: Vendido | H5: 45931 | I5: 46267 | J5: 336d | K5: >90 | L5: 6 | M5: 4 | N5: Media | O5: 57750 | P5: Cada 20 lotes vendidos
A6: L-003 | B6: M-01 | C6: Etapa 1 | D6: 150 | E6: 57500 | F6: 57500 | G6: Vendido | H6: 45931 | I6: 46268 | J6: 337d | K6: >90 | L6: 9 | M6: 0 | N6: Alta | O6: 60375 | P6: Cada 20 lotes vendidos
A7: L-004 | B7: M-01 | C7: Etapa 1 | D7: 120 | E7: 60000 | F7: 60000 | G7: Vendido | H7: 45931 | I7: 46269 | J7: 338d | K7: >90 | L7: 0 | M7: 2 | N7: Baja | O7: 63000 | P7: Cada 20 lotes vendidos
A8: L-005 | B8: M-01 | C8: Etapa 1 | D8: 130 | E8: 62500 | F8: 62500 | G8: Vendido | H8: 45931 | I8: 46270 | J8: 339d | K8: >90 | L8: 3 | M8: 4 | N8: Baja | O8: 65625 | P8: Cada 20 lotes vendidos
A9: L-006 | B9: M-01 | C9: Etapa 1 | D9: 140 | E9: 65000 | F9: 65000 | G9: Vendido | H9: 45931 | I9: 46271 | J9: 340d | K9: >90 | L9: 6 | M9: 0 | N9: Media | O9: 68250 | P9: Cada 20 lotes vendidos
A10: L-007 | B10: M-01 | C10: Etapa 1 | D10: 150 | E10: 50000 | F10: 50000 | G10: Vendido | H10: 45931 | I10: 46272 | J10: 341d | K10: >90 | L10: 9 | M10: 2 | N10: Alta | O10: 52500 | P10: Cada 20 lotes vendidos
A11: L-008 | B11: M-01 | C11: Etapa 1 | D11: 120 | E11: 52500 | F11: 52500 | G11: Vendido | H11: 45931 | I11: 46273 | J11: 342d | K11: >90 | L11: 0 | M11: 4 | N11: Baja | O11: 55125 | P11: Cada 20 lotes vendidos
A12: L-009 | B12: M-01 | C12: Etapa 1 | D12: 130 | E12: 55000 | F12: 55000 | G12: Vendido | H12: 45931 | I12: 46274 | J12: 343d | K12: >90 | L12: 3 | M12: 0 | N12: Baja | O12: 57750 | P12: Cada 20 lotes vendidos
A13: L-010 | B13: M-01 | C13: Etapa 1 | D13: 140 | E13: 57500 | F13: 57500 | G13: Vendido | H13: 45931 | I13: 46275 | J13: 344d | K13: >90 | L13: 6 | M13: 2 | N13: Media | O13: 60375 | P13: Cada 20 lotes vendidos
A14: L-011 | B14: M-02 | C14: Etapa 1 | D14: 150 | E14: 60000 | F14: 60000 | G14: Vendido | H14: 45931 | I14: 46276 | J14: 345d | K14: >90 | L14: 9 | M14: 4 | N14: Alta | O14: 63000 | P14: Cada 20 lotes vendidos
A15: L-012 | B15: M-02 | C15: Etapa 1 | D15: 120 | E15: 62500 | F15: 62500 | G15: Disponible | H15: 45931 | J15: 345d | K15: >90 | L15: 0 | M15: 0 | N15: Baja | O15: 65625 | P15: Cada 20 lotes vendidos
A16: L-013 | B16: M-02 | C16: Etapa 1 | D16: 130 | E16: 65000 | F16: 65000 | G16: Disponible | H16: 45931 | J16: 345d | K16: >90 | L16: 3 | M16: 2 | N16: Baja | O16: 68250 | P16: Cada 20 lotes vendidos
A17: L-014 | B17: M-02 | C17: Etapa 1 | D17: 140 | E17: 50000 | F17: 50000 | G17: Disponible | H17: 45931 | J17: 345d | K17: >90 | L17: 6 | M17: 4 | N17: Media | O17: 52500 | P17: Cada 20 lotes vendidos
A18: L-015 | B18: M-02 | C18: Etapa 1 | D18: 150 | E18: 52500 | F18: 52500 | G18: Disponible | H18: 45931 | J18: 345d | K18: >90 | L18: 9 | M18: 0 | N18: Alta | O18: 55125 | P18: Cada 20 lotes vendidos
A19: L-016 | B19: M-02 | C19: Etapa 1 | D19: 120 | E19: 55000 | F19: 55000 | G19: Disponible | H19: 45931 | J19: 345d | K19: >90 | L19: 0 | M19: 2 | N19: Baja | O19: 57750 | P19: Cada 20 lotes vendidos
A20: L-017 | B20: M-02 | C20: Etapa 1 | D20: 130 | E20: 57500 | F20: 57500 | G20: Disponible | H20: 45931 | J20: 345d | K20: >90 | L20: 3 | M20: 4 | N20: Baja | O20: 60375 | P20: Cada 20 lotes vendidos
A21: L-018 | B21: M-02 | C21: Etapa 1 | D21: 140 | E21: 60000 | F21: 60000 | G21: Disponible | H21: 45931 | J21: 345d | K21: >90 | L21: 6 | M21: 0 | N21: Media | O21: 63000 | P21: Cada 20 lotes vendidos
A22: L-019 | B22: M-02 | C22: Etapa 1 | D22: 150 | E22: 62500 | F22: 62500 | G22: Disponible | H22: 45931 | J22: 345d | K22: >90 | L22: 9 | M22: 2 | N22: Alta | O22: 65625 | P22: Cada 20 lotes vendidos
A23: L-020 | B23: M-02 | C23: Etapa 1 | D23: 120 | E23: 65000 | F23: 65000 | G23: Disponible | H23: 45931 | J23: 345d | K23: >90 | L23: 0 | M23: 4 | N23: Baja | O23: 68250 | P23: Cada 20 lotes vendidos
A24: L-021 | B24: M-03 | C24: Etapa 1 | D24: 130 | E24: 50000 | F24: 50000 | G24: Disponible | H24: 45931 | J24: 345d | K24: >90 | L24: 3 | M24: 0 | N24: Baja | O24: 52500 | P24: Cada 20 lotes vendidos
A25: L-022 | B25: M-03 | C25: Etapa 1 | D25: 140 | E25: 52500 | F25: 52500 | G25: Disponible | H25: 45931 | J25: 345d | K25: >90 | L25: 6 | M25: 2 | N25: Media | O25: 55125 | P25: Cada 20 lotes vendidos
A26: L-023 | B26: M-03 | C26: Etapa 1 | D26: 150 | E26: 55000 | F26: 55000 | G26: Disponible | H26: 45931 | J26: 345d | K26: >90 | L26: 9 | M26: 4 | N26: Alta | O26: 57750 | P26: Cada 20 lotes vendidos
... A184: L-181 | B184: M-19 | C184: Etapa 2 | D184: 130 | E184: 65000 | F184: 65000 | G184: Disponible | H184: 46023 | J184: 253d | K184: >90 | L184: 3 | M184: 2 | N184: Baja | O184: 68250 | P184: Cada 20 lotes vendidos

Sheet Configuracion
A1: CONFIGURACIÓN COMERCIAL
A3: NOTAS IMPORTANTES
A4: 1 | B4: La regla comercial 3:1 equivale a 33.3% de conversión de visita a separación.
A5: 2 | B5: Cambia vendedores, metas y conversiones aquí; el resto del archivo se actualiza automáticamente.
A6: 3 | B6: Para usar data real, reemplaza las filas de ejemplo en Data_KOMMO sin cambiar los encabezados.
A8: Inicio la venta | B8: 45931
A10: Parámetro | B10: Valor | E10: Fuentes estándar | F10: Uso
A11: Conversión Lead → Agendado | B11: 0.2 | E11: Publicidad pagada | F11: Meta Ads / TikTok Ads / Google Ads
A12: Asistencia Agendado → Visita | B12: 0.6 | E12: Referido | F12: Referidos de clientes o contactos
A13: Conversión Visita → Separación | B13: 0.33333333 | E13: Activación | F13: Campo, volanteo, módulos, activaciones
A14: Conversión Separación → Venta | B14: 0.8 | E14: Orgánico | F14: Redes sociales sin pauta
A15: Ticket promedio de venta (S/) | B15: 40000 | E15: Base de datos | F15: Reactivación / cartera
A16: Meta de ventas mensual | B16: 10 | E16: Redes Sociales
A17: Semanas operativas por mes | B17: 4.33 | E17: tiktok
A19: KPI adicionales de ventas | B19: Valor | E19: Estado CRM
A20: Cash-in mínimo % | B20: 0.35 | E20: REALIZAR INVITACION
A21: inicial promedio minimo % | B21: 0.2 | E21: NO CONTESTA - por confirmar
A22: Descuento máximo % | B22: 0.04 | E22: No asistio
A23: Cancelaciones maximo % | B23: 0.05 | E23: Presentación Zoom
A24: Meta de consolidacion % | B24: 0.95 | E24: Visitó proyecto
E25: En Cotizacion
E26: Listo para Comprar
E27: Separado | I27: REALIZAR INVITACION
E28: Venta | I28: NO CONTESTA - por confirmar
E29: Venta Perdida | I29: respondieron LLAMADA/ WHATSAPP
I30: INTERESADo
E31: Tipo de compra | I31: seguimiento
E32: Financiado | I32: agendo oficina /presentación virtual
E33: Contado | I33: AGENDO VISITA al proyecto
I34: ASISTIO al PROYECTO
I35: LISTO PARA COMPRAR
I36: Separo lote
I37: Lote vendido
I38: NO CONTESTA 3V

Sheet diccionario
A1: DICCIONARIO DE KPIs DEL CSO — QUÉ MIDE, FÓRMULA, FRECUENCIA Y ACCIÓN
A3: Bloque | B3: KPI | C3: Qué responde | D3: Fórmula conceptual | E3: Frecuencia | F3: Dueño / apoyo | G3: Acción si se desvía
A4: Resultado | B4: Ventas S/ | C4: ¿Cuánto vendimos? | D4: SUMA precio de venta activo | E4: Diario | F4: CSO | G4: Plan de cierre / acelerar pipeline
A5: Resultado | B5: Ventas netas S/ | C5: ¿Cuánto quedó después de cancelaciones? | D5: Ventas activas consolidadas | E5: Semanal | F5: CSO | G5: Reducir caídas
A6: Resultado | B6: Unidades vendidas | C6: ¿Cuántos lotes? | D6: COUNT ventas activas | E6: Diario | F6: CSO | G6: Activar motores de venta
A7: Resultado | B7: % cumplimiento meta | C7: ¿Vamos sobre la meta? | D7: Venta real / meta | E7: Diario | F7: CSO | G7: Cerrar gap
A8: Resultado | B8: Forecast cierre | C8: ¿Dónde cerraremos? | D8: Venta real + pipeline ponderado | E8: Semanal | F8: CSO | G8: Replanificar
A9: Predictivo | B9: Bolsa cotizaciones | C9: ¿Cuánto hay cotizado? | D9: SUM oportunidades abiertas | E9: Diario | F9: CSO | G9: Generar cotizaciones
A10: Predictivo | B10: Pipeline ponderado | C10: ¿Cuánto probablemente cierre? | D10: SUM cotización × probabilidad | E10: Diario | F10: CSO | G10: Madurar oportunidades
A11: Predictivo | B11: Cobertura pipeline | C11: ¿Pipeline cubre el gap? | D11: Pipeline ponderado / gap pendiente | E11: Semanal | F11: CSO | G11: Subir cobertura
A12: Predictivo | B12: Forecast accuracy | C12: ¿El CSO predice bien? | D12: 1-|forecast-real|/real | E12: Mensual | F12: CSO/CIO | G12: Calibrar probabilidades
A13: Calidad | B13: Cash-in S/ | C13: ¿Cuánto dinero entra por ventas nuevas? | D13: Contado + iniciales cobradas | E13: Diario | F13: CSO/CFO | G13: Subir inicial / contado
A14: Calidad | B14: Cash-in % | C14: ¿Qué % de venta se convierte en caja? | D14: Cash-in / venta | E14: Semanal | F14: CSO/CFO | G14: Cambiar mix/condiciones
... A54: Riesgo | B54: Concentración comercial | C54: ¿Dependemos de pocos asesores/canales? | D54: % ventas top 1/top 3 asesor o canal | E54: Mensual | F54: CSO | G54: Diversificar capacidad

Sheet Hoja 3
B2: Exactamente. Antes de crear el dashboard, necesitamos definir el “contrato de resultados” entre tú, como CEO, y cada C-Level.
B4: La lógica que usaría es esta:
B6: El CEO no dirige tareas. Dirige resultados, prioridades, recursos, límites y decisiones.
B8: Cada responsable debería tener claro cinco cosas:
B10: 1. Qué resultado final espero de ti.
B11: 2. Cómo voy a medirlo.
B12: 3. Qué indicadores me anticipan si vas a lograrlo.
B13: 4. Qué riesgos debes controlar.
B14: 5. Qué necesitas recibir del CEO para poder cumplir.
B16: Voy a asumir, como veníamos trabajando, CCO = Chief Customer Officer y CSIO = Chief Strategy & Innovation Officer.
B18: 1. La arquitectura completa
B20: Tu empresa podría verse así:
... B69: Tus grandes indicadores deberían ser:
B71: KPI CEO | C71: Pregunta que responde
B72: Ventas | C72: ¿Estamos creciendo?
B73: Ventas netas | C73: ¿Las ventas realmente se consolidan?
B74: Cobranza | C74: ¿La venta se convierte en dinero?
B75: Margen bruto | C75: ¿El negocio inmobiliario es rentable?
B76: EBITDA | C76: ¿La operación genera beneficio?
B77: Utilidad neta | C77: ¿Cuánto termina ganando la empresa?
B78: Caja | C78: ¿Tenemos liquidez?
B79: Forecast de caja | C79: ¿Tendremos liquidez?
B80: Inventario | C80: ¿Cuánto capital tenemos inmovilizado?
B81: Velocidad de venta | C81: ¿Qué tan rápido monetizamos inventario?
B82: ROIC / retorno sobre capital | C82: ¿Estamos utilizando bien nuestro capital?
... B85: Forecast utilidad | C85: ¿Cuánto vamos a ganar?
B87: Pero tú no produces directamente esos números.
B89: Tus C-Level los producen.
B91: 3. CSO — CHIEF SALES OFFICER
B92: ¿Qué compras tú del CSO?
B93: Ventas rentables, predecibles y sostenibles.
B95: No quieres simplemente vendedores ocupados.
B97: Quieres conversión.
B99: KPI de resultado
B100: KPI | C100: Qué debes observar
B101: Ventas S/ | C101: Meta vs real
B102: Ventas netas | C102: Descontando anulaciones
B103: Unidades | C103: Cantidad vendida
B104: Ticket promedio | C104: S/ por operación
B105: % cumplimiento meta | C105: Resultado
B106: Forecast cierre | C106: Dónde terminará el mes
B107: Separaciones | C107: Ventas potenciales
B108: Cancelaciones | C108: Calidad de ventas
B109: Velocidad de venta | C109: Inventario vendido/periodo
B110: Indicadores predictivos
B112: Estos son incluso más importantes semanalmente:
B114: contactos efectivos;
B115: citas;
B116: presentaciones;
B117: visitas;
B118: propuestas;
B119: separaciones;
B120: pipeline;
B121: cobertura de pipeline;
B122: conversión por etapa;
B123: productividad por asesor;
... B162: KPI de resultado
B163: KPI | C163: Qué significa
B164: Leads calificados | C164: Demanda útil
B165: CAC | C165: Costo por comprador
B166: Pipeline generado | C166: Dinero potencial originado por marketing
B167: Ventas atribuidas | C167: Ventas originadas por marketing
B168: Facturación atribuida | C168: S/ generados
B169: Margen atribuible | C169: Rentabilidad real
B170: ROAS / ROMI | C170: Retorno
B171: CPL calificado | C171: Eficiencia
B172: Predictivos
B173: CTR;
B174: tasa landing;
B175: CPL;
B176: tasa de lead calificado;
B177: citas generadas;
B178: costo por cita;
B179: costo por visita;
B180: calidad por canal;
B181: frecuencia;
B182: saturación creativa;
B183: tiempo lead → contacto.
... B225: Ejemplo:
B227: Canal | C227: Leads | D227: Visitas | E227: Ventas | F227: CAC | G227: Ventas S/
B228: Meta | C228: 1000 | D228: 120 | E228: 30 | F228: S/900 | G228: S/2.4M
B229: TikTok | C229: 700 | D229: 45 | E229: 7 | F229: S/1,800 | G229: S/500K
B230: Referidos | C230: 100 | D230: 35 | E230: 15 | F230: S/300 | G230: S/1.1M
B232: Ahora puedes asignar capital racionalmente.
B234: 6. CFO — CHIEF FINANCIAL OFFICER
B235: ¿Qué compras del CFO?
B236: Rentabilidad + liquidez + control financiero.
B238: El CSO te puede hacer millonario en Excel y el CFO quebrarte en caja si las cosas no están ordenadas. | I238: Y para el CFO
B240: KPI principales | I240: El CFO debería tener una visión más profunda:
B241: KPI | C241: Qué observas
B242: Ingresos | C242: Reconocimiento financiero | I242: Presupuesto vs real por centro de costo por cada area
B243: Margen bruto | C243: Rentabilidad producto
B244: Margen operativo | C244: Rentabilidad operación | I244: Por ejemplo:
B245: EBITDA | C245: Salud operativa
B246: Utilidad neta | C246: Beneficio final | I246: Centro de costo | J246: Presupuesto | K246: Real | L246: Variación
B247: Caja disponible | C247: Liquidez actual | I247: CSO | J247: S/80K | K247: S/70K | L247: -S/10K
B248: Forecast 13 semanas | C248: Liquidez futura | I248: CMO | J248: S/40K | K248: S/45K | L248: =+S/5K -> #ERROR!
B249: Cobranza | C249: Conversión ventas → efectivo | I249: COO | J249: S/150K | K249: S/165K | L249: =+S/15K -> #ERROR!
B250: Morosidad | C250: Riesgo cartera | I250: CLO | J250: S/25K | K250: S/22K | L250: -S/3K
B251: Cuentas por pagar | C251: Obligaciones | I251: Administración | J251: S/60K | K251: S/58K | L251: -S/2K
...
